Workbook
Name _____CLK1: #REF!
Name ____CLK1: #REF!
Name ___CLK1: #REF!
Name ___rrr11: #REF!
Name ___sde098: #REF!
Name __CLK1: #REF!
Name __rrr11: #REF!
Name __sde098: #REF!
Name _0: #REF!
Name _04: #REF!
Name _1: #REF!
Name _10: #REF!
Name _11: #REF!
Name _111: #REF!
Name _115: #REF!
Name _12: #REF!
Name _13: #REF!
Name _14: #REF!
Name _15: #REF!
Name _16: #REF!
Name _17: #REF!
Name _2: #REF!
Name _200: #REF!
Name _201: #REF!
Name _202: #REF!
Name _203: #REF!
Name _204: #REF!
Name _205: #REF!
Name _206: #REF!
Name _207: #REF!
Name _208: #REF!
Name _209: #REF!
Name _210: #REF!
Name _211: #REF!
Name _212: #REF!
Name _213: #REF!
Name _214: #REF!
Name _215: #REF!
Name _216: #REF!
Name _217: #REF!
Name _218: #REF!
Name _219: #REF!
Name _220: #REF!
Name _221: #REF!
Name _222: #REF!
Name _223: #REF!
Name _224: #REF!
Name _225: #REF!
Name _226: #REF!
Name _227: #REF!
Name _228: #REF!
Name _229: #REF!
Name _230: #REF!
Name _231: #REF!
Name _232: #REF!
Name _233: #REF!
Name _234: #REF!
Name _235: #REF!
Name _236: #REF!
Name _237: #REF!

Sheet Title
E3: Project Name: | F3: Conceptual Trade-off Study for Radhikapur West
E5: Block Name: | F5: Radhikapur West
E7: Project No: | F7: IN1411
E9: Client: | F9: VEDANTA LIMITED
E11: Operations: | F11: Opencast Coal Mine
E13: Purpose: | F13: High level Economic Assessment
E15: Included Scenarios: | F15: Option 1- 15 Mtpa; Departmental/ MDO Operation; Coal - Surface Miner; Waste - Truck & Shovel
E17: File: | F17: =MID(CELL("filename",A1),FIND("[",CELL("filename",A1))+1,FIND("]", CELL("filename",A1))-FIND("[",CELL("filename",A1))-1) -> Option 3_15 Mtpa_rev1_smg opt2 quality.xlsx
E21: Project Manager: | F21: Mrinal Kanti Sarkar
E22: Economic Assessment by: | F22: Mrinal Kanti Sarkar; Aniket Banerjee
E23: Reviewer | F23: Somnath Gain; Sudipta De

Sheet Revision
B15: Revision History | C15: Name | D15: Date | E15: Scenario | F15: Comments
B16: 1 | C16: =Title!F17 -> Option 3_15 Mtpa_rev1_smg opt2 quality.xlsx | D16: 16.04.2026 | E16: Scenario 1 | F16: =VLOOKUP(E16,'Scenario Matrix'!$B$4:$F$20,5,FALSE) -> Option 1 - Base Case: Conventional pit progression from in-crop and movement towards dip side
B35: Scenario Matrix
B36: Scenario ID | C36: Mode of Operation | D36: Peak Rated Capacity (Mtpa) | E36: Mining Method | F36: Description
B38: Scenario 1 | C38: Departmental | D38: 15 | E38: Coal - Surface Miner. Waste - Drilling & Blasting | F38: Option 1 - Base Case: Conventional pit progression from in-crop and movement towards dip side | I38: Option 1 - Base Case: Conventional pit progression from in-crop and movement towards dip side
B39: Scenario 2 | C39: MDO/Outsourcing | D39: 15 | E39: Coal - Surface Miner. Waste - Drilling & Blasting | F39: Option 1 - Base Case: Conventional pit progression from in-crop and movement towards dip side | I39: Option 2 - Pit progression following optimizer guided push-backs
B40: Scenario 3 | C40: Departmental | D40: 15 | E40: Coal - Surface Miner. Waste - Drilling & Blasting | F40: Option 2 - Pit progression following optimizer guided push-backs | I40: Option 3 - Two pit strategy; following Grade Distribution of deciding Seam IX – balancing low grade and comparatively high grade
B41: Scenario 4 | C41: MDO/Outsourcing | D41: 15 | E41: Coal - Surface Miner. Waste - Drilling & Blasting | F41: Option 2 - Pit progression following optimizer guided push-backs | I41: Sub variant of Option 2 - Modified for MDO Tender as requested by Vedanta
B42: Scenario 5 | C42: Departmental | D42: 15 | E42: Coal - Surface Miner. Waste - Drilling & Blasting | F42: Option 3 - Two pit strategy; following Grade Distribution of deciding Seam IX – balancing low grade and comparatively high grade
B43: Scenario 6 | C43: MDO/Outsourcing | D43: 15 | E43: Coal - Surface Miner. Waste - Drilling & Blasting | F43: Option 3 - Two pit strategy; following Grade Distribution of deciding Seam IX – balancing low grade and comparatively high grade
B44: Scenario 7 | C44: Departmental | D44: 20 | E44: Coal - Surface Miner. Waste - Drilling & Blasting | F44: Option 1 - Base Case: Conventional pit progression from in-crop and movement towards dip side
B45: Scenario 8 | C45: MDO/Outsourcing | D45: 20 | E45: Coal - Surface Miner. Waste - Drilling & Blasting | F45: Option 1 - Base Case: Conventional pit progression from in-crop and movement towards dip side
B46: Scenario 9 | C46: Departmental | D46: 20 | E46: Coal - Surface Miner. Waste - Drilling & Blasting | F46: Option 2 - Pit progression following optimizer guided push-backs
B47: Scenario 10 | C47: MDO/Outsourcing | D47: 20 | E47: Coal - Surface Miner. Waste - Drilling & Blasting | F47: Option 2 - Pit progression following optimizer guided push-backs
B48: Scenario 11 | C48: Departmental | D48: 20 | E48: Coal - Surface Miner. Waste - Drilling & Blasting | F48: Option 3 - Two pit strategy; following Grade Distribution of deciding Seam IX – balancing low grade and comparatively high grade
B49: Scenario 12 | C49: MDO/Outsourcing | D49: 20 | E49: Coal - Surface Miner. Waste - Drilling & Blasting | F49: Option 3 - Two pit strategy; following Grade Distribution of deciding Seam IX – balancing low grade and comparatively high grade
B50: Scenario 13 | C50: Departmental | D50: 10 | E50: Coal - Surface Miner. Waste - Drilling & Blasting | F50: Sub variant of Option 2 - Modified for MDO Tender as requested by Vedanta
B51: Scenario 14 | C51: MDO/Outsourcing | D51: 10 | E51: Coal - Surface Miner. Waste - Drilling & Blasting | F51: Sub variant of Option 2 - Modified for MDO Tender as requested by Vedanta
B52: Scenario 15 | C52: MDO/Outsourcing | D52: 15 | E52: Drilling & Blasting only | F52: Option 3 - Two pit strategy; following Grade Distribution of deciding Seam IX – balancing low grade and comparatively high grade
B53: Scenario 16 | C53: MDO/Outsourcing | D53: 15 | E53: Drilling & Blasting only | F53: Option 3 - Two pit strategy; following Grade Distribution of deciding Seam IX – balancing low grade and comparatively high grade

Sheet Scenario Matrix
B2: Scenario Matrix
B3: Scenario ID | C3: Mode of Operation | D3: Peak Rated Capacity (Mtpa) | E3: Mining Method | F3: Description
B4: 1 | C4: 2 | D4: 3 | E4: 4 | F4: 5
B5: Scenario 1 | C5: Departmental | D5: 15 | E5: Coal - Surface Miner. Waste - Drilling & Blasting | F5: Option 1 - Base Case: Conventional pit progression from in-crop and movement towards dip side | I5: Option 1 - Base Case: Conventional pit progression from in-crop and movement towards dip side
B6: Scenario 2 | C6: MDO/Outsourcing | D6: 15 | E6: Coal - Surface Miner. Waste - Drilling & Blasting | F6: Option 1 - Base Case: Conventional pit progression from in-crop and movement towards dip side | I6: Option 2 - Pit progression following optimizer guided push-backs
B7: Scenario 3 | C7: Departmental | D7: 15 | E7: Coal - Surface Miner. Waste - Drilling & Blasting | F7: Option 2 - Pit progression following optimizer guided push-backs | I7: Option 3 - Two pit strategy; following Grade Distribution of deciding Seam IX – balancing low grade and comparatively high grade
B8: Scenario 4 | C8: MDO/Outsourcing | D8: 15 | E8: Coal - Surface Miner. Waste - Drilling & Blasting | F8: Option 2 - Pit progression following optimizer guided push-backs | I8: Sub variant of Option 2 - Modified for MDO Tender as requested by Vedanta
B9: Scenario 5 | C9: Departmental | D9: 15 | E9: Coal - Surface Miner. Waste - Drilling & Blasting | F9: Option 3 - Two pit strategy; following Grade Distribution of deciding Seam IX – balancing low grade and comparatively high grade
B10: Scenario 6 | C10: MDO/Outsourcing | D10: 15 | E10: Coal - Surface Miner. Waste - Drilling & Blasting | F10: Option 3 - Two pit strategy; following Grade Distribution of deciding Seam IX – balancing low grade and comparatively high grade
B11: Scenario 7 | C11: Departmental | D11: 20 | E11: Coal - Surface Miner. Waste - Drilling & Blasting | F11: Option 1 - Base Case: Conventional pit progression from in-crop and movement towards dip side
B12: Scenario 8 | C12: MDO/Outsourcing | D12: 20 | E12: Coal - Surface Miner. Waste - Drilling & Blasting | F12: Option 1 - Base Case: Conventional pit progression from in-crop and movement towards dip side
B13: Scenario 9 | C13: Departmental | D13: 20 | E13: Coal - Surface Miner. Waste - Drilling & Blasting | F13: Option 2 - Pit progression following optimizer guided push-backs
B14: Scenario 10 | C14: MDO/Outsourcing | D14: 20 | E14: Coal - Surface Miner. Waste - Drilling & Blasting | F14: Option 2 - Pit progression following optimizer guided push-backs
B15: Scenario 11 | C15: Departmental | D15: 20 | E15: Coal - Surface Miner. Waste - Drilling & Blasting | F15: Option 3 - Two pit strategy; following Grade Distribution of deciding Seam IX – balancing low grade and comparatively high grade
B16: Scenario 12 | C16: MDO/Outsourcing | D16: 20 | E16: Coal - Surface Miner. Waste - Drilling & Blasting | F16: Option 3 - Two pit strategy; following Grade Distribution of deciding Seam IX – balancing low grade and comparatively high grade
B17: Scenario 13 | C17: Departmental | D17: 10 | E17: Coal - Surface Miner. Waste - Drilling & Blasting | F17: Sub variant of Option 2 - Modified for MDO Tender as requested by Vedanta
B18: Scenario 14 | C18: MDO/Outsourcing | D18: 10 | E18: Coal - Surface Miner. Waste - Drilling & Blasting | F18: Sub variant of Option 2 - Modified for MDO Tender as requested by Vedanta
B19: Scenario 15 | C19: MDO/Outsourcing | D19: 15 | E19: Drilling & Blasting only | F19: Option 3 - Two pit strategy; following Grade Distribution of deciding Seam IX – balancing low grade and comparatively high grade
B20: Scenario 16 | C20: MDO/Outsourcing | D20: 15 | E20: Drilling & Blasting only | F20: Option 3 - Two pit strategy; following Grade Distribution of deciding Seam IX – balancing low grade and comparatively high grade

Sheet Disclaimer
C2: Disclaimer & Notice to Reader
C5: The opinions expressed in this Report have been based on the information supplied to SRK Mining Services (India) Pvt. Ltd. (SRK) by Vedanta Limited. The opinions in this Report are provided in response to a specific request from Vedanta to do so. SRK has exercised all due care in reviewing the supplied information. Whilst SRK has compared key supplied data with expected values, the accuracy of the results and conclusions from the review are entirely reliant on the accuracy and completeness of the supplied data. SRK does not accept responsibility for any errors or omissions in the supplied information and does not accept any consequential liability arising from commercial decisions or actions resulting from them. Opinions presented in this report apply to the site conditions and features as they existed at the time of SRK’s investigations, and those reasonably foreseeable. These opinions do not necessarily apply to conditions and features that may arise after the date of this Report, about which SRK had no prior knowledge nor had the opportunity to evaluate. Opinions expressed in this document can significantly vary based on specific site conditions, project technicalities and engineering designs, decided through an appropriate technical works. If this document is disclosed or distributed to any third party, no such third party shall be entitled to place reliance upon any information, warranties or representations which may be contained within this document and the Recipients of this document shall indemnify SRK against all and any claims, losses and costs which may be incurred by SRK relating to such third parties There is a wide range of modifying factors – including increasingly important social and environmental impacts – that mining projects had to explore and mitigate before a mine’s viability could be fully assessed. Given the nature of the mandate, multiple best guess assumptions are taken, in most cases in consultation with the company, to assess impact which undoubtedly needs to be validated in future and through a full feasibility study before any production decisions are made.

Sheet Guide
C3: Description | D3: Status
B4: Tab Colors
B5: Yellow | C5: Title, Revision History, Disclaimer and Guide
B6: Purple | C6: Charts
B7: Red | C7: Summary
B8: Green | C8: Inputs/Quotes
B9: Blue | C9: Calculation Sheets (do not type in these tabs)
B10: Cell Colors
B11: Blue | C11: Links to another tab
B12: Red | C12: Hard Input
B13: Black | C13: Calculation using links from current tab
B14: Pink | C14: Links to external file
B15: Green | C15: Calculation using Named Values/Arrays
B16: Black | C16: Drop down Cell
B17: Grey | C17: Not required/No data

Sheet Assumptions_Dashboard
B2: Basic Considerations | K2: Coal Mining Machinery | L2: Surface Miner | M2: Surface Miner | P2: LOM Opex
B3: General considerations | C3: Unit | D3: Value | E3: Basis | L3: P-IRR | M3: Shovel & Dumper | P3: Sl No | Q3: List | R3: Unit | S3: Total
B4: Project Start Date | C4: date | D4: 45627 | E4: Standard Assumption based on Vesting Order | K4: Mining Operation | L4: Departmental | M4: MDO | P4: 1 | Q4: ='Project OPEX'!B13 -> MDO/ Contractor Cost | R4: ='Project OPEX'!C13 -> INR/t | S4: ='Project OPEX'!D13 -> 0
B5: Effective Start Date for Model | C5: date | D5: 46023 | M5: Departmental | Q5: Pit Head cost
B6: Production Start Date | C6: date | D6: 47119 | E6: Standard Assumption based on CMDPA | K6: Pre Tax & Pre Finance Basis | L6: Yes | P6: =P4+1 -> 2 | Q6: HEMM Consumable | R6: INR/t | S6: =SUM('Project OPEX'!D15:D18) -> 196.2501
B7: Production Starting Year | C7: No. | D7: 5 | P7: =P6+1 -> 3 | Q7: ='Project OPEX'!B19 -> CHP | R7: INR/t | S7: ='Project OPEX'!D19 -> 9.7551601
B8: Total Coal | C8: Mt | D8: ='Production Schedule'!D5 -> 225.70441 | E8: Estimated from Design | K8: Coal Price | L8: Commercial | P8: =P7+1 -> 4 | Q8: ='Project OPEX'!B20 -> Power | R8: INR/t | S8: ='Project OPEX'!D20 -> 10.001119
B9: Total Waste | C9: Mbcm | D9: ='Production Schedule'!D8 -> 535.39467 | E9: Estimated from Design | P9: =P8+1 -> 5 | Q9: ='Project OPEX'!B69 -> Owner Wage | R9: INR/t | S9: ='Project OPEX'!D23 -> 41.628474
B10: Rated Capacity | C10: Mtpa | D10: =MAX('Production Schedule'!E5:AM5) -> 15.000016 | E10: Mutual Discussion with Company | K10: Price co-relation factor (NCI to Commercial) | L10: 1.6 | P10: =P9+1 -> 6 | Q10: ='Project OPEX'!B70 -> Explosives | R10: INR/t | S10: ='Project OPEX'!D24 -> 56.413078
B11: Production in 1st year | C11: Mt | D11: ='Production Schedule'!I5 -> 1.9999998 | E11: Estimated from Design | P11: =P10+1 -> 7 | Q11: ='Project OPEX'!B71 -> Civil Infrastructure Maintenance | R11: INR/t | S11: ='Project OPEX'!D25 -> 4.019638
B12: Life of Mine | C12: Year | D12: =MAX('Production Schedule'!E3:AM3) -> 19 | E12: Estimated from Design | P12: =P11+1 -> 8 | Q12: ='Project OPEX'!B72 -> Railway Track & Siding Repair & Maintenance | R12: INR/t | S12: ='Project OPEX'!D26 -> 15.91019
B13: Block Area | C13: ha | D13: 1048 | E13: As per Tender | J13: Initial Capital Costs (Owner) | P13: =P12+1 -> 9 | Q13: ='Project OPEX'!B73 -> Fire Fighting & Dust Suppression | R13: INR/t | S13: ='Project OPEX'!D27 -> 0.4257449
B14: Working Regime | J14: Sl No | K14: List | L14: Unit | M14: Total | N14: % | P14: =P13+1 -> 10 | Q14: ='Project OPEX'!B74 -> Rehandling | R14: INR/t | S14: ='Project OPEX'!D28 -> 23.459001
B15: Description | C15: Units | D15: Values | E15: Basis | J15: 1 | K15: ='Owner CAPEX'!B11 -> Pre-operative costs | L15: INR Cr | M15: ='Owner CAPEX'!D11 -> 214.12704 | N15: =M15/$M$30 -> 0.044304252 | P15: =P14+1 -> 11 | Q15: ='Project OPEX'!B75 -> Digitalization (AMC) | R15: INR/t | S15: ='Project OPEX'!D29 -> 0.29463315
B16: Number of Shifts/day | C16: Nos. | D16: 3 | E16: Standard Assumption | J16: =J15+1 -> 2 | K16: ='Owner CAPEX'!B12 -> Upfront Amount | L16: INR Cr | M16: ='Owner CAPEX'!D12 -> 99.07 | N16: =M16/$M$30 -> 0.020498216 | P16: =P15+1 -> 12 | Q16: ='Project OPEX'!B76 -> Environment Management & OHS costs | R16: INR/t | S16: ='Project OPEX'!D30 -> 2.6937888
B17: Hours/ Shift | C17: hrs | D17: 8 | J17: =J16+1 -> 3 | K17: ='Owner CAPEX'!B13 -> Land Cost | L17: INR Cr | M17: ='Owner CAPEX'!D13 -> 985.07802 | N17: =M17/$M$30 -> 0.20381893 | P17: =P16+1 -> 13 | Q17: ='Project OPEX'!B77 -> Canteen, Accommodation, Laundry, Vehicle etc. Cost | R17: INR/t | S17: ='Project OPEX'!D31 -> 0.12344686
B18: Delays & Refreshment | C18: hrs | D18: 0 | E18: Considered in Utilization % | J18: =J17+1 -> 4 | K18: ='Owner CAPEX'!B14 -> R&R Cost | L18: INR Cr | M18: ='Owner CAPEX'!D14 -> 1048.57 | N18: =M18/$M$30 -> 0.21695584 | P18: =P17+1 -> 14 | Q18: ='Project OPEX'!B78 -> Admin and Overhead | R18: INR/t | S18: ='Project OPEX'!D32 -> 15
B19: Actual Hours/ Shift | C19: hrs | D19: =D17-D18 -> 8 | E19: Standard Assumption | J19: =J18+1 -> 5 | K19: ='Owner CAPEX'!B15 -> HEMM Equipment | L19: INR Cr | M19: ='Owner CAPEX'!D15 -> 701.51584 | N19: =M19/$M$30 -> 0.14514811 | P19: =P18+1 -> 15 | Q19: ='Project OPEX'!B79 -> R&R (Resettlement & Rehabilitation) | R19: INR/t | S19: ='Project OPEX'!D33 -> 3.2669141
B20: Calendar Days | C20: Days | D20: 365 | E20: Standard Assumption | J20: =J19+1 -> 6 | K20: ='Owner CAPEX'!B16 -> CHP | L20: INR Cr | M20: ='Owner CAPEX'!D16 -> 335.19 | N20: =M20/$M$30 -> 0.069352952 | P20: =P19+1 -> 16 | Q20: ='Project OPEX'!B80 -> Contingency | R20: INR/t | S20: ='Project OPEX'!D34 -> 56.886193
B21: National Holidays | C21: Days | D21: 8 | E21: Standard Assumption | J21: =J20+1 -> 7 | K21: ='Owner CAPEX'!B17 -> Railway Siding | L21: INR Cr | M21: ='Owner CAPEX'!D17 -> 540 | N21: =M21/$M$30 -> 0.11172945 | Q21: Subtotal | R21: INR/t | S21: =SUM(S6:S20) -> 436.12748
B22: Festival Impact | C22: Days | D22: =1+1 -> 2 | E22: Impacted attendence due to festival | J22: =J21+1 -> 8 | K22: ='Owner CAPEX'!B18 -> Civil Infrastructure | L22: INR Cr | M22: ='Owner CAPEX'!D18 -> 191 | N22: =M22/$M$30 -> 0.03951912 | Q22: Government Fees & Charges | R22: INR/t
B23: Available Days | C23: Days | D23: =D20-D21-D22 -> 355 | E23: Derived | J23: =J22+1 -> 9 | K23: ='Owner CAPEX'!B19 -> Fire Fighting & Dust Suppression | L23: INR Cr | M23: ='Owner CAPEX'!D19 -> 14.45 | N23: =M23/$M$30 -> 0.0029897973 | P23: =P20+1 -> 17 | Q23: ='Project OPEX'!B37 -> Revenue Sharing | R23: INR/t | S23: ='Project OPEX'!D37 -> 204.54301
B24: Extreme Summer Impact | C24: Days | D24: =(30*4)/24 -> 5 | E24: 30days of extreme heat consider with no work of 4 hours in day (11am to 3pm) | G24: =M30 -> 4833.1036 | I24: INR Cr | J24: =J23+1 -> 10 | K24: ='Owner CAPEX'!B20 -> Workshop and Store | L24: INR Cr | M24: ='Owner CAPEX'!D20 -> 27.27 | N24: =M24/$M$30 -> 0.0056423372 | P24: =P23+1 -> 18 | Q24: ='Project OPEX'!B38 -> GST on Revenue Sharing | R24: INR/t | S24: ='Project OPEX'!D38 -> 36.817742
B25: Number of Moonsoon Month having heavy rainfall | C25: Months | D25: 2 | E25: Standard Assumption | J25: =J24+1 -> 11 | K25: ='Owner CAPEX'!B21 -> Electrical | L25: INR Cr | M25: ='Owner CAPEX'!D21 -> 34.35 | N25: =M25/$M$30 -> 0.0071072344 | P25: =P24+1 -> 19 | Q25: ='Project OPEX'!B39 -> Royalty (% of NCI notified Price) | R25: INR/t | S25: ='Project OPEX'!D39 -> 139.28825
B26: Hours loss per day in Moonsoon Month | C26: hrs/day | D26: 8 | E26: Standard Assumption | J26: =J25+1 -> 12 | K26: ='Owner CAPEX'!B22 -> Mine Dewatering System | L26: INR Cr | M26: ='Owner CAPEX'!D22 -> 15 | N26: =M26/$M$30 -> 0.0031035958 | P26: =P25+1 -> 20 | Q26: ='Project OPEX'!B40 -> DMF (District Mineral Foundation) | R26: INR/t | S26: ='Project OPEX'!D40 -> 13.928825
B27: Days loss due to rain | C27: Days | D27: =((D25*30)*D26)/24 -> 20 | E27: Derived | J27: =J26+1 -> 13 | K27: ='Owner CAPEX'!B23 -> Digitalisation | L27: INR Cr | M27: ='Owner CAPEX'!D23 -> 10 | N27: =M27/$M$30 -> 0.0020690639 | P27: =P26+1 -> 21 | Q27: ='Project OPEX'!B41 -> NMET (National Mineral Exploration Trust) | R27: INR/t | S27: ='Project OPEX'!D41 -> 4.1786476
B28: Working days | C28: Days | D28: =D23-D24-D27 -> 330 | E28: Derived | J28: =J27+1 -> 14 | K28: ='Owner CAPEX'!B24 -> Contingency | L28: INR Cr | M28: ='Owner CAPEX'!D24 -> 617.48264 | N28: =M28/$M$30 -> 0.1277611 | P28: =P27+1 -> 22 | Q28: ='Project OPEX'!B42 -> Surface Rent | R28: INR/t | S28: ='Project OPEX'!D42 -> 0.17644317
B29: Total available Hours | C29: hrs | D29: =D28*D16*$D$19 -> 7920 | E29: Derived | J29: =J28+1 -> 15 | K29: ='Owner CAPEX'!B25 -> IDC | L29: INR Cr | M29: ='Owner CAPEX'!D25 -> 0 | N29: =M29/$M$30 -> 0 | P29: =P28+1 -> 23 | Q29: ='Project OPEX'!B43 -> GST on Royalty, DMF, NMET, etc | R29: INR/t | S29: ='Project OPEX'!D43 -> 28.362991
B30: Density & Swell Factor | K30: Total Initial Capital Expenditure | L30: INR Cr | M30: =SUM(M15:M29) -> 4833.1036 | P30: =P29+1 -> 24 | Q30: ='Project OPEX'!B44 -> Progressive Mine Closure Costs | R30: INR/t | S30: ='Project OPEX'!D44 -> 12.963778
B31: Description | C31: Unit | D31: Value | E31: Basis | P31: =P30+1 -> 25 | Q31: ='Project OPEX'!B45 -> Bank Fee on PBG | R31: INR/t | S31: ='Project OPEX'!D45 -> 2.2153887
B32: Average density of Coal | C32: t/cum | D32: 1.72 | E32: In-situ Density | J32: Sl No | K32: List | L32: Unit | M32: Value | P32: =P31+1 -> 26 | Q32: Subtotal | R32: INR/t | S32: =SUM(S23:S31) -> 442.47508
B33: Average density of Waste | C33: t/cum | D33: 2.1 | E33: In-situ Density | J33: 1 | K33: =CF!C40 -> Equity IRR | L33: % | M33: =CF!D40 -> 0.15815964 | Q33: Total Initial Capital Expenditure | R33: INR Cr | S33: =S4+S21+S32 -> 878.60256
B34: Swell factor for Coal | C34: % | D34: 0.2 | J34: 2 | K34: =CF!C41 -> Equity NPV | L34: INR CR | M34: =CF!D41 -> 900.32264 | R34: INR/kcal | S34: ='Project OPEX'!D54 -> 0.28220195
B35: Swell factor for Waste | C35: % | D35: 0.2
B36: Salary & Wages | J36: 3 | K36: =CF!C18 -> Project IRR | L36: % | M36: =CF!D18 -> 0.15815964
B37: Category wise Executives wage details | C37: Category | D37: Annual CTC | E37: Basis | J37: 4 | K37: =CF!C19 -> Project NPV | L37: INR CR | M37: =CF!D19 -> 900.32264
B38: Project Head/ Vice-President | C38: E9 | D38: 6000000 | E38: SRK Assumption
B39: Vice-President/Chief General Manager | C39: E8 | D39: 4500000 | E39: SRK Assumption
B40: General Manager | C40: E7 | D40: 4000000 | E40: SRK Assumption
B41: Deputy General Manager | C41: E6 | D41: 3500000 | E41: SRK Assumption
B42: Assistant General Manager | C42: E5 | D42: 2500000 | E42: SRK Assumption
B43: Senior Manager | C43: E4 | D43: 1800000 | E43: SRK Assumption
B44: Manager | C44: E3 | D44: 1500000 | E44: SRK Assumption
B45: Assistant Manager | C45: E2 | D45: 1235000 | E45: SRK Assumption
B46: Deputy Manager | C46: E1 | D46: 960000 | E46: SRK Assumption
B47: GET/ Junior Engineer | C47: E0 | D47: 750000 | E47: SRK Assumption
B48: Project Head/ Vice-President | C48: M9 | D48: 7000000 | E48: MDO Salary, Industry Standards
B49: Vice-President/Chief General Manager | C49: M8 | D49: 5500000 | E49: MDO Salary, Industry Standards
... B52: Assistant General Manager | C52: M5 | D52: 2500000 | E52: MDO Salary, Industry Standards
B53: Senior Manager | C53: M4 | D53: 1800000 | E53: MDO Salary, Industry Standards | G53: =L106 -> 59.35 | I53: INR Cr
B54: Manager | C54: M3 | D54: 1500000 | E54: MDO Salary, Industry Standards
B55: Assistant Manager | C55: M2 | D55: 1235000 | E55: MDO Salary, Industry Standards
B56: Deputy Manager | C56: M1 | D56: 960000 | E56: MDO Salary, Industry Standards
B57: GET/ Junior Engineer | C57: M0 | D57: 750000 | E57: MDO Salary, Industry Standards
B58: Statutory Staffs & Operator wage details
B59: Staff | C59: S10 | D59: 900000 | E59: SRK Assumption
B60: Staff | C60: S9 | D60: 780000 | E60: SRK Assumption
B61: Staff | C61: S8 | D61: 670000 | E61: SRK Assumption
B62: Staff | C62: S7 | D62: 400000 | E62: Industry Standard
B63: Operator - Senior | C63: S6 | D63: 610000 | E63: =E73 -> HPC Wage/ SRK In-house databasr
B64: Operator - Mid Senior | C64: S5 | D64: 600000 | E64: =E74 -> HPC Wage/ SRK In-house databasr
B65: Operator - Junior | C65: S4 | D65: 600000 | E65: =E76 -> HPC Wage/ SRK In-house databasr
B66: Staff Wage System as per norms
B67: Highly skilled | C67: S3 | D67: 420000 | E67: Central Wage Rule/ SRK in-house database | K67: =L112 -> 878.30792 | L67: INR/t | Q67: =L110 -> 435.83284 | R67: INR/t | U67: =L111 -> 442.47508 | V67: INR/t
B68: Skilled /Clerical | C68: S2 | D68: 360000 | E68: Central Wage Rule/ SRK in-house database
B69: Semi Skilled/unskilled supervisory | C69: S1 | D69: 300000 | E69: Central Wage Rule/ SRK in-house database
B70: Unskilled | C70: S0 | D70: 240000 | E70: Central Wage Rule/ SRK in-house database
B71: Security - Armed | C71: O1 | D71: 320000 | E71: Central Wage Rule/ SRK in-house database
B72: Security - Unarmed | C72: O2 | D72: 300000 | E72: Central Wage Rule/ SRK in-house database
B73: Highly skilled | C73: S3a | D73: 610000 | E73: HPC Wage/ SRK In-house databasr
B74: Skilled | C74: S2a | D74: 600000 | E74: HPC Wage/ SRK In-house databasr
B75: Semi Skilled/unskilled supervisory | C75: S1a | D75: 580000 | E75: HPC Wage/ SRK In-house databasr
B76: Unskilled | C76: S0a | D76: 570000 | E76: HPC Wage/ SRK In-house databasr
T77: 1
B78: Explosives | K78: Initial Capital Costs (Owner) | L78: INR Cr | T78: =T77+0.1 -> 1.1
B79: Description | C79: Unit | D79: Value | E79: Basis | K79: Pre-operative | L79: =M15+M16 -> 313.19704 | T79: =T78+0.1 -> 1.2
B80: Blasting Requirement 100% for how many years | C80: Year | D80: 2 | E80: SRK Assumption | K80: Land and R&R | L80: =M17+M18 -> 2033.648 | T80: =T79+0.1 -> 1.3
B81: Blasting Requirement in coal through out life | C81: % | D81: 0.15 | E81: SRK Assumption | K81: HEMM | L81: =M19 -> 701.51584 | T81: =T80+0.1 -> 1.4
B82: Density of explosives | C82: t/cum | D82: 1.1 | E82: SRK Assumption | K82: CHP and Infrastructure | L82: =M20+M22+M24+M23 -> 567.91 | T82: =T81+0.1 -> 1.5
B83: Boosters required in a hole/ 250mm | C83: gm | D83: 600 | E83: SRK Assumption | K83: Railway Siding | L83: =M21 -> 540 | T83: =T82+0.1 -> 1.6
B84: Boosters required in a hole/ 160mm | C84: gm | D84: 500 | E84: SRK Assumption | K84: Others | L84: =M26+M27+M25+M29 -> 59.35 | T84: =T83+0.1 -> 1.7
B85: Boosters required in a hole/ 115mm | C85: gm | D85: 400 | E85: SRK Assumption | K85: Contingency | L85: =M28 -> 617.48264 | T85: =T84+0.1 -> 1.8
B86: Booster costs | C86: INR/ 100g | D86: 30 | E86: SRK Assumption | T86: =T85+0.1 -> 1.9
B87: Nonel (downhole and surface delay) costs | C87: INR/m | D87: 25 | E87: SRK Assumption | T87: =T86+0.1 -> 2
B88: Bulk explosives costs - Basic rate | C88: INR/kg | D88: 52 | E88: SRK Assumption | T88: =T87+0.1 -> 2.1
B89: R&R | T89: =T88+0.1 -> 2.2
B90: Name of the Village | C90: PDF (to be R&R) | D90: PAF (to be R&R) | E90: PAF/PAP (R&R done) | K90: Total | L90: =SUM(L79:L89) -> 4833.1036 | T90: =T89+0.1 -> 2.3
B91: All | D91: 3150 | T91: =T90+0.1 -> 2.4
B92: Total | C92: =ROUND(SUM(C91:C91),0) -> 0 | D92: =ROUND(SUM(D91:D91),0) -> 3150 | E92: =SUM(E91:E91) -> 0 | T92: =T91+0.1 -> 2.5
B93: R&R Contingency
B94: Cost assumptions | K94: Others | L94: INR Cr
B95: Unit Rates and Operating Costs | C95: Unit | D95: Base Rate | E95: Basis | K95: Electrical | L95: =M25 -> 34.35
B96: Administrative Cost | C96: INR/t | D96: 15 | E96: SRK Assumption | K96: Mine Dewatering System | L96: =M26 -> 15
B97: Environment Management Cost | C97: INR Cr. | D97: =30*(15/6) -> 75 | E97: SRK Assumption (2.5 escalation factor wrt capital cost),considered in pre operative. | K97: Digitalisation | L97: =M27 -> 10
B98: Environment Management & OHS Cost | C98: INR Cr. | D98: =1.28*(15/6) -> 3.2 | E98: SRK Assumption (2.5 escalation factor wrt capital cost). | K98: IDC | L98: =M29 -> 0
B99: Operating cost contingency | C99: % | D99: 0.15 | E99: SRK Assumption
B100: Capital cost contingency | C100: % | D100: 0.15 | E100: SRK Assumption
B101: Base diesel cost (5% Discount on Bulk Purchase) | C101: INR/lit | D101: =95 -> 95 | E101: As per circle rate
B102: Power Charge | C102: INR/KVAh | D102: 7.4 | E102: As per state electric board charges
B103: Owner - Number of person to avail the facility | C103: % | D103: 0.5 | E103: SRK Assumption
...

Sheet Production Schedule
E1: =Assumptions_Dashboard!$D$5 -> 46023 | F1: =E1+366 -> 46389 | G1: =F1+366 -> 46755 | H1: =G1+366 -> 47121 | I1: =H1+366 -> 47487 | J1: =I1+366 -> 47853 | K1: =J1+366 -> 48219 | L1: =K1+366 -> 48585 | M1: =L1+366 -> 48951 | ... AA1: =Z1+366 -> 54075
A2: 1. Working Hours | E2: 1 | F2: =IF(MAX($E$2:E$2)<=(Assumptions_Dashboard!$D$11+Assumptions_Dashboard!$D$6-2),E$2+1,0) -> 2 | G2: =IF(MAX($E$2:F$2)<=(Assumptions_Dashboard!$D$11+Assumptions_Dashboard!$D$6-2),F$2+1,0) -> 3 | H2: =IF(MAX($E$2:G$2)<=(Assumptions_Dashboard!$D$11+Assumptions_Dashboard!$D$6-2),G$2+1,0) -> 4 | I2: =IF(MAX($E$2:H$2)<=(Assumptions_Dashboard!$D$11+Assumptions_Dashboard!$D$6-2),H$2+1,0) -> 5 | J2: =IF(MAX($E$2:I$2)<=(Assumptions_Dashboard!$D$11+Assumptions_Dashboard!$D$6-2),I$2+1,0) -> 6 | K2: =IF(MAX($E$2:J$2)<=(Assumptions_Dashboard!$D$11+Assumptions_Dashboard!$D$6-2),J$2+1,0) -> 7 | L2: =IF(MAX($E$2:K$2)<=(Assumptions_Dashboard!$D$11+Assumptions_Dashboard!$D$6-2),K$2+1,0) -> 8 | M2: =IF(MAX($E$2:L$2)<=(Assumptions_Dashboard!$D$11+Assumptions_Dashboard!$D$6-2),L$2+1,0) -> 9 | ... AA2: =IF(MAX($E$2:Z$2)<=(Assumptions_Dashboard!$D$11+Assumptions_Dashboard!$D$6-2),Z$2+1,0) -> 23
B3: Description | C3: Units | D3: Total/ Average | E3: =IF(E2=0,0,IF((E$2-Assumptions_Dashboard!$D$7)<0,E$2-Assumptions_Dashboard!$D$7,E$2-(Assumptions_Dashboard!$D$7-1))) -> -4 | F3: =IF(F2=0,0,IF((F$2-Assumptions_Dashboard!$D$7)<0,F$2-Assumptions_Dashboard!$D$7,F$2-(Assumptions_Dashboard!$D$7-1))) -> -3 | G3: =IF(G2=0,0,IF((G$2-Assumptions_Dashboard!$D$7)<0,G$2-Assumptions_Dashboard!$D$7,G$2-(Assumptions_Dashboard!$D$7-1))) -> -2 | H3: =IF(H2=0,0,IF((H$2-Assumptions_Dashboard!$D$7)<0,H$2-Assumptions_Dashboard!$D$7,H$2-(Assumptions_Dashboard!$D$7-1))) -> -1 | I3: =IF(I2=0,0,IF((I$2-Assumptions_Dashboard!$D$7)<0,I$2-Assumptions_Dashboard!$D$7,I$2-(Assumptions_Dashboard!$D$7-1))) -> 1 | J3: =IF(J2=0,0,IF((J$2-Assumptions_Dashboard!$D$7)<0,J$2-Assumptions_Dashboard!$D$7,J$2-(Assumptions_Dashboard!$D$7-1))) -> 2 | K3: =IF(K2=0,0,IF((K$2-Assumptions_Dashboard!$D$7)<0,K$2-Assumptions_Dashboard!$D$7,K$2-(Assumptions_Dashboard!$D$7-1))) -> 3 | L3: =IF(L2=0,0,IF((L$2-Assumptions_Dashboard!$D$7)<0,L$2-Assumptions_Dashboard!$D$7,L$2-(Assumptions_Dashboard!$D$7-1))) -> 4 | ... AA3: =IF(AA2=0,0,IF((AA$2-Assumptions_Dashboard!$D$7)<0,AA$2-Assumptions_Dashboard!$D$7,AA$2-(Assumptions_Dashboard!$D$7-1))) -> 19
B4: Total available Hours excavation | C4: hrs | D4: =MAX(E4:AD4) -> 7920 | E4: =IF(E$3<=0,0,Assumptions_Dashboard!$D$29) -> 0 | F4: =IF(F$3<=0,0,Assumptions_Dashboard!$D$29) -> 0 | G4: =IF(G$3<=0,0,Assumptions_Dashboard!$D$29) -> 0 | H4: =IF(H$3<=0,0,Assumptions_Dashboard!$D$29) -> 0 | I4: =IF(I$3<=0,0,Assumptions_Dashboard!$D$29) -> 7920 | J4: =IF(J$3<=0,0,Assumptions_Dashboard!$D$29) -> 7920 | K4: =IF(K$3<=0,0,Assumptions_Dashboard!$D$29) -> 7920 | L4: =IF(L$3<=0,0,Assumptions_Dashboard!$D$29) -> 7920 | ... AA4: =IF(AA$3<=0,0,Assumptions_Dashboard!$D$29) -> 7920
B5: Production Coal/Ore | C5: Mt | D5: =SUM(E5:AA5) -> 225.70441 | I5: {=TRANSPOSE(K42:K60)} -> 1.9999998 | J5: 3.9999987 | K5: 8.0000007 | L5: 11.999999 | M5: 14.999995 | N5: 15.000007 | O5: 14.999999 | P5: 14.999997 | Q5: 15.000004 | R5: 14.999995 | S5: 14.999997 | T5: 15.000002 | U5: 15.000016 | V5: 15.000002 | W5: 15.000002 | X5: 15 | Y5: 9.9999996 | Z5: 7.5000027 | AA5: 2.2043909
A6: =IF(Assumptions_Dashboard!L2="Surface Miner",Assumptions_Dashboard!D81,100%) -> 0.15 | B6: Blasted Coal/Ore | C6: Mt | D6: =SUM(E6:AA6) -> 38.95566 | I6: =IF(Assumptions_Dashboard!$D$80>=I3,I5,I5*$A$6) -> 1.9999998 | J6: =IF(Assumptions_Dashboard!$D$80>=J3,J5,J5*$A$6) -> 3.9999987 | K6: =IF(Assumptions_Dashboard!$D$80>=K3,K5,K5*$A$6) -> 1.2000001 | L6: =IF(Assumptions_Dashboard!$D$80>=L3,L5,L5*$A$6) -> 1.7999998 | M6: =IF(Assumptions_Dashboard!$D$80>=M3,M5,M5*$A$6) -> 2.2499993 | N6: =IF(Assumptions_Dashboard!$D$80>=N3,N5,N5*$A$6) -> 2.2500011 | O6: =IF(Assumptions_Dashboard!$D$80>=O3,O5,O5*$A$6) -> 2.2499998 | P6: =IF(Assumptions_Dashboard!$D$80>=P3,P5,P5*$A$6) -> 2.2499995 | ... AA6: =IF(Assumptions_Dashboard!$D$80>=AA3,AA5,AA5*$A$6) -> 0.33065864
B7: Surface Miner Coal/Ore | C7: Mt | D7: =SUM(E7:AA7) -> 186.74875 | I7: =I5-I6 -> 0 | J7: =J5-J6 -> 0 | K7: =K5-K6 -> 6.8000006 | L7: =L5-L6 -> 10.199999 | M7: =M5-M6 -> 12.749996 | N7: =N5-N6 -> 12.750006 | O7: =O5-O6 -> 12.749999 | P7: =P5-P6 -> 12.749997 | ... AA7: =AA5-AA6 -> 1.8737323
B8: Waste (Topsoil + Overburden + Interburden) | C8: Mbcm | D8: =SUM(E8:AA8) -> 535.39467 | I8: {=TRANSPOSE(O42:O60)} -> 11.466046 | J8: 9.5178188 | K8: 17.240515 | L8: 36.817196 | M8: 35.420575 | N8: 47.463611 | O8: 43.447467 | P8: 36.337475 | Q8: 37.865192 | R8: 33.778948 | S8: 38.053482 | T8: 28.983165 | U8: 25.44988 | V8: 31.615551 | W8: 31.515275 | X8: 40.123367 | Y8: 24.726595 | Z8: 4.2960407 | AA8: 1.2764738
B9: Top Soil | C9: Mbcm | D9: =SUM(E9:AO9) -> 1.6670317 | I9: 0.061151145 | J9: 0.086432905 | K9: 0.1789022 | L9: 0.20884342 | M9: 0.16172259 | N9: 0.094374156 | O9: 0.094374156 | P9: 0.094374156 | Q9: 0.094374156 | R9: 0.094374156 | S9: 0.0582654 | T9: 0.0582654 | U9: 0.0582654 | V9: 0.0582654 | W9: 0.0582654 | X9: 0.051695409 | Y9: 0.051695409 | Z9: 0.051695409 | AA9: 0.051695409
B10: OB | C10: Mbcm | D10: =SUM(E10:AA10) -> 121.47374 | I10: =I8-I9-I11 -> 2.5760394 | J10: =J8-J9-J11 -> 2.1026654 | K10: =K8-K9-K11 -> 3.7864162 | L10: =L8-L9-L11 -> 8.2591117 | M10: =M8-M9-M11 -> 7.9850096 | N10: =N8-N9-N11 -> 10.822256 | O10: =O8-O9-O11 -> 9.8985433 | P10: =P8-P9-P11 -> 8.2632451 | ... AA10: =AA8-AA9-AA11 -> 0.24189357
A11: 0.77 | B11: Partings | C11: Mbcm | D11: =SUM(E11:AA11) -> 412.2539 | I11: =I8*$A$11 -> 8.8288552 | J11: =J8*$A$11 -> 7.3287205 | K11: =K8*$A$11 -> 13.275197 | L11: =L8*$A$11 -> 28.349241 | M11: =M8*$A$11 -> 27.273843 | N11: =N8*$A$11 -> 36.546981 | O11: =O8*$A$11 -> 33.45455 | P11: =P8*$A$11 -> 27.979856 | ... AA11: =AA8*$A$11 -> 0.98288486
A12: 0.05 | B12: Rehandling at CHP | C12: Mbcm | D12: =SUM(E12:AA12) -> 6.5611746 | I12: =I5/Assumptions_Dashboard!$D$32*$A$12 -> 0.058139528 | J12: =J5/Assumptions_Dashboard!$D$32*$A$12 -> 0.11627903 | K12: =K5/Assumptions_Dashboard!$D$32*$A$12 -> 0.23255816 | L12: =L5/Assumptions_Dashboard!$D$32*$A$12 -> 0.34883717 | M12: =M5/Assumptions_Dashboard!$D$32*$A$12 -> 0.43604637 | N12: =N5/Assumptions_Dashboard!$D$32*$A$12 -> 0.43604672 | O12: =O5/Assumptions_Dashboard!$D$32*$A$12 -> 0.43604647 | P12: =P5/Assumptions_Dashboard!$D$32*$A$12 -> 0.43604642 | ... AA12: =AA5/Assumptions_Dashboard!$D$32*$A$12 -> 0.064081132
B13: Waste - Rehandle | C13: Mbcm | D13: =SUM(E13:AO13) -> 75.64 | O13: 11.85 | P13: 11.85 | Q13: 11.85 | R13: 11.85 | S13: 7.06 | T13: 7.06 | U13: 7.06 | V13: 7.06
B14: GCV (ADB) | C14: kcal/kg | D14: =SUMPRODUCT(E5:AA5,E14:AA14)/D5 -> 3113.3823 | I14: {=TRANSPOSE(M42:M60)} -> 3210 | J14: 3150 | K14: 3160 | L14: 3150 | M14: 3120 | N14: 3190 | O14: 3090 | P14: 3160 | Q14: 3190 | R14: 3280 | S14: 3280 | T14: 3020 | U14: 3120 | V14: 3100 | W14: 2850 | X14: 2970 | Y14: 3020 | Z14: 3040 | AA14: 3200
B15: Relaive Density (RD) | C15: g/cm²
B16: Raw ash | C16: %
B17: Moisture | C17: %
B18: Stripping Ratio
B19: YoY | C19: cum/t | I19: =I8/I5 -> 5.7330236 | J19: =J8/J5 -> 2.3794555 | K19: =K8/K5 -> 2.1550642 | L19: =L8/L5 -> 3.0681001 | M19: =M8/M5 -> 2.3613724 | N19: =N8/N5 -> 3.1642392 | O19: =O8/O5 -> 2.8964981 | P19: =P8/P5 -> 2.4224988 | ... AA19: =AA8/AA5 -> 0.57905965
B20: Cumulative | C20: cum/t | D20: =D8/D5 -> 2.3721055 | I20: =I8/I5 -> 5.7330236 | J20: =SUM($I$8:J8)/SUM($I$5:J5) -> 3.4973117 | K20: =SUM($I$8:K8)/SUM($I$5:K5) -> 2.730313 | L20: =SUM($I$8:L8)/SUM($I$5:L5) -> 2.8862147 | M20: =SUM($I$8:M8)/SUM($I$5:M5) -> 2.6941993 | N20: =SUM($I$8:N8)/SUM($I$5:N5) -> 2.8201029 | O20: =SUM($I$8:O8)/SUM($I$5:O5) -> 2.8362427 | P20: =SUM($I$8:P8)/SUM($I$5:P5) -> 2.7640781 | Q20: =SUM($I$8:Q8)/SUM($I$5:Q5) -> 2.7284742 | ... AA20: =SUM($I$8:AA8)/SUM($I$5:AA5) -> 2.3721055
B22: Haul Distance
B23: ROM | C23: km | D23: =SUMPRODUCT(I23:AH23,I5:AH5)/SUM(I5:AH5) -> 3.488188 | I23: 1.6 | J23: 1.6 | K23: 2 | L23: 2.5 | M23: 2.6 | N23: 2.8 | O23: 3 | P23: 3.2 | Q23: 3.4 | R23: 3.5 | S23: 3.7 | T23: 3.8 | U23: 4 | V23: 4.2 | W23: 4.4 | X23: 4.4 | Y23: 4.4 | Z23: 4.4 | AA23: 4.4
B24: Waste | C24: km | D24: =SUMPRODUCT(I24:AH24,I8:AH8)/SUM(I8:AH8) -> 1.7159833 | I24: 1.475764 | J24: 1.8169713 | K24: 1.7860172 | L24: 1.5927861 | M24: 1.2863679 | N24: 1.4290943 | O24: 1.5718207 | P24: 1.7145471 | Q24: 1.8572736 | R24: 2 | S24: 1.96 | T24: 1.92 | U24: 1.88 | V24: 1.84 | W24: 1.8 | X24: 1.74 | Y24: 1.68 | Z24: 1.62 | AA24: 1.5
B25: In-Pit | C25: km | L25: 0.8 | M25: 1 | N25: 1.4290943 | O25: 1.5718207 | P25: 1.7145471 | Q25: 1.8572736 | R25: 2 | S25: 1.96 | T25: 1.92 | U25: 1.88 | V25: 1.84 | W25: 1.8 | X25: 1.74 | Y25: 1.68 | Z25: 1.62 | AA25: 1.5
B26: Ex-Pit | C26: km | I26: 1.475764 | J26: 1.8169713 | K26: 1.7860172 | L26: 1.8 | M26: 1.8
B27: Rehandling | C27: km | O27: 3 | P27: 3 | Q27: 3 | R27: 3 | S27: 3 | T27: 3 | U27: 3 | V27: 3
B29: Bench Specification
B30: Bench Height - Coal | C30: m | D30: 5
B31: Bench Width - Coal | C31: m | D31: 20
B32: Bench Height - OB/IB | C32: m | D32: 10
B33: Bench Width - OB/IB | C33: m | D33: 20
B35: Rehandling cost | C35: INR Cr | D35: =SUM(E35:AH35) -> 529.48 | E35: =Assumptions_Dashboard!$D$153*E13/10 -> 0 | F35: =Assumptions_Dashboard!$D$153*F13/10 -> 0 | G35: =Assumptions_Dashboard!$D$153*G13/10 -> 0 | H35: =Assumptions_Dashboard!$D$153*H13/10 -> 0 | I35: =Assumptions_Dashboard!$D$153*I13/10 -> 0 | J35: =Assumptions_Dashboard!$D$153*J13/10 -> 0 | K35: =Assumptions_Dashboard!$D$153*K13/10 -> 0 | L35: =Assumptions_Dashboard!$D$153*L13/10 -> 0 | ... AA35: =Assumptions_Dashboard!$D$153*AA13/10 -> 0
L40: Diluted | M40: Rounded | N40: Cumulative
J41: Year | K41: Coal (Mt) | L41: GCV Dil (Kcal/Kg) | M41: GCV Dil (Kcal/Kg) | N41: Coal (Mt) | O41: Waste (Mcum)
J42: 1 | K42: 1.9999998 | L42: 3210 | M42: =ROUND(L42,-1) -> 3210 | N42: =K42 -> 1.9999998 | O42: 11.466046
J43: =J42+1 -> 2 | K43: 3.9999987 | L43: 3150 | M43: =ROUND(L43,-1) -> 3150 | N43: =N42+K43 -> 5.9999984 | O43: 9.5178188
J44: =J43+1 -> 3 | K44: 8.0000007 | L44: 3160 | M44: =ROUND(L44,-1) -> 3160 | N44: =N43+K44 -> 13.999999 | O44: 17.240515
J45: =J44+1 -> 4 | K45: 11.999999 | L45: 3150 | M45: =ROUND(L45,-1) -> 3150 | N45: =N44+K45 -> 25.999998 | O45: 36.817196
J46: =J45+1 -> 5 | K46: 14.999995 | L46: 3120 | M46: =ROUND(L46,-1) -> 3120 | N46: =N45+K46 -> 40.999993 | O46: 35.420575
J47: =J46+1 -> 6 | K47: 15.000007 | L47: 3190 | M47: =ROUND(L47,-1) -> 3190 | N47: =N46+K47 -> 56 | O47: 47.463611
J48: =J47+1 -> 7 | K48: 14.999999 | L48: 3090 | M48: =ROUND(L48,-1) -> 3090 | N48: =N47+K48 -> 70.999999 | O48: 43.447467
J49: =J48+1 -> 8 | K49: 14.999997 | L49: 3160 | M49: =ROUND(L49,-1) -> 3160 | N49: =N48+K49 -> 85.999995 | O49: 36.337475
J50: =J49+1 -> 9 | K50: 15.000004 | L50: 3190 | M50: =ROUND(L50,-1) -> 3190 | N50: =N49+K50 -> 101 | O50: 37.865192
J51: =J50+1 -> 10 | K51: 14.999995 | L51: 3280 | M51: =ROUND(L51,-1) -> 3280 | N51: =N50+K51 -> 115.99999 | O51: 33.778948
J52: =J51+1 -> 11 | K52: 14.999997 | L52: 3280 | M52: =ROUND(L52,-1) -> 3280 | N52: =N51+K52 -> 130.99999 | O52: 38.053482
J53: =J52+1 -> 12 | K53: 15.000002 | L53: 3020 | M53: =ROUND(L53,-1) -> 3020 | N53: =N52+K53 -> 145.99999 | O53: 28.983165
J54: =J53+1 -> 13 | K54: 15.000016 | L54: 3120 | M54: =ROUND(L54,-1) -> 3120 | N54: =N53+K54 -> 161.00001 | O54: 25.44988
... J60: =J59+1 -> 19 | K60: 2.2043909 | L60: 3200 | M60: =ROUND(L60,-1) -> 3200 | N60: =N59+K60 -> 225.70441 | O60: 1.2764738
J61: Total | K61: =SUM(K42:K60) -> 225.70441 | L61: =SUMPRODUCT(K42:K60,L42:L60)/SUM(K42:K60) -> 3113.3823 | M61: =ROUND(SUMPRODUCT(K42:K60,M42:M60)/SUM(K42:K60),-1) -> 3110 | O61: =SUM(O42:O60) -> 535.39467

Sheet Sensitivity
B2: Sensitivity
B3: Parameters | C3: % Change | Q3: %Change in Coal Selling Price | R3: Equity IRR | S3: Project IRR | T3: Project NPV | U3: Equity NPV
B4: Capex | C4: 0 | R4: 0.11436347 | S4: 0.1132572 | T4: 316.35859 | U4: 301.84625
B5: Opex | C5: 0 | Q5: -0.2 | R5: 0.072989795 | S5: 0.076714511 | T5: -503.93299 | U5: -518.44533
B6: Coal Price | C6: 0 | Q6: -0.15 | R6: 0.084183611 | S6: 0.086651723 | T6: -296.79548 | U6: -311.30782
Q7: -0.1 | R7: 0.094697914 | S7: 0.095951181 | T7: -92.333856 | U7: -106.8462
Q8: -0.05 | R8: 0.10473416 | S8: 0.1047977 | T8: 112.01237 | U8: 97.500024
Q9: 0 | R9: 0.11436347 | S9: 0.1132572 | T9: 316.35859 | U9: 301.84625
Q10: 0.05 | R10: 0.12363789 | S10: 0.1213785 | T10: 520.70481 | U10: 506.19247
B11: GST on Revenue Sharing | C11: Yes | Q11: 0.1 | R11: 0.13259898 | S11: 0.12920097 | T11: 725.05103 | U11: 710.53869
C12: P-IRR | D12: E-IRR | Q12: 0.15 | R12: 0.14128044 | S12: 0.13675686 | T12: 929.39725 | U12: 914.88491
Q13: 0.2 | R13: 0.14970998 | S13: 0.14407296 | T13: 1133.7435 | U13: 1119.2311
B14: Yes
B15: No | F15: Project IRR Sensitivity | Q15: %Change in Capex | R15: Equity IRR | S15: Project IRR | T15: Project NPV | U15: Equity NPV
F16: Selling Price (INR/t) | I16: 1280.2632 | J16: 1440.2961 | K16: 1520.3125 | L16: 1600.329 | M16: 1680.3454 | N16: 1760.3619 | O16: 1920.3948 | R16: 0.11436347 | S16: 0.1132572 | T16: 316.35859 | U16: 301.84625
B17: Refund of GST Credit | C17: No | F17: Capital (INR Cr) | H17: 0.1132572 | I17: -0.2 | J17: -0.1 | K17: -0.05 | L17: 0 | M17: 0.05 | N17: 0.1 | O17: 0.2 | Q17: -0.2 | R17: 0.14372199 | S17: 0.13889172 | T17: 792.95658 | U17: 781.3467
C18: P-IRR | D18: E-IRR | G18: 3424.3802 | H18: -0.2 | I18: 0.098657608 | J18: 0.1197446 | K18: 0.12952438 | L18: 0.13889172 | M18: 0.14789711 | N18: 0.15658129 | O18: 0.17311409 | Q18: -0.15 | R18: 0.13542599 | S18: 0.13167144 | T18: 673.80708 | U18: 661.47159
G19: 3852.4277 | H19: -0.1 | I19: 0.086882366 | J19: 0.10689978 | K19: 0.11617022 | L19: 0.12504237 | M19: 0.13356583 | N19: 0.14178061 | O19: 0.15740969 | Q19: -0.1 | R19: 0.12782759 | S19: 0.12504237 | T19: 554.65758 | U19: 541.59648
B20: Yes | G20: 4066.4514 | H20: -0.05 | I20: 0.081630536 | J20: 0.10121972 | K20: 0.11026898 | L20: 0.11892588 | M20: 0.12723961 | N20: 0.13524986 | O20: 0.15048445 | Q20: -0.05 | R20: 0.12083258 | S20: 0.11892588 | T20: 435.50809 | U20: 421.72136
B21: No | G21: 4280.4752 | H21: 0 | I21: 0.076714511 | J21: 0.095951181 | K21: 0.1047977 | L21: 0.1132572 | M21: 0.1213785 | N21: 0.12920097 | O21: 0.14407296 | Q21: 0 | R21: 0.11436347 | S21: 0.1132572 | T21: 316.35859 | U21: 301.84625
G22: 4494.499 | H22: 0.05 | I22: 0.072134626 | J22: 0.091044836 | K22: 0.099704758 | L22: 0.10798251 | M22: 0.11592654 | N22: 0.12357594 | O22: 0.13811344 | Q22: 0.05 | R22: 0.10835588 | S22: 0.10798251 | T22: 197.20909 | U22: 181.97113
G23: 4708.5227 | H23: 0.1 | I23: 0.067852459 | J23: 0.086459298 | K23: 0.09494683 | L23: 0.10305662 | M23: 0.11083677 | N23: 0.11832609 | O23: 0.13255399 | Q23: 0.1 | R23: 0.10275589 | S23: 0.10305662 | T23: 78.059592 | U23: 62.096016
G24: 5136.5702 | H24: 0.2 | I24: 0.060056165 | J24: 0.078060953 | K24: 0.086294834 | L24: 0.094104003 | M24: 0.10159072 | N24: 0.10879326 | O24: 0.12246599 | Q24: 0.15 | R24: 0.097517949 | S24: 0.098441313 | T24: -41.089906 | U24: -57.779099
Q25: 0.2 | R25: 0.092603293 | S25: 0.094104003 | T25: -160.2394 | U25: -177.65421
F27: Project IRR Sensitivity | Q27: %Change in Operating Cost | R27: Equity IRR | S27: Project IRR | T27: Project NPV | U27: Equity NPV
F28: Selling Price (INR/t) | I28: 1280.2632 | J28: 1440.2961 | K28: 1520.3125 | L28: 1600.329 | M28: 1680.3454 | N28: 1760.3619 | O28: 1920.3948 | R28: 0.11436347 | S28: 0.1132572 | T28: 316.35859 | U28: 301.84625
F29: Operating Cost (INR/t) | H29: 0.1132572 | I29: -0.2 | J29: -0.1 | K29: -0.05 | L29: 0 | M29: 0.05 | N29: 0.1 | O29: 0.2 | Q29: -0.2 | R29: 0.14140877 | S29: 0.13686179 | T29: 930.90751 | U29: 916.39517
G30: 677.34774 | H30: -0.2 | I30: 0.10198189 | J30: 0.12014994 | K30: 0.12866413 | L30: 0.13686179 | M30: 0.14477728 | N30: 0.15243907 | O30: 0.16709329 | Q30: -0.15 | R30: 0.1348845 | S30: 0.13118824 | T30: 777.27028 | U30: 762.75794
G31: 762.01621 | H31: -0.1 | I31: 0.089839736 | J31: 0.1084117 | K31: 0.117065 | L31: 0.12537157 | M31: 0.13337183 | N31: 0.14109888 | O31: 0.1558386 | Q31: -0.1 | R31: 0.12821116 | S31: 0.12537157 | T31: 623.63305 | U31: 609.12071
G32: 804.35044 | H32: -0.05 | I32: 0.083453134 | J32: 0.10228078 | K32: 0.11102274 | L32: 0.11939934 | M32: 0.12745485 | N32: 0.13522523 | O32: 0.15002433 | Q32: -0.05 | R32: 0.12137583 | S32: 0.11939934 | T32: 469.99582 | U32: 455.48348
G33: 846.68467 | H33: 0 | I33: 0.076714511 | J33: 0.095951181 | K33: 0.1047977 | L33: 0.1132572 | M33: 0.1213785 | N33: 0.12920097 | O33: 0.14407296 | Q33: 0 | R33: 0.11436347 | S33: 0.1132572 | T33: 316.35859 | U33: 301.84625
G34: 889.01891 | H34: 0.05 | I34: 0.069700699 | J34: 0.089400645 | K34: 0.098370733 | L34: 0.10692842 | M34: 0.11512797 | N34: 0.12301283 | O34: 0.13797354 | Q34: 0.05 | R34: 0.10715643 | S34: 0.10692842 | T34: 162.72136 | U34: 148.20902
G35: 931.35314 | H35: 0.1 | I35: 0.062365781 | J35: 0.082602566 | K35: 0.091719171 | L35: 0.10039334 | M35: 0.10868599 | N35: 0.11664542 | O35: 0.1317135 | Q35: 0.1 | R35: 0.099733809 | S35: 0.10039334 | T35: 9.0841276 | U35: -5.4282146
B36: Coal Mining Machinery | C36: Surface Miner | G36: 1016.0216 | H36: 0.2 | I36: 0.046494507 | J36: 0.067897141 | K36: 0.077558299 | L36: 0.086606485 | M36: 0.095142536 | N36: 0.10329773 | O36: 0.11865106 | Q36: 0.15 | R36: 0.092070592 | S36: 0.093628671 | T36: -144.5531 | U36: -159.06544
C37: P-IRR | D37: E-IRR | Q37: 0.2 | R37: 0.084136521 | S37: 0.086606485 | T37: -298.19033 | U37: -312.70267
B39: Surface Miner
B40: Shovel & Dumper
B42: Mining Operation | C42: Departmental
C43: P-IRR | D43: E-IRR
B45: Departmental
B46: MDO
B48: MDO rate Provided | C48: Yes
B53: FMIPCC | C53: Yes

Sheet P&L
G5: ='Production Schedule'!E1 -> 46023 | H5: ='Production Schedule'!F1 -> 46389 | I5: ='Production Schedule'!G1 -> 46755 | J5: ='Production Schedule'!H1 -> 47121 | K5: ='Production Schedule'!I1 -> 47487 | L5: ='Production Schedule'!J1 -> 47853 | M5: ='Production Schedule'!K1 -> 48219 | N5: ='Production Schedule'!L1 -> 48585 | ... AC5: ='Production Schedule'!AA1 -> 54075
C6: Year No. | G6: ='Production Schedule'!E3 -> -4 | H6: ='Production Schedule'!F3 -> -3 | I6: ='Production Schedule'!G3 -> -2 | J6: ='Production Schedule'!H3 -> -1 | K6: ='Production Schedule'!I3 -> 1 | L6: ='Production Schedule'!J3 -> 2 | M6: ='Production Schedule'!K3 -> 3 | N6: ='Production Schedule'!L3 -> 4 | ... AC6: ='Production Schedule'!AA3 -> 19 | AK6: ='Production Schedule'!AI3 -> 0 | AL6: ='Production Schedule'!AJ3 -> 0 | AM6: ='Production Schedule'!AK3 -> 0 | AN6: ='Production Schedule'!AL3 -> 0 | AO6: ='Production Schedule'!AM3 -> 0 | AP6: ='Production Schedule'!AN3 -> 0
C7: Sales Products
A8: assuming 100% sold | C8: Total Product | D8: (Mt) | E8: =SUM(G8:AP8) -> 225.70441 | G8: ='Production Schedule'!E5 -> 0 | H8: ='Production Schedule'!F5 -> 0 | I8: ='Production Schedule'!G5 -> 0 | J8: ='Production Schedule'!H5 -> 0 | K8: ='Production Schedule'!I5 -> 1.9999998 | L8: ='Production Schedule'!J5 -> 3.9999987 | M8: ='Production Schedule'!K5 -> 8.0000007 | N8: ='Production Schedule'!L5 -> 11.999999 | ... AC8: ='Production Schedule'!AA5 -> 2.2043909
C9: Revenue
C10: Gross Revenue | D10: (INR Cr) | E10: =+SUM(G10:AP10) -> 35929.111 | G10: =Government!E8+Government!E9 -> 0 | H10: =Government!F8+Government!F9 -> 0 | I10: =Government!G8+Government!G9 -> 0 | J10: =Government!H8+Government!H9 -> 0 | K10: =Government!I8+Government!I9 -> 330.23996 | L10: =Government!J8+Government!J9 -> 660.47978 | M10: =Government!K8+Government!K9 -> 1320.9601 | N10: =Government!L8+Government!L9 -> 1981.4398 | ... AC10: =Government!AA8+Government!AA9 -> 363.98903
C11: Profit & Loss Statement
C12: Realisation | D12: (INR Cr) | E12: =+SUM(G12:AP12) -> 35929.111 | F12: =E12/$E$8*10 -> 1591.8658 | G12: =G10 -> 0 | H12: =H10 -> 0 | I12: =I10 -> 0 | J12: =J10 -> 0 | K12: =K10 -> 330.23996 | L12: =L10 -> 660.47978 | M12: =M10 -> 1320.9601 | N12: =N10 -> 1981.4398 | ... AC12: =AC10 -> 363.98903
C14: Less : Cost
C15: Operating Cost | D15: (INR Cr) | E15: =+SUM(G15:AP15) -> 23147.947 | F15: =E15/$E$8*10 -> 1025.5868 | G15: =SUM(G17:G18)*(1+Sensitivity!$C$5) -> 0 | H15: =SUM(H17:H18)*(1+Sensitivity!$C$5) -> 0 | I15: =SUM(I17:I18)*(1+Sensitivity!$C$5) -> 0 | J15: =SUM(J17:J18)*(1+Sensitivity!$C$5) -> 0 | K15: =SUM(K17:K18)*(1+Sensitivity!$C$5) -> 258.82253 | L15: =SUM(L17:L18)*(1+Sensitivity!$C$5) -> 364.52803 | M15: =SUM(M17:M18)*(1+Sensitivity!$C$5) -> 664.51221 | N15: =SUM(N17:N18)*(1+Sensitivity!$C$5) -> 1161.1992 | ... AC15: =SUM(AC17:AC18)*(1+Sensitivity!$C$5) -> 276.34771
C16: Fixed Cost
C17: Operating Cost | D17: INR Cr | E17: =+SUM(G17:AP17) -> 19830.447 | F17: =E17/$E$8*10 -> 878.60256 | G17: ='Project OPEX'!E100 -> 0 | H17: ='Project OPEX'!F100 -> 0 | I17: ='Project OPEX'!G100 -> 0 | J17: ='Project OPEX'!H100 -> 0 | K17: ='Project OPEX'!I100 -> 258.82253 | L17: ='Project OPEX'!J100 -> 334.82803 | M17: ='Project OPEX'!K100 -> 620.51221 | N17: ='Project OPEX'!L100 -> 1073.1992 | ... AC17: ='Project OPEX'!AA100 -> 276.34771
C18: Cost of Purchased Coal | D18: INR Cr | E18: =+SUM(G18:AP18) -> 3317.5 | F18: =E18/$E$8*10 -> 146.98428 | G18: ='Coal Price'!E10 -> 0 | H18: ='Coal Price'!F10 -> 0 | I18: ='Coal Price'!G10 -> 0 | J18: ='Coal Price'!H10 -> 0 | K18: ='Coal Price'!I10 -> 0 | L18: ='Coal Price'!J10 -> 29.7 | M18: ='Coal Price'!K10 -> 44 | N18: ='Coal Price'!L10 -> 88 | ... AC18: ='Coal Price'!AA10 -> 0
C21: Total Cost | D21: (INR Cr) | E21: =+SUM(G21:AP21) -> 23147.947 | F21: =E21/$E$8*10 -> 1025.5868 | G21: =G15 -> 0 | H21: =H15 -> 0 | I21: =I15 -> 0 | J21: =J15 -> 0 | K21: =K15 -> 258.82253 | L21: =L15 -> 364.52803 | M21: =M15 -> 664.51221 | N21: =N15 -> 1161.1992 | ... AC21: =AC15 -> 276.34771
C23: EBIDTA | D23: (INR Cr) | E23: =+SUM(G23:AP23) -> 12781.165 | F23: =E23/$E$8*10 -> 566.27892 | G23: =+G12-G21 -> 0 | H23: =+H12-H21 -> 0 | I23: =+I12-I21 -> 0 | J23: =+J12-J21 -> 0 | K23: =+K12-K21 -> 71.417433 | L23: =+L12-L21 -> 295.95175 | M23: =+M12-M21 -> 656.44791 | N23: =+N12-N21 -> 820.24052 | ... AC23: =+AC12-AC21 -> 87.641319
C24: EBIDTA % | E24: =+E23/E12 -> 0.35573283 | G24: =+IFERROR(G23/G12,"") | H24: =+IFERROR(H23/H12,"") | I24: =+IFERROR(I23/I12,"") | J24: =+IFERROR(J23/J12,"") | K24: =+IFERROR(K23/K12,"") -> 0.21625921 | L24: =+IFERROR(L23/L12,"") -> 0.44808601 | M24: =+IFERROR(M23/M12,"") -> 0.49694756 | N24: =+IFERROR(N23/N12,"") -> 0.41396188 | ... AC24: =+IFERROR(AC23/AC12,"") -> 0.24078011
C26: Less : Depreciation (Straight Line) | D26: (INR Cr) | E26: =+SUM(G26:AM26) -> -4934.6654 | F26: =E26/$E$8*10 -> -218.63399 | G26: =-'Depreciation-Owner'!H114 -> -14.631973 | H26: =-'Depreciation-Owner'!I114 -> -32.036732 | I26: =-'Depreciation-Owner'!J114 -> -66.593835 | J26: =-'Depreciation-Owner'!K114 -> -97.214807 | K26: =-'Depreciation-Owner'!L114 -> -135.14873 | L26: =-'Depreciation-Owner'!M114 -> -144.59207 | M26: =-'Depreciation-Owner'!N114 -> -161.45289 | N26: =-'Depreciation-Owner'!O114 -> -207.49698 | ... AC26: =-'Depreciation-Owner'!AD114 -> -250.9493
C27: Add: Salvage Value | D27: (INR Cr) | E27: =+SUM(G27:AM27) -> 1499.0601 | F27: =E27/$E$8*10 -> 66.416961 | AC27: ='Depreciation-Owner'!AD46+'Depreciation-Owner'!AD52+'Depreciation-Owner'!AD58+'Depreciation-Owner'!AD64+'Depreciation-Owner'!AD70+'Depreciation-Owner'!AD76+'Depreciation-Owner'!AD82+'Depreciation-Owner'!AD88+'Depreciation-Owner'!AD94+'Depreciation-Owner'!AD100+'Depreciation-Owner'!AD106+'Depreciation-Owner'!AD112 -> 1499.0601
C29: EBIT | D29: (INR Cr) | E29: =+SUM(G29:AM29) -> 9345.5593 | F29: =E29/$E$8*10 -> 414.06189 | G29: =+G23+G26+G27 -> -14.631973 | H29: =+H23+H26+H27 -> -32.036732 | I29: =+I23+I26+I27 -> -66.593835 | J29: =+J23+J26+J27 -> -97.214807 | K29: =+K23+K26+K27 -> -63.731295 | L29: =+L23+L26+L27 -> 151.35968 | M29: =+M23+M26+M27 -> 494.99501 | N29: =+N23+N26+N27 -> 612.74354 | ... AC29: =+AC23+AC26+AC27 -> 1335.7521
C31: Less : Interest | D31: (INR Cr) | E31: =+SUM(G31:AM31) -> 0 | F31: =E31/$E$8*10 -> 0 | G31: =-'Borrowings-Owner'!G96 -> 0 | H31: =-'Borrowings-Owner'!H96 -> 0 | I31: =-'Borrowings-Owner'!I96 -> 0 | J31: =-'Borrowings-Owner'!J96 -> 0 | K31: =-'Borrowings-Owner'!K96 -> 0 | L31: =-'Borrowings-Owner'!L96 -> 0 | M31: =-'Borrowings-Owner'!M96 -> 0 | N31: =-'Borrowings-Owner'!N96 -> 0 | ... AC31: =-'Borrowings-Owner'!AC96 -> 0
C33: EBT | D33: (INR Cr) | E33: =+SUM(G33:AM33) -> 9345.5593 | F33: =E33/$E$8*10 -> 414.06189 | G33: =+G29+G31 -> -14.631973 | H33: =+H29+H31 -> -32.036732 | I33: =+I29+I31 -> -66.593835 | J33: =+J29+J31 -> -97.214807 | K33: =+K29+K31 -> -63.731295 | L33: =+L29+L31 -> 151.35968 | M33: =+M29+M31 -> 494.99501 | N33: =+N29+N31 -> 612.74354 | ... AC33: =+AC29+AC31 -> 1335.7521
H34: =IFERROR(H33/#REF!,"") | I34: =IFERROR(I33/#REF!,"") | J34: =IFERROR(J33/#REF!,"")
C35: Less : Tax | D35: (INR Cr) | E35: =+SUM(G35:AM35) -> 0 | F35: =E35/$E$8*10 -> 0 | G35: =-Tax!F14 -> 0 | H35: =-Tax!G14 -> 0 | I35: =-Tax!H14 -> 0 | J35: =-Tax!I14 -> 0 | K35: =-Tax!J14 -> 0 | L35: =-Tax!K14 -> 0 | M35: =-Tax!L14 -> 0 | N35: =-Tax!M14 -> 0 | ... AC35: =-Tax!AB14 -> 0
C37: PAT | D37: (INR Cr) | E37: =+SUM(G37:AM37) -> 9345.5593 | F37: =E37/$E$8*10 -> 414.06189 | G37: =+G33+G35 -> -14.631973 | H37: =+H33+H35 -> -32.036732 | I37: =+I33+I35 -> -66.593835 | J37: =+J33+J35 -> -97.214807 | K37: =+K33+K35 -> -63.731295 | L37: =+L33+L35 -> 151.35968 | M37: =+M33+M35 -> 494.99501 | N37: =+N33+N35 -> 612.74354 | ... AC37: =+AC33+AC35 -> 1335.7521
C39: CSR Spend per Companies Act | D39: (INR Cr) | E39: =+SUM(G39:AM39) -> -201.24745 | F39: =E39/$E$8*10 -> -8.9164165 | G39: =-IF(G37<0,0,G37*$C$40) -> 0 | H39: =-IF(H37<0,0,H37*$C$40) -> 0 | I39: =-IF(I37<0,0,I37*$C$40) -> 0 | J39: =-IF(J37<0,0,J37*$C$40) -> 0 | K39: =-IF(K37<0,0,K37*$C$40) -> 0 | L39: =-IF(L37<0,0,L37*$C$40) -> -3.0271936 | M39: =-IF(M37<0,0,M37*$C$40) -> -9.8999003 | N39: =-IF(N37<0,0,N37*$C$40) -> -12.254871 | ... AC39: =-IF(AC37<0,0,AC37*$C$40) -> -26.715042
C40: =Assumptions_Dashboard!D132 -> 0.02 | D40: (INR Cr)
C41: PAT after CSR spent | D41: (INR Cr) | E41: =+SUM(G41:AM41) -> 9144.3119 | F41: =E41/$E$8*10 -> 405.14547 | G41: =+G37+G39 -> -14.631973 | H41: =+H37+H39 -> -32.036732 | I41: =+I37+I39 -> -66.593835 | J41: =+J37+J39 -> -97.214807 | K41: =+K37+K39 -> -63.731295 | L41: =+L37+L39 -> 148.33248 | M41: =+M37+M39 -> 485.09511 | N41: =+N37+N39 -> 600.48867 | ... AC41: =+AC37+AC39 -> 1309.0371

Sheet CF
F2: ='P&L'!G5 -> 46023 | G2: ='P&L'!H5 -> 46389 | H2: ='P&L'!I5 -> 46755 | I2: ='P&L'!J5 -> 47121 | J2: ='P&L'!K5 -> 47487 | K2: ='P&L'!L5 -> 47853 | L2: ='P&L'!M5 -> 48219 | M2: ='P&L'!N5 -> 48585 | ... AB2: ='P&L'!AC5 -> 54075
C3: Year No. | F3: ='P&L'!G6 -> -4 | G3: ='P&L'!H6 -> -3 | H3: ='P&L'!I6 -> -2 | I3: ='P&L'!J6 -> -1 | J3: ='P&L'!K6 -> 1 | K3: ='P&L'!L6 -> 2 | L3: ='P&L'!M6 -> 3 | M3: ='P&L'!N6 -> 4 | ... AB3: ='P&L'!AC6 -> 19 | AJ3: ='P&L'!AK6 -> 0 | AK3: ='P&L'!AL6 -> 0 | AL3: ='P&L'!AM6 -> 0 | AM3: ='P&L'!AN6 -> 0
C5: Project Cash Inflow
C6: Realisation | D6: (INR Cr) | E6: =SUM(F6:AM6) -> 35929.111 | F6: ='P&L'!G12 -> 0 | G6: ='P&L'!H12 -> 0 | H6: ='P&L'!I12 -> 0 | I6: ='P&L'!J12 -> 0 | J6: ='P&L'!K12 -> 330.23996 | K6: ='P&L'!L12 -> 660.47978 | L6: ='P&L'!M12 -> 1320.9601 | M6: ='P&L'!N12 -> 1981.4398 | ... AB6: ='P&L'!AC12 -> 363.98903
C7: Total Cash In-Flow | D7: (INR Cr) | E7: =SUM(F7:AM7) -> 35929.111 | F7: =SUM(F6:F6) -> 0 | G7: =SUM(G6:G6) -> 0 | H7: =SUM(H6:H6) -> 0 | I7: =SUM(I6:I6) -> 0 | J7: =SUM(J6:J6) -> 330.23996 | K7: =SUM(K6:K6) -> 660.47978 | L7: =SUM(L6:L6) -> 1320.9601 | M7: =SUM(M6:M6) -> 1981.4398 | ... AB7: =SUM(AB6:AB6) -> 363.98903
C8: Project Cash Outflow
C9: Operating Cost | D9: (INR Cr) | E9: =SUM(F9:AM9) -> -23147.947 | F9: =-'P&L'!G15 -> 0 | G9: =-'P&L'!H15 -> 0 | H9: =-'P&L'!I15 -> 0 | I9: =-'P&L'!J15 -> 0 | J9: =-'P&L'!K15 -> -258.82253 | K9: =-'P&L'!L15 -> -364.52803 | L9: =-'P&L'!M15 -> -664.51221 | M9: =-'P&L'!N15 -> -1161.1992 | ... AB9: =-'P&L'!AC15 -> -276.34771
C10: Capex | D10: (INR Cr) | E10: =SUM(F10:AM10) -> -6433.7255 | F10: =-'Depreciation-Owner'!H35 -> -155.9943 | G10: =-'Depreciation-Owner'!I35 -> -343.46765 | H10: =-'Depreciation-Owner'!J35 -> -677.7139 | I10: =-'Depreciation-Owner'!K35 -> -542.15415 | J10: =-'Depreciation-Owner'!L35 -> -512.0367 | K10: =-'Depreciation-Owner'!M35 -> -185.81301 | L10: =-'Depreciation-Owner'!N35 -> -214.02863 | M10: =-'Depreciation-Owner'!O35 -> -587.76578 | ... AB10: =-'Depreciation-Owner'!AD35 -> -180.57944
C11: Taxes | D11: (INR Cr) | E11: =SUM(F11:AM11) -> 0 | F11: =-Tax!F14 -> 0 | G11: =-Tax!G14 -> 0 | H11: =-Tax!H14 -> 0 | I11: =-Tax!I14 -> 0 | J11: =-Tax!J14 -> 0 | K11: =-Tax!K14 -> 0 | L11: =-Tax!L14 -> 0 | M11: =-Tax!M14 -> 0 | ... AB11: =-Tax!AB14 -> 0
C12: Total Cash Out-Flow | D12: (INR Cr) | E12: =SUM(F12:AM12) -> -29581.672 | F12: =SUM(F9:F11) -> -155.9943 | G12: =SUM(G9:G11) -> -343.46765 | H12: =SUM(H9:H11) -> -677.7139 | I12: =SUM(I9:I11) -> -542.15415 | J12: =SUM(J9:J11) -> -770.85922 | K12: =SUM(K9:K11) -> -550.34104 | L12: =SUM(L9:L11) -> -878.54085 | M12: =SUM(M9:M11) -> -1748.965 | ... AB12: =SUM(AB9:AB11) -> -456.92715
C13: Free Cash flow for Project
C14: Project Cashflow | D14: (INR Cr) | E14: =SUM(F14:AM14) -> 6347.4392 | F14: =F7+F12 -> -155.9943 | G14: =G7+G12 -> -343.46765 | H14: =H7+H12 -> -677.7139 | I14: =I7+I12 -> -542.15415 | J14: =J7+J12 -> -440.61926 | K14: =K7+K12 -> 110.13874 | L14: =L7+L12 -> 442.41927 | M14: =M7+M12 -> 232.47474 | ... AB14: =AB7+AB12 -> -92.938121
C15: Cummulative Cashflow | D15: (INR Cr) | F15: =F14 -> -155.9943 | G15: =F15+G14 -> -499.46195 | H15: =G15+H14 -> -1177.1758 | I15: =H15+I14 -> -1719.33 | J15: =I15+J14 -> -2159.9493 | K15: =J15+K14 -> -2049.8105 | L15: =K15+L14 -> -1607.3912 | M15: =L15+M14 -> -1374.9165 | N15: =M15+N14 -> -638.92615 | ... AB15: =AA15+AB14 -> 6347.4392
C18: Project IRR | D18: =IFERROR(IRR(F14:AB14),"-") -> 0.15815964
C19: Project NPV | D19: =NPV(E19,F14:AB14) -> 900.32264 | E19: 0.1
C20: Payback | D20: =COUNTIF(F15:AI15,"<0")+INDEX(F21:AI21,COUNTIF(F21:AI21,"<0")+1) -> 10 | E20: from Now
D21: =COUNTIF(F15:AI15,"<0")+INDEX(F21:AI21,COUNTIF(F21:AI21,"<0")+1)-COUNT(F15:I15) -> 6 | E21: from Start of Production | F21: =IF(F14<0,0,IFERROR(IF(F15<0,0,ABS(F15)/F14),0)) -> 0 | G21: =IF(G14<0,0,IFERROR(IF(G15<0,0,ABS(G15)/G14),0)) -> 0 | H21: =IF(H14<0,0,IFERROR(IF(H15<0,0,ABS(H15)/H14),0)) -> 0 | I21: =IF(I14<0,0,IFERROR(IF(I15<0,0,ABS(I15)/I14),0)) -> 0 | J21: =IF(J14<0,0,IFERROR(IF(J15<0,0,ABS(J15)/J14),0)) -> 0 | K21: =IF(K14<0,0,IFERROR(IF(K15<0,0,ABS(K15)/K14),0)) -> 0 | L21: =IF(L14<0,0,IFERROR(IF(L15<0,0,ABS(L15)/L14),0)) -> 0 | M21: =IF(M14<0,0,IFERROR(IF(M15<0,0,ABS(M15)/M14),0)) -> 0 | ... AB21: =IF(AB14<0,0,IFERROR(IF(AB15<0,0,ABS(AB15)/AB14),0)) -> 0
C24: Equity Cash Inflow
C25: Realisation | D25: (INR Cr) | E25: =SUM(F25:AM25) -> 35929.111 | F25: =F6 -> 0 | G25: =G6 -> 0 | H25: =H6 -> 0 | I25: =I6 -> 0 | J25: =J6 -> 330.23996 | K25: =K6 -> 660.47978 | L25: =L6 -> 1320.9601 | M25: =M6 -> 1981.4398 | ... AB25: =AB6 -> 363.98903
C26: Borrowing | D26: (INR Cr) | E26: =SUM(F26:AM26) -> 0 | F26: ='Borrowings-Owner'!G23+'Borrowings-Owner'!G67+'Borrowings-Owner'!G88 -> 0 | G26: ='Borrowings-Owner'!H23+'Borrowings-Owner'!H67+'Borrowings-Owner'!H88 -> 0 | H26: ='Borrowings-Owner'!I23+'Borrowings-Owner'!I67+'Borrowings-Owner'!I88 -> 0 | I26: ='Borrowings-Owner'!J23+'Borrowings-Owner'!J67+'Borrowings-Owner'!J88 -> 0 | J26: ='Borrowings-Owner'!K23+'Borrowings-Owner'!K67+'Borrowings-Owner'!K88 -> 0 | K26: ='Borrowings-Owner'!L23+'Borrowings-Owner'!L67+'Borrowings-Owner'!L88 -> 0 | L26: ='Borrowings-Owner'!M23+'Borrowings-Owner'!M67+'Borrowings-Owner'!M88 -> 0 | M26: ='Borrowings-Owner'!N23+'Borrowings-Owner'!N67+'Borrowings-Owner'!N88 -> 0 | ... AB26: ='Borrowings-Owner'!AC23+'Borrowings-Owner'!AC67+'Borrowings-Owner'!AC88 -> 0
C27: Total Cash In-Flow | D27: (INR Cr) | E27: =SUM(F27:AM27) -> 35929.111 | F27: =SUM(F25:F26) -> 0 | G27: =SUM(G25:G26) -> 0 | H27: =SUM(H25:H26) -> 0 | I27: =SUM(I25:I26) -> 0 | J27: =SUM(J25:J26) -> 330.23996 | K27: =SUM(K25:K26) -> 660.47978 | L27: =SUM(L25:L26) -> 1320.9601 | M27: =SUM(M25:M26) -> 1981.4398 | ... AB27: =SUM(AB25:AB26) -> 363.98903
C28: Equity Cash Outflow
C29: Operating Cost | D29: (INR Cr) | E29: =SUM(F29:AM29) -> -23147.947 | F29: =F9 -> 0 | G29: =G9 -> 0 | H29: =H9 -> 0 | I29: =I9 -> 0 | J29: =J9 -> -258.82253 | K29: =K9 -> -364.52803 | L29: =L9 -> -664.51221 | M29: =M9 -> -1161.1992 | ... AB29: =AB9 -> -276.34771
C30: Capex | D30: (INR Cr) | E30: =SUM(F30:AM30) -> -6433.7255 | F30: =F10 -> -155.9943 | G30: =G10 -> -343.46765 | H30: =H10 -> -677.7139 | I30: =I10 -> -542.15415 | J30: =J10 -> -512.0367 | K30: =K10 -> -185.81301 | L30: =L10 -> -214.02863 | M30: =M10 -> -587.76578 | ... AB30: =AB10 -> -180.57944
C31: Taxes | D31: (INR Cr) | E31: =SUM(F31:AM31) -> 0 | F31: =-Tax!F14 -> 0 | G31: =-Tax!G14 -> 0 | H31: =-Tax!H14 -> 0 | I31: =-Tax!I14 -> 0 | J31: =-Tax!J14 -> 0 | K31: =-Tax!K14 -> 0 | L31: =-Tax!L14 -> 0 | M31: =-Tax!M14 -> 0 | ... AB31: =-Tax!AB14 -> 0
C32: Interest | D32: (INR Cr) | E32: =SUM(F32:AM32) -> 0 | F32: ='P&L'!G31 -> 0 | G32: ='P&L'!H31 -> 0 | H32: ='P&L'!I31 -> 0 | I32: ='P&L'!J31 -> 0 | J32: ='P&L'!K31 -> 0 | K32: ='P&L'!L31 -> 0 | L32: ='P&L'!M31 -> 0 | M32: ='P&L'!N31 -> 0 | ... AB32: ='P&L'!AC31 -> 0
C33: Repayment | D33: (INR Cr) | E33: =SUM(F33:AM33) -> 0 | F33: =-('Borrowings-Owner'!G24+'Borrowings-Owner'!G68+'Borrowings-Owner'!G89) -> 0 | G33: =-('Borrowings-Owner'!H24+'Borrowings-Owner'!H68+'Borrowings-Owner'!H89) -> 0 | H33: =-('Borrowings-Owner'!I24+'Borrowings-Owner'!I68+'Borrowings-Owner'!I89) -> 0 | I33: =-('Borrowings-Owner'!J24+'Borrowings-Owner'!J68+'Borrowings-Owner'!J89) -> 0 | J33: =-('Borrowings-Owner'!K24+'Borrowings-Owner'!K68+'Borrowings-Owner'!K89) -> 0 | K33: =-('Borrowings-Owner'!L24+'Borrowings-Owner'!L68+'Borrowings-Owner'!L89) -> 0 | L33: =-('Borrowings-Owner'!M24+'Borrowings-Owner'!M68+'Borrowings-Owner'!M89) -> 0 | M33: =-('Borrowings-Owner'!N24+'Borrowings-Owner'!N68+'Borrowings-Owner'!N89) -> 0 | ... AB33: =-('Borrowings-Owner'!AC24+'Borrowings-Owner'!AC68+'Borrowings-Owner'!AC89) -> 0
C34: Total Cash Out-Flow | D34: (INR Cr) | E34: =SUM(F34:AM34) -> -29581.672 | F34: =SUM(F29:F33) -> -155.9943 | G34: =SUM(G29:G33) -> -343.46765 | H34: =SUM(H29:H33) -> -677.7139 | I34: =SUM(I29:I33) -> -542.15415 | J34: =SUM(J29:J33) -> -770.85922 | K34: =SUM(K29:K33) -> -550.34104 | L34: =SUM(L29:L33) -> -878.54085 | M34: =SUM(M29:M33) -> -1748.965 | ... AB34: =SUM(AB29:AB33) -> -456.92715
C35: Free Cash flow for Equity Shareholder
C36: Equity Shareholder Cashflow | D36: (INR Cr) | E36: =SUM(F36:AM36) -> 6347.4392 | F36: =F27+F34 -> -155.9943 | G36: =G27+G34 -> -343.46765 | H36: =H27+H34 -> -677.7139 | I36: =I27+I34 -> -542.15415 | J36: =J27+J34 -> -440.61926 | K36: =K27+K34 -> 110.13874 | L36: =L27+L34 -> 442.41927 | M36: =M27+M34 -> 232.47474 | ... AB36: =AB27+AB34 -> -92.938121
C37: Cummulative Cashflow | D37: (INR Cr) | F37: =F36 -> -155.9943 | G37: =F37+G36 -> -499.46195 | H37: =G37+H36 -> -1177.1758 | I37: =H37+I36 -> -1719.33 | J37: =I37+J36 -> -2159.9493 | K37: =J37+K36 -> -2049.8105 | L37: =K37+L36 -> -1607.3912 | M37: =L37+M36 -> -1374.9165 | N37: =M37+N36 -> -638.92615 | ... AB37: =AA37+AB36 -> 6347.4392
C40: Equity IRR | D40: =IFERROR(IRR(F36:AB36),"-") -> 0.15815964
C41: Equity NPV | D41: =NPV(E41,F36:AB36) -> 900.32264 | E41: =E19 -> 0.1

Sheet Tax
F4: ='P&L'!G5 -> 46023 | G4: ='P&L'!H5 -> 46389 | H4: ='P&L'!I5 -> 46755 | I4: ='P&L'!J5 -> 47121 | J4: ='P&L'!K5 -> 47487 | K4: ='P&L'!L5 -> 47853 | L4: ='P&L'!M5 -> 48219 | M4: ='P&L'!N5 -> 48585 | ... AP4: ='P&L'!AQ5 -> 0
C5: Year No. | F5: ='P&L'!G6 -> -4 | G5: ='P&L'!H6 -> -3 | H5: ='P&L'!I6 -> -2 | I5: ='P&L'!J6 -> -1 | J5: ='P&L'!K6 -> 1 | K5: ='P&L'!L6 -> 2 | L5: ='P&L'!M6 -> 3 | M5: ='P&L'!N6 -> 4 | ... AP5: ='P&L'!AQ6 -> 0
C7: Normal Tax
C8: EBIDTA | D8: (INR Cr) | E8: =SUM(F8:AP8) -> 12781.165 | F8: ='P&L'!G23 -> 0 | G8: ='P&L'!H23 -> 0 | H8: ='P&L'!I23 -> 0 | I8: ='P&L'!J23 -> 0 | J8: ='P&L'!K23 -> 71.417433 | K8: ='P&L'!L23 -> 295.95175 | L8: ='P&L'!M23 -> 656.44791 | M8: ='P&L'!N23 -> 820.24052 | ... AI8: ='P&L'!AJ23 -> 0
C9: Less : Depreciation | D9: (INR Cr) | E9: =SUM(F9:AN9) -> #REF! | F9: ='Depreciation-Owner'!H114 -> 14.631973 | G9: ='Depreciation-Owner'!I114 -> 32.036732 | H9: ='Depreciation-Owner'!J114 -> 66.593835 | I9: ='Depreciation-Owner'!K114 -> 97.214807 | J9: ='Depreciation-Owner'!L114 -> 135.14873 | K9: ='Depreciation-Owner'!M114 -> 144.59207 | L9: ='Depreciation-Owner'!N114 -> 161.45289 | M9: ='Depreciation-Owner'!O114 -> 207.49698 | ... AB9: ='Depreciation-Owner'!AD114 -> 250.9493 | AC9: ='Depreciation-Owner'!#REF! -> #REF! | AD9: ='Depreciation-Owner'!#REF! -> #REF! | AE9: ='Depreciation-Owner'!#REF! -> #REF! | AF9: ='Depreciation-Owner'!#REF! -> #REF! | AG9: ='Depreciation-Owner'!#REF! -> #REF! | AH9: ='Depreciation-Owner'!#REF! -> #REF! | AI9: ='Depreciation-Owner'!#REF! -> #REF!
C10: Less : Interest | D10: (INR Cr) | E10: =SUM(F10:AN10) -> 0 | F10: =-'P&L'!G31 -> 0 | G10: =-'P&L'!H31 -> 0 | H10: =-'P&L'!I31 -> 0 | I10: =-'P&L'!J31 -> 0 | J10: =-'P&L'!K31 -> 0 | K10: =-'P&L'!L31 -> 0 | L10: =-'P&L'!M31 -> 0 | M10: =-'P&L'!N31 -> 0 | ... AI10: =-'P&L'!AJ31 -> 0
C11: EBT for normal tax | D11: (INR Cr) | E11: =SUM(F11:AN11) -> #REF! | F11: =+F8-SUM(F9:F10) -> -14.631973 | G11: =+G8-SUM(G9:G10) -> -32.036732 | H11: =+H8-SUM(H9:H10) -> -66.593835 | I11: =+I8-SUM(I9:I10) -> -97.214807 | J11: =+J8-SUM(J9:J10) -> -63.731295 | K11: =+K8-SUM(K9:K10) -> 151.35968 | L11: =+L8-SUM(L9:L10) -> 494.99501 | M11: =+M8-SUM(M9:M10) -> 612.74354 | ... AI11: =+AI8-SUM(AI9:AI10) -> #REF!
B14: =Assumptions_Dashboard!D128 -> 0.2517 | C14: Normal Tax | D14: (INR Cr) | E14: =SUM(F14:AN14) -> 0 | F14: =IF(Assumptions_Dashboard!$L$6="Yes",0,IF(F11<0,0,F11*$B$14)) -> 0 | G14: =IF(Assumptions_Dashboard!$L$6="Yes",0,IF(G11<0,0,G11*$B$14)) -> 0 | H14: =IF(Assumptions_Dashboard!$L$6="Yes",0,IF(H11<0,0,H11*$B$14)) -> 0 | I14: =IF(Assumptions_Dashboard!$L$6="Yes",0,IF(I11<0,0,I11*$B$14)) -> 0 | J14: =IF(Assumptions_Dashboard!$L$6="Yes",0,IF(J11<0,0,J11*$B$14)) -> 0 | K14: =IF(Assumptions_Dashboard!$L$6="Yes",0,IF(K11<0,0,K11*$B$14)) -> 0 | L14: =IF(Assumptions_Dashboard!$L$6="Yes",0,IF(L11<0,0,L11*$B$14)) -> 0 | M14: =IF(Assumptions_Dashboard!$L$6="Yes",0,IF(M11<0,0,M11*$B$14)) -> 0 | ... AI14: =IF(Assumptions_Dashboard!$L$6="Yes",0,IF(AI11<0,0,AI11*$B$14)) -> 0
I239: =(#REF!+#REF!*20%) -> #REF!

Sheet Borrowings-Owner
G1: ='Production Schedule'!E1 -> 46023 | H1: ='Production Schedule'!F1 -> 46389 | I1: ='Production Schedule'!G1 -> 46755 | J1: ='Production Schedule'!H1 -> 47121 | K1: ='Production Schedule'!I1 -> 47487 | L1: ='Production Schedule'!J1 -> 47853 | M1: ='Production Schedule'!K1 -> 48219 | N1: ='Production Schedule'!L1 -> 48585 | ... AC1: ='Production Schedule'!AA1 -> 54075
C2: Year No. | G2: ='Production Schedule'!E3 -> -4 | H2: ='Production Schedule'!F3 -> -3 | I2: ='Production Schedule'!G3 -> -2 | J2: ='Production Schedule'!H3 -> -1 | K2: ='Production Schedule'!I3 -> 1 | L2: ='Production Schedule'!J3 -> 2 | M2: ='Production Schedule'!K3 -> 3 | N2: ='Production Schedule'!L3 -> 4 | ... AC2: ='Production Schedule'!AA3 -> 19
C3: Technical Drivers
C4: Production | D4: Mt | E4: =SUM(G4:AC4) -> 225.70441 | G4: ='Production Schedule'!E5 -> 0 | H4: ='Production Schedule'!F5 -> 0 | I4: ='Production Schedule'!G5 -> 0 | J4: ='Production Schedule'!H5 -> 0 | K4: ='Production Schedule'!I5 -> 1.9999998 | L4: ='Production Schedule'!J5 -> 3.9999987 | M4: ='Production Schedule'!K5 -> 8.0000007 | N4: ='Production Schedule'!L5 -> 11.999999 | ... AC4: ='Production Schedule'!AA5 -> 2.2043909
C5: Capital Borrowing
C6: Non Funded Capex | D6: (INR Cr) | E6: =SUM(G6:AC6) -> 4833.1036 | G6: ='Depreciation-Owner'!H23 -> 155.9943 | H6: ='Depreciation-Owner'!I23 -> 343.46765 | I6: ='Depreciation-Owner'!J23 -> 677.7139 | J6: ='Depreciation-Owner'!K23 -> 542.15415 | K6: ='Depreciation-Owner'!L23 -> 512.0367 | L6: ='Depreciation-Owner'!M23 -> 185.81301 | M6: ='Depreciation-Owner'!N23 -> 214.02863 | N6: ='Depreciation-Owner'!O23 -> 587.76578 | ... AC6: ='Depreciation-Owner'!AD23 -> 0
B7: No | C7: Sustaining Capital | D7: (INR Cr) | E7: =SUM(G7:AC7) -> 0 | G7: =IF($B$7="Yes",'Depreciation-Owner'!H33,0) -> 0 | H7: =IF($B$7="Yes",'Depreciation-Owner'!I33,0) -> 0 | I7: =IF($B$7="Yes",'Depreciation-Owner'!J33,0) -> 0 | J7: =IF($B$7="Yes",'Depreciation-Owner'!K33,0) -> 0 | K7: =IF($B$7="Yes",'Depreciation-Owner'!L33,0) -> 0 | L7: =IF($B$7="Yes",'Depreciation-Owner'!M33,0) -> 0 | M7: =IF($B$7="Yes",'Depreciation-Owner'!N33,0) -> 0 | N7: =IF($B$7="Yes",'Depreciation-Owner'!O33,0) -> 0 | ... AC7: =IF($B$7="Yes",'Depreciation-Owner'!AD33,0) -> 0
D8: (INR Cr) | E8: =SUM(G8:AC8) -> 4833.1036 | G8: =SUM(G6:G7) -> 155.9943 | H8: =SUM(H6:H7) -> 343.46765 | I8: =SUM(I6:I7) -> 677.7139 | J8: =SUM(J6:J7) -> 542.15415 | K8: =SUM(K6:K7) -> 512.0367 | L8: =SUM(L6:L7) -> 185.81301 | M8: =SUM(M6:M7) -> 214.02863 | N8: =SUM(N6:N7) -> 587.76578 | ... AC8: =SUM(AC6:AC7) -> 0
C10: Funded Capex | D10: (INR Cr) | E10: =SUM(G10:AC10) -> 0
C12: Debt : Equity
C13: - Debt | D13: (%) | E13: =E20/E8 -> 0 | G13: =Assumptions_Dashboard!$D$144 -> 0 | H13: =G13 -> 0 | I13: =H13 -> 0 | J13: =I13 -> 0 | K13: =J13 -> 0 | L13: =K13 -> 0 | M13: =L13 -> 0 | N13: =M13 -> 0 | O13: =N13 -> 0 | ... AC13: =AB13 -> 0
C14: - Equity | D14: (%) | E14: =E19/E8 -> 1 | G14: =1-G13 -> 1 | H14: =1-H13 -> 1 | I14: =1-I13 -> 1 | J14: =1-J13 -> 1 | K14: =1-K13 -> 1 | L14: =1-L13 -> 1 | M14: =1-M13 -> 1 | N14: =1-N13 -> 1 | ... AC14: =1-AC13 -> 1
C16: Interest Rate | D16: (%) | E16: =Assumptions_Dashboard!$D$140 -> 0.1 | G16: =E16 -> 0.1 | H16: =G16 -> 0.1 | I16: =H16 -> 0.1 | J16: =I16 -> 0.1 | K16: =J16 -> 0.1 | L16: =K16 -> 0.1 | M16: =L16 -> 0.1 | N16: =M16 -> 0.1 | O16: =N16 -> 0.1 | ... AC16: =AB16 -> 0.1
C18: Non Funded Capital Borrowing
C19: Equity Capital | D19: (INR Cr) | E19: =SUM(G19:AC19) -> 4833.1036 | G19: =G8-G20 -> 155.9943 | H19: =H8-H20 -> 343.46765 | I19: =I8-I20 -> 677.7139 | J19: =J8-J20 -> 542.15415 | K19: =K8-K20 -> 512.0367 | L19: =L8-L20 -> 185.81301 | M19: =M8-M20 -> 214.02863 | N19: =N8-N20 -> 587.76578 | ... AC19: =AC8-AC20 -> 0
B20: Yes | C20: Debt Schedule | D20: (INR Cr) | E20: =SUM(G20:AC20) -> 0 | F20: =SUM(E19:E20)=E8 -> TRUE | G20: =IF($B$20="No",0,G8*G13) -> 0 | H20: =IF($B$20="No",0,H8*H13) -> 0 | I20: =IF($B$20="No",0,I8*I13) -> 0 | J20: =IF($B$20="No",0,J8*J13) -> 0 | K20: =IF($B$20="No",0,K8*K13) -> 0 | L20: =IF($B$20="No",0,L8*L13) -> 0 | M20: =IF($B$20="No",0,M8*M13) -> 0 | N20: =IF($B$20="No",0,N8*N13) -> 0 | ... AC20: =IF($B$20="No",0,AC8*AC13) -> 0
C22: Opening Borrowings | D22: (INR Cr) | G22: =F63 -> 0 | H22: =G63 -> 0 | I22: =H63 -> 0 | J22: =I63 -> 0 | K22: =J63 -> 0 | L22: =K63 -> 0 | M22: =L63 -> 0 | N22: =M63 -> 0 | ... AC22: =AB63 -> 0
C23: Add : Further Borrowings | D23: (INR Cr) | E23: =SUM(G23:AC23) -> 0 | G23: =+IF(G20>0,G20,0) -> 0 | H23: =+IF(H20>0,H20,0) -> 0 | I23: =+IF(I20>0,I20,0) -> 0 | J23: =+IF(J20>0,J20,0) -> 0 | K23: =+IF(K20>0,K20,0) -> 0 | L23: =+IF(L20>0,L20,0) -> 0 | M23: =+IF(M20>0,M20,0) -> 0 | N23: =+IF(N20>0,N20,0) -> 0 | ... AC23: =+IF(AC20>0,AC20,0) -> 0
C24: Less : Repayments | D24: (INR Cr) | E24: =SUM(G24:AC24) -> 0 | G24: =SUM(G25:G59) -> 0 | H24: =SUM(H25:H59) -> 0 | I24: =SUM(I25:I59) -> 0 | J24: =SUM(J25:J59) -> 0 | K24: =SUM(K25:K59) -> 0 | L24: =SUM(L25:L59) -> 0 | M24: =SUM(M25:M59) -> 0 | N24: =SUM(N25:N59) -> 0 | ... AC24: =SUM(AC25:AC59) -> 0
C25: {=TRANSPOSE(G2:AC2)} -> -4 | D25: (INR Cr) | E25: =SUM(G25:AC25) -> 0 | K25: =$G20/7 -> 0 | L25: =$G20/7 -> 0 | M25: =$G20/7 -> 0 | N25: =$G20/7 -> 0 | O25: =$G20/7 -> 0 | P25: =$G20/7 -> 0 | Q25: =$G20/7 -> 0
C26: -3 | D26: (INR Cr) | E26: =SUM(G26:AC26) -> 0 | K26: =$H20/7 -> 0 | L26: =$H20/7 -> 0 | M26: =$H20/7 -> 0 | N26: =$H20/7 -> 0 | O26: =$H20/7 -> 0 | P26: =$H20/7 -> 0 | Q26: =$H20/7 -> 0
C27: -2 | D27: (INR Cr) | E27: =SUM(G27:AC27) -> 0 | K27: =$I20/7 -> 0 | L27: =$I20/7 -> 0 | M27: =$I20/7 -> 0 | N27: =$I20/7 -> 0 | O27: =$I20/7 -> 0 | P27: =$I20/7 -> 0 | Q27: =$I20/7 -> 0
C28: -1 | D28: (INR Cr) | E28: =SUM(G28:AC28) -> 0 | K28: =$J20/7 -> 0 | L28: =$J20/7 -> 0 | M28: =$J20/7 -> 0 | N28: =$J20/7 -> 0 | O28: =$J20/7 -> 0 | P28: =$J20/7 -> 0 | Q28: =$J20/7 -> 0
C29: 1 | D29: (INR Cr) | E29: =SUM(G29:AC29) -> 0 | L29: =$K20/7 -> 0 | M29: =$K20/7 -> 0 | N29: =$K20/7 -> 0 | O29: =$K20/7 -> 0 | P29: =$K20/7 -> 0 | Q29: =$K20/7 -> 0 | R29: =$K20/7 -> 0
C30: 2 | D30: (INR Cr) | E30: =SUM(G30:AC30) -> 0 | M30: =$L20/7 -> 0 | N30: =$L20/7 -> 0 | O30: =$L20/7 -> 0 | P30: =$L20/7 -> 0 | Q30: =$L20/7 -> 0 | R30: =$L20/7 -> 0 | S30: =$L20/7 -> 0
C31: 3 | D31: (INR Cr) | E31: =SUM(G31:AC31) -> 0 | N31: =$M20/7 -> 0 | O31: =$M20/7 -> 0 | P31: =$M20/7 -> 0 | Q31: =$M20/7 -> 0 | R31: =$M20/7 -> 0 | S31: =$M20/7 -> 0 | T31: =$M20/7 -> 0
C32: 4 | D32: (INR Cr) | E32: =SUM(G32:AC32) -> 0 | O32: =$N20/7 -> 0 | P32: =$N20/7 -> 0 | Q32: =$N20/7 -> 0 | R32: =$N20/7 -> 0 | S32: =$N20/7 -> 0 | T32: =$N20/7 -> 0 | U32: =$N20/7 -> 0
C33: 5 | D33: (INR Cr) | E33: =SUM(G33:AC33) -> 0 | P33: =$O20/7 -> 0 | Q33: =$O20/7 -> 0 | R33: =$O20/7 -> 0 | S33: =$O20/7 -> 0 | T33: =$O20/7 -> 0 | U33: =$O20/7 -> 0 | V33: =$O20/7 -> 0
C34: 6 | D34: (INR Cr) | E34: =SUM(G34:AC34) -> 0 | Q34: =$P20/7 -> 0 | R34: =$P20/7 -> 0 | S34: =$P20/7 -> 0 | T34: =$P20/7 -> 0 | U34: =$P20/7 -> 0 | V34: =$P20/7 -> 0 | W34: =$P20/7 -> 0
C35: 7 | D35: (INR Cr) | E35: =SUM(G35:AC35) -> 0 | R35: =$Q20/7 -> 0 | S35: =$Q20/7 -> 0 | T35: =$Q20/7 -> 0 | U35: =$Q20/7 -> 0 | V35: =$Q20/7 -> 0 | W35: =$Q20/7 -> 0 | X35: =$Q20/7 -> 0
C36: 8 | D36: (INR Cr) | E36: =SUM(G36:AC36) -> 0 | S36: =$R20/7 -> 0 | T36: =$R20/7 -> 0 | U36: =$R20/7 -> 0 | V36: =$R20/7 -> 0 | W36: =$R20/7 -> 0 | X36: =$R20/7 -> 0 | Y36: =$R20/7 -> 0
C37: 9 | D37: (INR Cr) | E37: =SUM(G37:AC37) -> 0 | T37: =$S20/7 -> 0 | U37: =$S20/7 -> 0 | V37: =$S20/7 -> 0 | W37: =$S20/7 -> 0 | X37: =$S20/7 -> 0 | Y37: =$S20/7 -> 0 | Z37: =$S20/7 -> 0
C38: 10 | D38: (INR Cr) | E38: =SUM(G38:AC38) -> 0 | U38: =$T20/7 -> 0 | V38: =$T20/7 -> 0 | W38: =$T20/7 -> 0 | X38: =$T20/7 -> 0 | Y38: =$T20/7 -> 0 | Z38: =$T20/7 -> 0 | AA38: =$T20/7 -> 0
C39: 11 | D39: (INR Cr) | E39: =SUM(G39:AC39) -> 0 | V39: =$U20/7 -> 0 | W39: =$U20/7 -> 0 | X39: =$U20/7 -> 0 | Y39: =$U20/7 -> 0 | Z39: =$U20/7 -> 0 | AA39: =$U20/7 -> 0 | AB39: =$U20/7 -> 0
C40: 12 | D40: (INR Cr) | E40: =SUM(G40:AC40) -> 0 | W40: =$V20/7 -> 0 | X40: =$V20/7 -> 0 | Y40: =$V20/7 -> 0 | Z40: =$V20/7 -> 0 | AA40: =$V20/7 -> 0 | AB40: =$V20/7 -> 0 | AC40: =$V20/7 -> 0
C41: 13 | D41: (INR Cr) | E41: =SUM(G41:AC41) -> 0 | X41: =$W20/6 -> 0 | Y41: =$W20/6 -> 0 | Z41: =$W20/6 -> 0 | AA41: =$W20/6 -> 0 | AB41: =$W20/6 -> 0 | AC41: =$W20/6 -> 0
C42: 14 | D42: (INR Cr) | E42: =SUM(G42:AC42) -> 0 | Y42: =$X20/5 -> 0 | Z42: =$X20/5 -> 0 | AA42: =$X20/5 -> 0 | AB42: =$X20/5 -> 0 | AC42: =$X20/5 -> 0
C43: 15 | D43: (INR Cr) | E43: =SUM(G43:AC43) -> 0 | Z43: =$Y20/4 -> 0 | AA43: =$Y20/4 -> 0 | AB43: =$Y20/4 -> 0 | AC43: =$Y20/4 -> 0
C44: 16 | D44: (INR Cr) | E44: =SUM(G44:AC44) -> 0 | AA44: =$Z20/3 -> 0 | AB44: =$Z20/3 -> 0 | AC44: =$Z20/3 -> 0
C45: 17 | D45: (INR Cr) | E45: =SUM(G45:AC45) -> 0 | AB45: =$AA20/2 -> 0 | AC45: =$AA20/2 -> 0
C46: 18 | D46: (INR Cr) | E46: =SUM(G46:AC46) -> 0 | AC46: =$AB20/1 -> 0
C47: 19 | D47: (INR Cr) | E47: =SUM(G47:AC47) -> 0
D48: (INR Cr) | E48: =SUM(G48:AC48) -> 0
D49: (INR Cr) | E49: =SUM(G49:AC49) -> 0
D50: (INR Cr) | E50: =SUM(G50:AC50) -> 0
D51: (INR Cr) | E51: =SUM(G51:AC51) -> 0
D52: (INR Cr) | E52: =SUM(G52:AC52) -> 0
D53: (INR Cr) | E53: =SUM(G53:AC53) -> 0
D54: (INR Cr) | E54: =SUM(G54:AC54) -> 0
D55: (INR Cr) | E55: =SUM(G55:AC55) -> 0
D56: (INR Cr) | E56: =SUM(G56:AC56) -> 0
D57: (INR Cr) | E57: =SUM(G57:AC57) -> 0
D58: (INR Cr) | E58: =SUM(G58:AC58) -> 0
D59: (INR Cr) | E59: =SUM(G59:AC59) -> 0
C61: Add : Interest Cost | D61: (INR Cr) | E61: =SUM(G61:AC61) -> 0 | G61: =(G22-G24)*G16+G23*G16*0.5+G24*G16*0.5 -> 0 | H61: =(H22-H24)*H16+H23*H16*0.5+H24*H16*0.5 -> 0 | I61: =(I22-I24)*I16+I23*I16*0.5+I24*I16*0.5 -> 0 | J61: =(J22-J24)*J16+J23*J16*0.5+J24*J16*0.5 -> 0 | K61: =(K22-K24)*K16+K23*K16*0.5+K24*K16*0.5 -> 0 | L61: =(L22-L24)*L16+L23*L16*0.5+L24*L16*0.5 -> 0 | M61: =(M22-M24)*M16+M23*M16*0.5+M24*M16*0.5 -> 0 | N61: =(N22-N24)*N16+N23*N16*0.5+N24*N16*0.5 -> 0 | ... AC61: =(AC22-AC24)*AC16+AC23*AC16*0.5+AC24*AC16*0.5 -> 0
C62: Less : Interest Paid | D62: (INR Cr) | E62: =SUM(G62:AC62) -> 0 | G62: =G61 -> 0 | H62: =H61 -> 0 | I62: =I61 -> 0 | J62: =J61 -> 0 | K62: =K61 -> 0 | L62: =L61 -> 0 | M62: =M61 -> 0 | N62: =N61 -> 0 | ... AC62: =AC61 -> 0
C63: Closing Borrowings | D63: (INR Cr) | G63: =G22+G23-G24+G61-G62 -> 0 | H63: =H22+H23-H24+H61-H62 -> 0 | I63: =I22+I23-I24+I61-I62 -> 0 | J63: =J22+J23-J24+J61-J62 -> 0 | K63: =K22+K23-K24+K61-K62 -> 0 | L63: =L22+L23-L24+L61-L62 -> 0 | M63: =M22+M23-M24+M61-M62 -> 0 | N63: =N22+N23-N24+N61-N62 -> 0 | ... AC63: =AC22+AC23-AC24+AC61-AC62 -> 0
C65: Funded Capital Borrowing
C66: Opening Borrowings | D66: (INR Cr) | G66: =F71 -> 0 | H66: =G71 -> 0 | I66: =H71 -> 0 | J66: =I71 -> 0 | K66: =J71 -> 0 | L66: =K71 -> 0 | M66: =L71 -> 0 | N66: =M71 -> 0 | ... AC66: =AB71 -> 0
C67: Add : Further Borrowings | D67: (INR Cr) | E67: =SUM(G67:AC67) -> 0 | G67: =G10*G13 -> 0 | H67: =H10*H13 -> 0 | I67: =I10*I13 -> 0 | J67: =J10*J13 -> 0 | K67: =K10*K13 -> 0 | L67: =L10*L13 -> 0 | M67: =M10*M13 -> 0 | N67: =N10*N13 -> 0 | ... AC67: =AC10*AC13 -> 0
C68: Less : Repayments | D68: (INR Cr) | E68: =SUM(G68:AC68) -> 0
C69: Add : Interest Cost | D69: (INR Cr) | E69: =SUM(G69:AC69) -> 0 | G69: =(G66-G68)*G16+G67*G16*0.5+G68*G16*0.5 -> 0 | H69: =(H66-H68)*H16+H67*H16*0.5+H68*H16*0.5 -> 0 | I69: =(I66-I68)*I16+I67*I16*0.5+I68*I16*0.5 -> 0 | J69: =(J66-J68)*J16+J67*J16*0.5+J68*J16*0.5 -> 0 | K69: =(K66-K68)*K16+K67*K16*0.5+K68*K16*0.5 -> 0 | L69: =(L66-L68)*L16+L67*L16*0.5+L68*L16*0.5 -> 0 | M69: =(M66-M68)*M16+M67*M16*0.5+M68*M16*0.5 -> 0 | N69: =(N66-N68)*N16+N67*N16*0.5+N68*N16*0.5 -> 0 | ... AC69: =(AC66-AC68)*AC16+AC67*AC16*0.5+AC68*AC16*0.5 -> 0
C70: Less : Interest Paid | D70: (INR Cr) | E70: =SUM(G70:AC70) -> 0 | G70: =G69 -> 0 | H70: =H69 -> 0 | I70: =I69 -> 0 | J70: =J69 -> 0 | K70: =K69 -> 0 | L70: =L69 -> 0 | M70: =M69 -> 0 | N70: =N69 -> 0 | ... AC70: =AC69 -> 0
C71: Closing Borrowings | D71: (INR Cr) | G71: =G66+G67-G68+G69-G70 -> 0 | H71: =H66+H67-H68+H69-H70 -> 0 | I71: =I66+I67-I68+I69-I70 -> 0 | J71: =J66+J67-J68+J69-J70 -> 0 | K71: =K66+K67-K68+K69-K70 -> 0 | L71: =L66+L67-L68+L69-L70 -> 0 | M71: =M66+M67-M68+M69-M70 -> 0 | N71: =N66+N67-N68+N69-N70 -> 0 | ... AC71: =AC66+AC67-AC68+AC69-AC70 -> 0
C75: Working Capital Borrowing
B76: 45 | C76: Accounts Receivable | D76: (INR Cr) | E76: =SUM(G76:AC76) -> 0 | G76: =$B$76/365*(0) -> 0 | H76: =$B$76/365*(0) -> 0 | I76: =$B$76/365*(0) -> 0 | J76: =$B$76/365*(0) -> 0 | K76: =$B$76/365*(0) -> 0 | L76: =$B$76/365*(0) -> 0 | M76: =$B$76/365*(0) -> 0 | N76: =$B$76/365*(0) -> 0 | ... AC76: =$B$76/365*(0) -> 0
B77: 30 | C77: Inventory | D77: (INR Cr) | E77: =SUM(G77:AC77) -> 0 | G77: =$B$77/365*(0) -> 0 | H77: =$B$77/365*(0) -> 0 | I77: =$B$77/365*(0) -> 0 | J77: =$B$77/365*(0) -> 0 | K77: =$B$77/365*(0) -> 0 | L77: =$B$77/365*(0) -> 0 | M77: =$B$77/365*(0) -> 0 | N77: =$B$77/365*(0) -> 0 | ... AC77: =$B$77/365*(0) -> 0
B78: 21 | C78: Accounts Payable | D78: (INR Cr) | E78: =SUM(G78:AC78) -> 0 | G78: =$B$78/365*(0) -> 0 | H78: =$B$78/365*(0) -> 0 | I78: =$B$78/365*(0) -> 0 | J78: =$B$78/365*(0) -> 0 | K78: =$B$78/365*(0) -> 0 | L78: =$B$78/365*(0) -> 0 | M78: =$B$78/365*(0) -> 0 | N78: =$B$78/365*(0) -> 0 | ... AC78: =$B$78/365*(0) -> 0
C79: Total Working Capital | D79: (INR Cr) | E79: =SUM(G79:AC79) -> 0 | G79: =SUM(G76:G77)-G78 -> 0 | H79: =SUM(H76:H77)-H78 -> 0 | I79: =SUM(I76:I77)-I78 -> 0 | J79: =SUM(J76:J77)-J78 -> 0 | K79: =SUM(K76:K77)-K78 -> 0 | L79: =SUM(L76:L77)-L78 -> 0 | M79: =SUM(M76:M77)-M78 -> 0 | N79: =SUM(N76:N77)-N78 -> 0 | ... AC79: =SUM(AC76:AC77)-AC78 -> 0
C80: Change in Working Capital | D80: (INR Cr) | E80: =SUM(G80:AC80) -> 0 | G80: =G79 -> 0 | H80: =H79-G79 -> 0 | I80: =I79-H79 -> 0 | J80: =J79-I79 -> 0 | K80: =K79-J79 -> 0 | L80: =L79-K79 -> 0 | M80: =M79-L79 -> 0 | N80: =N79-M79 -> 0 | O80: =O79-N79 -> 0 | ... AC80: =AC79-AB79 -> 0
B81: Yes | C81: Working Capital | D81: (INR Cr) | E81: =SUM(G81:AC81) -> 0 | G81: =IF($B$81="Yes",G80,0) -> 0 | H81: =IF($B$81="Yes",H80,0) -> 0 | I81: =IF($B$81="Yes",I80,0) -> 0 | J81: =IF($B$81="Yes",J80,0) -> 0 | K81: =IF($B$81="Yes",K80,0) -> 0 | L81: =IF($B$81="Yes",L80,0) -> 0 | M81: =IF($B$81="Yes",M80,0) -> 0 | N81: =IF($B$81="Yes",N80,0) -> 0 | ... AC81: =IF($B$81="Yes",AC80,0) -> 0
C82: Total | D82: (INR Cr) | E82: =SUM(G82:AC82) -> 0 | G82: =G81 -> 0 | H82: =H81 -> 0 | I82: =I81 -> 0 | J82: =J81 -> 0 | K82: =K81 -> 0 | L82: =L81 -> 0 | M82: =M81 -> 0 | N82: =N81 -> 0 | ... AC82: =AC81 -> 0
C83: Debt : Equity
C84: - Debt | D84: (%) | E84: =E13 -> 0 | G84: =E84 -> 0 | H84: =G84 -> 0 | I84: =H84 -> 0 | J84: =I84 -> 0 | K84: =J84 -> 0 | L84: =K84 -> 0 | M84: =L84 -> 0 | N84: =M84 -> 0 | O84: =N84 -> 0 | ... AC84: =AB84 -> 0
C85: - Equity | D85: (%) | E85: =1-E84 -> 1 | G85: =E85 -> 1 | H85: =G85 -> 1 | I85: =H85 -> 1 | J85: =I85 -> 1 | K85: =J85 -> 1 | L85: =K85 -> 1 | M85: =L85 -> 1 | N85: =M85 -> 1 | O85: =N85 -> 1 | ... AC85: =AB85 -> 1
C87: Opening Borrowings | D87: (INR Cr) | E87: =SUM(G87:AC87) -> 0 | G87: =F92 -> 0 | H87: =G92 -> 0 | I87: =H92 -> 0 | J87: =I92 -> 0 | K87: =J92 -> 0 | L87: =K92 -> 0 | M87: =L92 -> 0 | N87: =M92 -> 0 | ... AC87: =AB92 -> 0
B88: Yes | C88: Add : Further Borrowings | D88: (INR Cr) | E88: =SUM(G88:AC88) -> 0 | G88: =IF($B$88="No",0,MAX(G82*G84,0)) -> 0 | H88: =IF($B$88="No",0,MAX(H82*H84,0)) -> 0 | I88: =IF($B$88="No",0,MAX(I82*I84,0)) -> 0 | J88: =IF($B$88="No",0,MAX(J82*J84,0)) -> 0 | K88: =IF($B$88="No",0,MAX(K82*K84,0)) -> 0 | L88: =IF($B$88="No",0,MAX(L82*L84,0)) -> 0 | M88: =IF($B$88="No",0,MAX(M82*M84,0)) -> 0 | N88: =IF($B$88="No",0,MAX(N82*N84,0)) -> 0 | ... AC88: =IF($B$88="No",0,MAX(AC82*AC84,0)) -> 0
C89: Less : Repayments | D89: (INR Cr) | E89: =SUM(G89:AC89) -> 0 | G89: =F88 -> 0 | H89: =G88 -> 0 | I89: =H88 -> 0 | J89: =I88 -> 0 | K89: =J88 -> 0 | L89: =K88 -> 0 | M89: =L88 -> 0 | N89: =M88 -> 0 | ... AC89: =AB88 -> 0
C90: Add : Interest Cost | D90: (INR Cr) | E90: =SUM(G90:AC90) -> 0 | G90: =+G87*$E$16+G88*$E$16/2 -> 0 | H90: =+H87*$E$16+H88*$E$16/2 -> 0 | I90: =+I87*$E$16+I88*$E$16/2 -> 0 | J90: =+J87*$E$16+J88*$E$16/2 -> 0 | K90: =+K87*$E$16+K88*$E$16/2 -> 0 | L90: =+L87*$E$16+L88*$E$16/2 -> 0 | M90: =+M87*$E$16+M88*$E$16/2 -> 0 | N90: =+N87*$E$16+N88*$E$16/2 -> 0 | ... AC90: =+AC87*$E$16+AC88*$E$16/2 -> 0
C91: Less : Interest Paid | D91: (INR Cr) | E91: =SUM(G91:AC91) -> 0 | G91: =G90 -> 0 | H91: =H90 -> 0 | I91: =I90 -> 0 | J91: =J90 -> 0 | K91: =K90 -> 0 | L91: =L90 -> 0 | M91: =M90 -> 0 | N91: =N90 -> 0 | ... AC91: =AC90 -> 0
C92: Closing Borrowings | D92: (INR Cr) | E92: =SUM(G92:AC92) -> 0 | G92: =+G87+G88-G89+G90-G91 -> 0 | H92: =+H87+H88-H89+H90-H91 -> 0 | I92: =+I87+I88-I89+I90-I91 -> 0 | J92: =+J87+J88-J89+J90-J91 -> 0 | K92: =+K87+K88-K89+K90-K91 -> 0 | L92: =+L87+L88-L89+L90-L91 -> 0 | M92: =+M87+M88-M89+M90-M91 -> 0 | N92: =+N87+N88-N89+N90-N91 -> 0 | ... AC92: =+AC87+AC88-AC89+AC90-AC91 -> 0
C96: Total Interest Cost | D96: (INR Cr) | E96: =SUM(G96:AC96) -> 0 | G96: =G62+G91+G70 -> 0 | H96: =H62+H91+H70 -> 0 | I96: =I62+I91+I70 -> 0 | J96: =J62+J91+J70 -> 0 | K96: =K62+K91+K70 -> 0 | L96: =L62+L91+L70 -> 0 | M96: =M62+M91+M70 -> 0 | N96: =N62+N91+N70 -> 0 | ... AC96: =AC62+AC91+AC70 -> 0
D97: (INR/t) | E97: =IFERROR(E96/E4*10,0) -> 0 | G97: =IFERROR(G96/G4*10,0) -> 0 | H97: =IFERROR(H96/H4*10,0) -> 0 | I97: =IFERROR(I96/I4*10,0) -> 0 | J97: =IFERROR(J96/J4*10,0) -> 0 | K97: =IFERROR(K96/K4*10,0) -> 0 | L97: =IFERROR(L96/L4*10,0) -> 0 | M97: =IFERROR(M96/M4*10,0) -> 0 | N97: =IFERROR(N96/N4*10,0) -> 0 | ... AC97: =IFERROR(AC96/AC4*10,0) -> 0

Sheet Borrowings-MDO
G1: ='Production Schedule'!E1 -> 46023 | H1: ='Production Schedule'!F1 -> 46389 | I1: ='Production Schedule'!G1 -> 46755 | J1: ='Production Schedule'!H1 -> 47121 | K1: ='Production Schedule'!I1 -> 47487 | L1: ='Production Schedule'!J1 -> 47853 | M1: ='Production Schedule'!K1 -> 48219 | N1: ='Production Schedule'!L1 -> 48585 | ... AQ1: ='Production Schedule'!AO1 -> 0
C2: Year No. | G2: ='Production Schedule'!E3 -> -4 | H2: ='Production Schedule'!F3 -> -3 | I2: ='Production Schedule'!G3 -> -2 | J2: ='Production Schedule'!H3 -> -1 | K2: ='Production Schedule'!I3 -> 1 | L2: ='Production Schedule'!J3 -> 2 | M2: ='Production Schedule'!K3 -> 3 | N2: ='Production Schedule'!L3 -> 4 | ... AQ2: ='Production Schedule'!AO3 -> 0
C3: Technical Drivers
C4: Production | D4: Mt | E4: =SUM(G4:AQ4) -> 225.70441 | G4: ='Production Schedule'!E5 -> 0 | H4: ='Production Schedule'!F5 -> 0 | I4: ='Production Schedule'!G5 -> 0 | J4: ='Production Schedule'!H5 -> 0 | K4: ='Production Schedule'!I5 -> 1.9999998 | L4: ='Production Schedule'!J5 -> 3.9999987 | M4: ='Production Schedule'!K5 -> 8.0000007 | N4: ='Production Schedule'!L5 -> 11.999999 | ... AJ4: ='Production Schedule'!AH5 -> 0
C5: Capital Borrowing
C6: Non Funded Capex | D6: (INR Cr) | E6: =SUM(G6:AO6) -> 0 | G6: ='Depreciation-MDO'!H23 -> 0 | H6: ='Depreciation-MDO'!I23 -> 0 | I6: ='Depreciation-MDO'!J23 -> 0 | J6: ='Depreciation-MDO'!K23 -> 0 | K6: ='Depreciation-MDO'!L23 -> 0 | L6: ='Depreciation-MDO'!M23 -> 0 | M6: ='Depreciation-MDO'!N23 -> 0 | N6: ='Depreciation-MDO'!O23 -> 0 | ... AJ6: ='Depreciation-MDO'!AK23 -> 0
B7: Yes | C7: Sustaining Capital | D7: (INR Cr) | E7: =SUM(G7:AO7) -> 0 | G7: ='Depreciation-MDO'!H33 -> 0 | H7: ='Depreciation-MDO'!I33 -> 0 | I7: ='Depreciation-MDO'!J33 -> 0 | J7: ='Depreciation-MDO'!K33 -> 0 | K7: ='Depreciation-MDO'!L33 -> 0 | L7: ='Depreciation-MDO'!M33 -> 0 | M7: ='Depreciation-MDO'!N33 -> 0 | N7: ='Depreciation-MDO'!O33 -> 0 | ... AJ7: ='Depreciation-MDO'!AK33 -> 0
D8: (INR Cr) | E8: =SUM(G8:AO8) -> 0 | G8: =SUM(G6:G7) -> 0 | H8: =SUM(H6:H7) -> 0 | I8: =SUM(I6:I7) -> 0 | J8: =SUM(J6:J7) -> 0 | K8: =SUM(K6:K7) -> 0 | L8: =SUM(L6:L7) -> 0 | M8: =SUM(M6:M7) -> 0 | N8: =SUM(N6:N7) -> 0 | ... AJ8: =SUM(AJ6:AJ7) -> 0
C10: Funded Capex | D10: (INR Cr) | E10: =SUM(G10:AF10) -> 0
C12: Debt : Equity
C13: - Debt | D13: (%) | E13: =IFERROR(E20/E8,0) -> 0 | G13: =Assumptions_Dashboard!$D$148 -> 0 | H13: =G13 -> 0 | I13: =H13 -> 0 | J13: =I13 -> 0 | K13: =J13 -> 0 | L13: =K13 -> 0 | M13: =L13 -> 0 | N13: =M13 -> 0 | O13: =N13 -> 0 | ... AJ13: =AI13 -> 0
C14: - Equity | D14: (%) | E14: =IFERROR(E19/E8,0) -> 0 | G14: =1-G13 -> 1 | H14: =1-H13 -> 1 | I14: =1-I13 -> 1 | J14: =1-J13 -> 1 | K14: =1-K13 -> 1 | L14: =1-L13 -> 1 | M14: =1-M13 -> 1 | N14: =1-N13 -> 1 | ... AJ14: =1-AJ13 -> 1
C16: Interest Rate | D16: (%) | E16: =Assumptions_Dashboard!$D$140 -> 0.1 | G16: =E16 -> 0.1 | H16: =G16 -> 0.1 | I16: =H16 -> 0.1 | J16: =I16 -> 0.1 | K16: =J16 -> 0.1 | L16: =K16 -> 0.1 | M16: =L16 -> 0.1 | N16: =M16 -> 0.1 | O16: =N16 -> 0.1 | ... AJ16: =AI16 -> 0.1
C18: Non Funded Capital Borrowing
C19: Equity Capital | D19: (INR Cr) | E19: =SUM(G19:AO19) -> 0 | G19: =G8-G20 -> 0 | H19: =H8-H20 -> 0 | I19: =I8-I20 -> 0 | J19: =J8-J20 -> 0 | K19: =K8-K20 -> 0 | L19: =L8-L20 -> 0 | M19: =M8-M20 -> 0 | N19: =N8-N20 -> 0 | ... AJ19: =AJ8-AJ20 -> 0
B20: Yes | C20: Debt Schedule | D20: (INR Cr) | E20: =SUM(G20:AO20) -> 0 | F20: =SUM(E19:E20)=E8 -> TRUE | G20: =IF($B$20="No",0,G8*G13) -> 0 | H20: =IF($B$20="No",0,H8*H13) -> 0 | I20: =IF($B$20="No",0,I8*I13) -> 0 | J20: =IF($B$20="No",0,J8*J13) -> 0 | K20: =IF($B$20="No",0,K8*K13) -> 0 | L20: =IF($B$20="No",0,L8*L13) -> 0 | M20: =IF($B$20="No",0,M8*M13) -> 0 | N20: =IF($B$20="No",0,N8*N13) -> 0 | ... AJ20: =IF($B$20="No",0,AJ8*AJ13) -> 0
C22: Opening Borrowings | D22: (INR Cr) | G22: =F63 -> 0 | H22: =G63 -> 0 | I22: =H63 -> 0 | J22: =I63 -> 0 | K22: =J63 -> 0 | L22: =K63 -> 0 | M22: =L63 -> 0 | N22: =M63 -> 0 | ... AJ22: =AI63 -> 0
C23: Add : Further Borrowings | D23: (INR Cr) | E23: =SUM(G23:AO23) -> 0 | G23: =+IF(G20>0,G20,0) -> 0 | H23: =+IF(H20>0,H20,0) -> 0 | I23: =+IF(I20>0,I20,0) -> 0 | J23: =+IF(J20>0,J20,0) -> 0 | K23: =+IF(K20>0,K20,0) -> 0 | L23: =+IF(L20>0,L20,0) -> 0 | M23: =+IF(M20>0,M20,0) -> 0 | N23: =+IF(N20>0,N20,0) -> 0 | ... AJ23: =+IF(AJ20>0,AJ20,0) -> 0
C24: Less : Repayments | D24: (INR Cr) | E24: =SUM(G24:AO24) -> 0 | G24: =SUM(G25:G59) -> 0 | H24: =SUM(H25:H59) -> 0 | I24: =SUM(I25:I59) -> 0 | J24: =SUM(J25:J59) -> 0 | K24: =SUM(K25:K59) -> 0 | L24: =SUM(L25:L59) -> 0 | M24: =SUM(M25:M59) -> 0 | N24: =SUM(N25:N59) -> 0 | ... AJ24: =SUM(AJ25:AJ59) -> 0
C25: {=TRANSPOSE(G2:AO2)} -> -4 | D25: (INR Cr) | E25: =SUM(G25:AO25) -> 0 | K25: =$G20/7 -> 0 | L25: =$G20/7 -> 0 | M25: =$G20/7 -> 0 | N25: =$G20/7 -> 0 | O25: =$G20/7 -> 0 | P25: =$G20/7 -> 0 | Q25: =$G20/7 -> 0
C26: -3 | D26: (INR Cr) | E26: =SUM(G26:AO26) -> 0 | K26: =$H20/7 -> 0 | L26: =$H20/7 -> 0 | M26: =$H20/7 -> 0 | N26: =$H20/7 -> 0 | O26: =$H20/7 -> 0 | P26: =$H20/7 -> 0 | Q26: =$H20/7 -> 0
C27: -2 | D27: (INR Cr) | E27: =SUM(G27:AO27) -> 0 | K27: =$I20/7 -> 0 | L27: =$I20/7 -> 0 | M27: =$I20/7 -> 0 | N27: =$I20/7 -> 0 | O27: =$I20/7 -> 0 | P27: =$I20/7 -> 0 | Q27: =$I20/7 -> 0
C28: -1 | D28: (INR Cr) | E28: =SUM(G28:AO28) -> 0 | K28: =$J20/7 -> 0 | L28: =$J20/7 -> 0 | M28: =$J20/7 -> 0 | N28: =$J20/7 -> 0 | O28: =$J20/7 -> 0 | P28: =$J20/7 -> 0 | Q28: =$J20/7 -> 0
C29: 1 | D29: (INR Cr) | E29: =SUM(G29:AO29) -> 0 | L29: =$K20/7 -> 0 | M29: =$K20/7 -> 0 | N29: =$K20/7 -> 0 | O29: =$K20/7 -> 0 | P29: =$K20/7 -> 0 | Q29: =$K20/7 -> 0 | R29: =$K20/7 -> 0
C30: 2 | D30: (INR Cr) | E30: =SUM(G30:AO30) -> 0 | M30: =$L20/7 -> 0 | N30: =$L20/7 -> 0 | O30: =$L20/7 -> 0 | P30: =$L20/7 -> 0 | Q30: =$L20/7 -> 0 | R30: =$L20/7 -> 0 | S30: =$L20/7 -> 0
C31: 3 | D31: (INR Cr) | E31: =SUM(G31:AO31) -> 0 | N31: =$M20/7 -> 0 | O31: =$M20/7 -> 0 | P31: =$M20/7 -> 0 | Q31: =$M20/7 -> 0 | R31: =$M20/7 -> 0 | S31: =$M20/7 -> 0 | T31: =$M20/7 -> 0
C32: 4 | D32: (INR Cr) | E32: =SUM(G32:AO32) -> 0 | O32: =$N20/7 -> 0 | P32: =$N20/7 -> 0 | Q32: =$N20/7 -> 0 | R32: =$N20/7 -> 0 | S32: =$N20/7 -> 0 | T32: =$N20/7 -> 0 | U32: =$N20/7 -> 0
C33: 5 | D33: (INR Cr) | E33: =SUM(G33:AO33) -> 0 | P33: =$O20/7 -> 0 | Q33: =$O20/7 -> 0 | R33: =$O20/7 -> 0 | S33: =$O20/7 -> 0 | T33: =$O20/7 -> 0 | U33: =$O20/7 -> 0 | V33: =$O20/7 -> 0
C34: 6 | D34: (INR Cr) | E34: =SUM(G34:AO34) -> 0 | Q34: =$P20/7 -> 0 | R34: =$P20/7 -> 0 | S34: =$P20/7 -> 0 | T34: =$P20/7 -> 0 | U34: =$P20/7 -> 0 | V34: =$P20/7 -> 0 | W34: =$P20/7 -> 0
C35: 7 | D35: (INR Cr) | E35: =SUM(G35:AO35) -> 0 | R35: =$Q20/7 -> 0 | S35: =$Q20/7 -> 0 | T35: =$Q20/7 -> 0 | U35: =$Q20/7 -> 0 | V35: =$Q20/7 -> 0 | W35: =$Q20/7 -> 0 | X35: =$Q20/7 -> 0
C36: 8 | D36: (INR Cr) | E36: =SUM(G36:AO36) -> 0 | S36: =$R20/7 -> 0 | T36: =$R20/7 -> 0 | U36: =$R20/7 -> 0 | V36: =$R20/7 -> 0 | W36: =$R20/7 -> 0 | X36: =$R20/7 -> 0 | Y36: =$R20/7 -> 0
C37: 9 | D37: (INR Cr) | E37: =SUM(G37:AO37) -> 0 | T37: =$S20/7 -> 0 | U37: =$S20/7 -> 0 | V37: =$S20/7 -> 0 | W37: =$S20/7 -> 0 | X37: =$S20/7 -> 0 | Y37: =$S20/7 -> 0 | Z37: =$S20/7 -> 0
C38: 10 | D38: (INR Cr) | E38: =SUM(G38:AO38) -> 0 | U38: =$T20/7 -> 0 | V38: =$T20/7 -> 0 | W38: =$T20/7 -> 0 | X38: =$T20/7 -> 0 | Y38: =$T20/7 -> 0 | Z38: =$T20/7 -> 0 | AA38: =$T20/7 -> 0
C39: 11 | D39: (INR Cr) | E39: =SUM(G39:AO39) -> 0 | V39: =$U20/7 -> 0 | W39: =$U20/7 -> 0 | X39: =$U20/7 -> 0 | Y39: =$U20/7 -> 0 | Z39: =$U20/7 -> 0 | AA39: =$U20/7 -> 0 | AB39: =$U20/7 -> 0
C40: 12 | D40: (INR Cr) | E40: =SUM(G40:AO40) -> 0 | W40: =$V20/7 -> 0 | X40: =$V20/7 -> 0 | Y40: =$V20/7 -> 0 | Z40: =$V20/7 -> 0 | AA40: =$V20/7 -> 0 | AB40: =$V20/7 -> 0 | AC40: =$V20/7 -> 0
C41: 13 | D41: (INR Cr) | E41: =SUM(G41:AO41) -> 0 | X41: =$W20/7 -> 0 | Y41: =$W20/7 -> 0 | Z41: =$W20/7 -> 0 | AA41: =$W20/7 -> 0 | AB41: =$W20/7 -> 0 | AC41: =$W20/7 -> 0 | AD41: =$W20/7 -> 0
C42: 14 | D42: (INR Cr) | E42: =SUM(G42:AO42) -> 0 | Y42: =$X20/7 -> 0 | Z42: =$X20/7 -> 0 | AA42: =$X20/7 -> 0 | AB42: =$X20/7 -> 0 | AC42: =$X20/7 -> 0 | AD42: =$X20/7 -> 0 | AE42: =$X20/7 -> 0
C43: 15 | D43: (INR Cr) | E43: =SUM(G43:AO43) -> 0 | Z43: =$Y20/7 -> 0 | AA43: =$Y20/7 -> 0 | AB43: =$Y20/7 -> 0 | AC43: =$Y20/7 -> 0 | AD43: =$Y20/7 -> 0 | AE43: =$Y20/7 -> 0 | AF43: =$Y20/7 -> 0
C44: 16 | D44: (INR Cr) | E44: =SUM(G44:AO44) -> 0 | AA44: =$Z20/7 -> 0 | AB44: =$Z20/7 -> 0 | AC44: =$Z20/7 -> 0 | AD44: =$Z20/7 -> 0 | AE44: =$Z20/7 -> 0 | AF44: =$Z20/7 -> 0 | AG44: =$Z20/7 -> 0
C45: 17 | D45: (INR Cr) | E45: =SUM(G45:AO45) -> 0 | AB45: =$AA20/7 -> 0 | AC45: =$AA20/7 -> 0 | AD45: =$AA20/7 -> 0 | AE45: =$AA20/7 -> 0 | AF45: =$AA20/7 -> 0 | AG45: =$AA20/7 -> 0 | AH45: =$AA20/7 -> 0
C46: 18 | D46: (INR Cr) | E46: =SUM(G46:AO46) -> 0 | AC46: =$AB20/7 -> 0 | AD46: =$AB20/7 -> 0 | AE46: =$AB20/7 -> 0 | AF46: =$AB20/7 -> 0 | AG46: =$AB20/7 -> 0 | AH46: =$AB20/7 -> 0 | AI46: =$AB20/7 -> 0
C47: 19 | D47: (INR Cr) | E47: =SUM(G47:AO47) -> 0 | AD47: =$AC20/7 -> 0 | AE47: =$AC20/7 -> 0 | AF47: =$AC20/7 -> 0 | AG47: =$AC20/7 -> 0 | AH47: =$AC20/7 -> 0 | AI47: =$AC20/7 -> 0 | AJ47: =$AC20/7 -> 0
C48: 0 | D48: (INR Cr) | E48: =SUM(G48:AO48) -> 0 | AE48: =$AD20/6 -> 0 | AF48: =$AD20/6 -> 0 | AG48: =$AD20/6 -> 0 | AH48: =$AD20/6 -> 0 | AI48: =$AD20/6 -> 0 | AJ48: =$AD20/6 -> 0
C49: 0 | D49: (INR Cr) | E49: =SUM(G49:AO49) -> 0 | AF49: =$AE20/5 -> 0 | AG49: =$AE20/5 -> 0 | AH49: =$AE20/5 -> 0 | AI49: =$AE20/5 -> 0 | AJ49: =$AE20/5 -> 0
C50: 0 | D50: (INR Cr) | E50: =SUM(G50:AO50) -> 0 | AG50: =$AF20/4 -> 0 | AH50: =$AF20/4 -> 0 | AI50: =$AF20/4 -> 0 | AJ50: =$AF20/4 -> 0
C51: 0 | D51: (INR Cr) | E51: =SUM(G51:AO51) -> 0 | AH51: =$AG20/3 -> 0 | AI51: =$AG20/3 -> 0 | AJ51: =$AG20/3 -> 0
C52: 0 | D52: (INR Cr) | E52: =SUM(G52:AO52) -> 0 | AI52: =$AH20/2 -> 0 | AJ52: =$AH20/2 -> 0
C53: 0 | D53: (INR Cr) | E53: =SUM(G53:AO53) -> 0 | AJ53: =$AI20/1 -> 0
C54: 0 | D54: (INR Cr) | E54: =SUM(G54:AO54) -> 0
C55: 0 | D55: (INR Cr) | E55: =SUM(G55:AO55) -> 0
C56: 0 | D56: (INR Cr) | E56: =SUM(G56:AO56) -> 0
C57: 0 | D57: (INR Cr) | E57: =SUM(G57:AO57) -> 0
C58: 0 | D58: (INR Cr) | E58: =SUM(G58:AO58) -> 0
C59: 0 | D59: (INR Cr) | E59: =SUM(G59:AO59) -> 0
C61: Add : Interest Cost | D61: (INR Cr) | E61: =SUM(G61:AO61) -> 0 | G61: =(G22-G24)*G16+G23*G16*0.5+G24*G16*0.5 -> 0 | H61: =(H22-H24)*H16+H23*H16*0.5+H24*H16*0.5 -> 0 | I61: =(I22-I24)*I16+I23*I16*0.5+I24*I16*0.5 -> 0 | J61: =(J22-J24)*J16+J23*J16*0.5+J24*J16*0.5 -> 0 | K61: =(K22-K24)*K16+K23*K16*0.5+K24*K16*0.5 -> 0 | L61: =(L22-L24)*L16+L23*L16*0.5+L24*L16*0.5 -> 0 | M61: =(M22-M24)*M16+M23*M16*0.5+M24*M16*0.5 -> 0 | N61: =(N22-N24)*N16+N23*N16*0.5+N24*N16*0.5 -> 0 | ... AJ61: =(AJ22-AJ24)*AJ16+AJ23*AJ16*0.5+AJ24*AJ16*0.5 -> 0
C62: Less : Interest Paid | D62: (INR Cr) | E62: =SUM(G62:AO62) -> 0 | G62: =G61 -> 0 | H62: =H61 -> 0 | I62: =I61 -> 0 | J62: =J61 -> 0 | K62: =K61 -> 0 | L62: =L61 -> 0 | M62: =M61 -> 0 | N62: =N61 -> 0 | ... AJ62: =AJ61 -> 0
C63: Closing Borrowings | D63: (INR Cr) | G63: =G22+G23-G24+G61-G62 -> 0 | H63: =H22+H23-H24+H61-H62 -> 0 | I63: =I22+I23-I24+I61-I62 -> 0 | J63: =J22+J23-J24+J61-J62 -> 0 | K63: =K22+K23-K24+K61-K62 -> 0 | L63: =L22+L23-L24+L61-L62 -> 0 | M63: =M22+M23-M24+M61-M62 -> 0 | N63: =N22+N23-N24+N61-N62 -> 0 | ... AJ63: =AJ22+AJ23-AJ24+AJ61-AJ62 -> 0
C65: Funded Capital Borrowing
C66: Opening Borrowings | D66: (INR Cr) | G66: =F71 -> 0 | H66: =G71 -> 0 | I66: =H71 -> 0 | J66: =I71 -> 0 | K66: =J71 -> 0 | L66: =K71 -> 0 | M66: =L71 -> 0 | N66: =M71 -> 0 | ... AJ66: =AI71 -> 0
C67: Add : Further Borrowings | D67: (INR Cr) | E67: =SUM(G67:AO67) -> 0 | G67: =G10*G13 -> 0 | H67: =H10*H13 -> 0 | I67: =I10*I13 -> 0 | J67: =J10*J13 -> 0 | K67: =K10*K13 -> 0 | L67: =L10*L13 -> 0 | M67: =M10*M13 -> 0 | N67: =N10*N13 -> 0 | ... AJ67: =AJ10*AJ13 -> 0
C68: Less : Repayments | D68: (INR Cr) | E68: =SUM(G68:AO68) -> 0
C69: Add : Interest Cost | D69: (INR Cr) | E69: =SUM(G69:AO69) -> 0 | G69: =(G66-G68)*G16+G67*G16*0.5+G68*G16*0.5 -> 0 | H69: =(H66-H68)*H16+H67*H16*0.5+H68*H16*0.5 -> 0 | I69: =(I66-I68)*I16+I67*I16*0.5+I68*I16*0.5 -> 0 | J69: =(J66-J68)*J16+J67*J16*0.5+J68*J16*0.5 -> 0 | K69: =(K66-K68)*K16+K67*K16*0.5+K68*K16*0.5 -> 0 | L69: =(L66-L68)*L16+L67*L16*0.5+L68*L16*0.5 -> 0 | M69: =(M66-M68)*M16+M67*M16*0.5+M68*M16*0.5 -> 0 | N69: =(N66-N68)*N16+N67*N16*0.5+N68*N16*0.5 -> 0 | ... AJ69: =(AJ66-AJ68)*AJ16+AJ67*AJ16*0.5+AJ68*AJ16*0.5 -> 0
C70: Less : Interest Paid | D70: (INR Cr) | E70: =SUM(G70:AO70) -> 0 | G70: =G69 -> 0 | H70: =H69 -> 0 | I70: =I69 -> 0 | J70: =J69 -> 0 | K70: =K69 -> 0 | L70: =L69 -> 0 | M70: =M69 -> 0 | N70: =N69 -> 0 | ... AJ70: =AJ69 -> 0
C71: Closing Borrowings | D71: (INR Cr) | G71: =G66+G67-G68+G69-G70 -> 0 | H71: =H66+H67-H68+H69-H70 -> 0 | I71: =I66+I67-I68+I69-I70 -> 0 | J71: =J66+J67-J68+J69-J70 -> 0 | K71: =K66+K67-K68+K69-K70 -> 0 | L71: =L66+L67-L68+L69-L70 -> 0 | M71: =M66+M67-M68+M69-M70 -> 0 | N71: =N66+N67-N68+N69-N70 -> 0 | ... AJ71: =AJ66+AJ67-AJ68+AJ69-AJ70 -> 0
C75: Working Capital Borrowing
B76: 45 | C76: Accounts Receivable | D76: (INR Cr) | E76: =SUM(G76:AO76) -> 0 | G76: =$B$76/365*(0) -> 0 | H76: =$B$76/365*(0) -> 0 | I76: =$B$76/365*(0) -> 0 | J76: =$B$76/365*(0) -> 0 | K76: =$B$76/365*(0) -> 0 | L76: =$B$76/365*(0) -> 0 | M76: =$B$76/365*(0) -> 0 | N76: =$B$76/365*(0) -> 0 | ... AJ76: =$B$76/365*(0) -> 0
B77: 30 | C77: Inventory | D77: (INR Cr) | E77: =SUM(G77:AO77) -> 0 | G77: =$B$77/365*(0) -> 0 | H77: =$B$77/365*(0) -> 0 | I77: =$B$77/365*(0) -> 0 | J77: =$B$77/365*(0) -> 0 | K77: =$B$77/365*(0) -> 0 | L77: =$B$77/365*(0) -> 0 | M77: =$B$77/365*(0) -> 0 | N77: =$B$77/365*(0) -> 0 | ... AJ77: =$B$77/365*(0) -> 0
B78: 21 | C78: Accounts Payable | D78: (INR Cr) | E78: =SUM(G78:AO78) -> 0 | G78: =$B$78/365*(0) -> 0 | H78: =$B$78/365*(0) -> 0 | I78: =$B$78/365*(0) -> 0 | J78: =$B$78/365*(0) -> 0 | K78: =$B$78/365*(0) -> 0 | L78: =$B$78/365*(0) -> 0 | M78: =$B$78/365*(0) -> 0 | N78: =$B$78/365*(0) -> 0 | ... AJ78: =$B$78/365*(0) -> 0
C79: Total Working Capital | D79: (INR Cr) | E79: =SUM(G79:AO79) -> 0 | G79: =SUM(G76:G77)-G78 -> 0 | H79: =SUM(H76:H77)-H78 -> 0 | I79: =SUM(I76:I77)-I78 -> 0 | J79: =SUM(J76:J77)-J78 -> 0 | K79: =SUM(K76:K77)-K78 -> 0 | L79: =SUM(L76:L77)-L78 -> 0 | M79: =SUM(M76:M77)-M78 -> 0 | N79: =SUM(N76:N77)-N78 -> 0 | ... AJ79: =SUM(AJ76:AJ77)-AJ78 -> 0
C80: Change in Working Capital | D80: (INR Cr) | E80: =SUM(G80:AO80) -> 0 | G80: =G79 -> 0 | H80: =H79-G79 -> 0 | I80: =I79-H79 -> 0 | J80: =J79-I79 -> 0 | K80: =K79-J79 -> 0 | L80: =L79-K79 -> 0 | M80: =M79-L79 -> 0 | N80: =N79-M79 -> 0 | O80: =O79-N79 -> 0 | ... AJ80: =AJ79-AI79 -> 0
B81: Yes | C81: Working Capital | D81: (INR Cr) | E81: =SUM(G81:AO81) -> 0 | G81: =IF($B$81="Yes",G80,0) -> 0 | H81: =IF($B$81="Yes",H80,0) -> 0 | I81: =IF($B$81="Yes",I80,0) -> 0 | J81: =IF($B$81="Yes",J80,0) -> 0 | K81: =IF($B$81="Yes",K80,0) -> 0 | L81: =IF($B$81="Yes",L80,0) -> 0 | M81: =IF($B$81="Yes",M80,0) -> 0 | N81: =IF($B$81="Yes",N80,0) -> 0 | ... AJ81: =IF($B$81="Yes",AJ80,0) -> 0
C82: Total | D82: (INR Cr) | E82: =SUM(G82:AO82) -> 0 | G82: =G81 -> 0 | H82: =H81 -> 0 | I82: =I81 -> 0 | J82: =J81 -> 0 | K82: =K81 -> 0 | L82: =L81 -> 0 | M82: =M81 -> 0 | N82: =N81 -> 0 | ... AJ82: =AJ81 -> 0
C83: Debt : Equity
C84: - Debt | D84: (%) | E84: =E13 -> 0 | G84: =E84 -> 0 | H84: =G84 -> 0 | I84: =H84 -> 0 | J84: =I84 -> 0 | K84: =J84 -> 0 | L84: =K84 -> 0 | M84: =L84 -> 0 | N84: =M84 -> 0 | O84: =N84 -> 0 | ... AJ84: =AI84 -> 0
C85: - Equity | D85: (%) | E85: =1-E84 -> 1 | G85: =E85 -> 1 | H85: =G85 -> 1 | I85: =H85 -> 1 | J85: =I85 -> 1 | K85: =J85 -> 1 | L85: =K85 -> 1 | M85: =L85 -> 1 | N85: =M85 -> 1 | O85: =N85 -> 1 | ... AJ85: =AI85 -> 1
C87: Opening Borrowings | D87: (INR Cr) | E87: =SUM(G87:AO87) -> 0 | G87: =F92 -> 0 | H87: =G92 -> 0 | I87: =H92 -> 0 | J87: =I92 -> 0 | K87: =J92 -> 0 | L87: =K92 -> 0 | M87: =L92 -> 0 | N87: =M92 -> 0 | ... AJ87: =AI92 -> 0
B88: Yes | C88: Add : Further Borrowings | D88: (INR Cr) | E88: =SUM(G88:AO88) -> 0 | G88: =IF($B$88="No",0,MAX(G82*G84,0)) -> 0 | H88: =IF($B$88="No",0,MAX(H82*H84,0)) -> 0 | I88: =IF($B$88="No",0,MAX(I82*I84,0)) -> 0 | J88: =IF($B$88="No",0,MAX(J82*J84,0)) -> 0 | K88: =IF($B$88="No",0,MAX(K82*K84,0)) -> 0 | L88: =IF($B$88="No",0,MAX(L82*L84,0)) -> 0 | M88: =IF($B$88="No",0,MAX(M82*M84,0)) -> 0 | N88: =IF($B$88="No",0,MAX(N82*N84,0)) -> 0 | ... AJ88: =IF($B$88="No",0,MAX(AJ82*AJ84,0)) -> 0
C89: Less : Repayments | D89: (INR Cr) | E89: =SUM(G89:AO89) -> 0 | G89: =F88 -> 0 | H89: =G88 -> 0 | I89: =H88 -> 0 | J89: =I88 -> 0 | K89: =J88 -> 0 | L89: =K88 -> 0 | M89: =L88 -> 0 | N89: =M88 -> 0 | ... AJ89: =AI88 -> 0
C90: Add : Interest Cost | D90: (INR Cr) | E90: =SUM(G90:AO90) -> 0 | G90: =+G87*$E$16+G88*$E$16/2 -> 0 | H90: =+H87*$E$16+H88*$E$16/2 -> 0 | I90: =+I87*$E$16+I88*$E$16/2 -> 0 | J90: =+J87*$E$16+J88*$E$16/2 -> 0 | K90: =+K87*$E$16+K88*$E$16/2 -> 0 | L90: =+L87*$E$16+L88*$E$16/2 -> 0 | M90: =+M87*$E$16+M88*$E$16/2 -> 0 | N90: =+N87*$E$16+N88*$E$16/2 -> 0 | ... AJ90: =+AJ87*$E$16+AJ88*$E$16/2 -> 0
C91: Less : Interest Paid | D91: (INR Cr) | E91: =SUM(G91:AO91) -> 0 | G91: =G90 -> 0 | H91: =H90 -> 0 | I91: =I90 -> 0 | J91: =J90 -> 0 | K91: =K90 -> 0 | L91: =L90 -> 0 | M91: =M90 -> 0 | N91: =N90 -> 0 | ... AJ91: =AJ90 -> 0
C92: Closing Borrowings | D92: (INR Cr) | E92: =SUM(G92:AO92) -> 0 | G92: =+G87+G88-G89+G90-G91 -> 0 | H92: =+H87+H88-H89+H90-H91 -> 0 | I92: =+I87+I88-I89+I90-I91 -> 0 | J92: =+J87+J88-J89+J90-J91 -> 0 | K92: =+K87+K88-K89+K90-K91 -> 0 | L92: =+L87+L88-L89+L90-L91 -> 0 | M92: =+M87+M88-M89+M90-M91 -> 0 | N92: =+N87+N88-N89+N90-N91 -> 0 | ... AJ92: =+AJ87+AJ88-AJ89+AJ90-AJ91 -> 0
C96: Total Interest Cost | D96: (INR Cr) | E96: =SUM(G96:AO96) -> 0 | G96: =G62+G91+G70 -> 0 | H96: =H62+H91+H70 -> 0 | I96: =I62+I91+I70 -> 0 | J96: =J62+J91+J70 -> 0 | K96: =K62+K91+K70 -> 0 | L96: =L62+L91+L70 -> 0 | M96: =M62+M91+M70 -> 0 | N96: =N62+N91+N70 -> 0 | ... AJ96: =AJ62+AJ91+AJ70 -> 0
D97: (INR/t) | E97: =IFERROR(E96/E4*10,0) -> 0 | G97: =IFERROR(G96/G4*10,0) -> 0 | H97: =IFERROR(H96/H4*10,0) -> 0 | I97: =IFERROR(I96/I4*10,0) -> 0 | J97: =IFERROR(J96/J4*10,0) -> 0 | K97: =IFERROR(K96/K4*10,0) -> 0 | L97: =IFERROR(L96/L4*10,0) -> 0 | M97: =IFERROR(M96/M4*10,0) -> 0 | N97: =IFERROR(N96/N4*10,0) -> 0 | ... AJ97: =IFERROR(AJ96/AJ4*10,0) -> 0

Sheet Depreciation-Owner
C2: Depreciation Estimation | H2: ='Production Schedule'!E1 -> 46023 | I2: ='Production Schedule'!F1 -> 46389 | J2: ='Production Schedule'!G1 -> 46755 | K2: ='Production Schedule'!H1 -> 47121 | L2: ='Production Schedule'!I1 -> 47487 | M2: ='Production Schedule'!J1 -> 47853 | N2: ='Production Schedule'!K1 -> 48219 | O2: ='Production Schedule'!L1 -> 48585 | ... AD2: ='Production Schedule'!AA1 -> 54075
D3: Unit | E3: Total | H3: ='Production Schedule'!E3 -> -4 | I3: ='Production Schedule'!F3 -> -3 | J3: ='Production Schedule'!G3 -> -2 | K3: ='Production Schedule'!H3 -> -1 | L3: ='Production Schedule'!I3 -> 1 | M3: ='Production Schedule'!J3 -> 2 | N3: ='Production Schedule'!K3 -> 3 | O3: ='Production Schedule'!L3 -> 4 | ... AD3: ='Production Schedule'!AA3 -> 19
C4: Production | D4: Mt | E4: =SUM(H4:AX4) -> 225.70441 | H4: ='Production Schedule'!E5 -> 0 | I4: ='Production Schedule'!F5 -> 0 | J4: ='Production Schedule'!G5 -> 0 | K4: ='Production Schedule'!H5 -> 0 | L4: ='Production Schedule'!I5 -> 1.9999998 | M4: ='Production Schedule'!J5 -> 3.9999987 | N4: ='Production Schedule'!K5 -> 8.0000007 | O4: ='Production Schedule'!L5 -> 11.999999 | ... AD4: ='Production Schedule'!AA5 -> 2.2043909
C5: Waste Removal | D5: Mbcm | E5: =SUM(H5:AX5) -> 535.39467 | H5: ='Production Schedule'!E8 -> 0 | I5: ='Production Schedule'!F8 -> 0 | J5: ='Production Schedule'!G8 -> 0 | K5: ='Production Schedule'!H8 -> 0 | L5: ='Production Schedule'!I8 -> 11.466046 | M5: ='Production Schedule'!J8 -> 9.5178188 | N5: ='Production Schedule'!K8 -> 17.240515 | O5: ='Production Schedule'!L8 -> 36.817196 | ... AD5: ='Production Schedule'!AA8 -> 1.2764738
C6: Waste Rehandle | D6: Mbcm | E6: =SUM(H6:AX6) -> 75.64 | H6: ='Production Schedule'!E13 -> 0 | I6: ='Production Schedule'!F13 -> 0 | J6: ='Production Schedule'!G13 -> 0 | K6: ='Production Schedule'!H13 -> 0 | L6: ='Production Schedule'!I13 -> 0 | M6: ='Production Schedule'!J13 -> 0 | N6: ='Production Schedule'!K13 -> 0 | O6: ='Production Schedule'!L13 -> 0 | ... AD6: ='Production Schedule'!AA13 -> 0
C7: Average Material Handling (AMH) | D7: Mbcm | E7: =SUM(H7:AX7) -> 742.25817 | H7: =(H4/Assumptions_Dashboard!$D$32)+H5+H6 -> 0 | I7: =(I4/Assumptions_Dashboard!$D$32)+I5+I6 -> 0 | J7: =(J4/Assumptions_Dashboard!$D$32)+J5+J6 -> 0 | K7: =(K4/Assumptions_Dashboard!$D$32)+K5+K6 -> 0 | L7: =(L4/Assumptions_Dashboard!$D$32)+L5+L6 -> 12.628836 | M7: =(M4/Assumptions_Dashboard!$D$32)+M5+M6 -> 11.843399 | N7: =(N4/Assumptions_Dashboard!$D$32)+N5+N6 -> 21.891678 | O7: =(O4/Assumptions_Dashboard!$D$32)+O5+O6 -> 43.793939 | ... AD7: =(AD4/Assumptions_Dashboard!$D$32)+AD5+AD6 -> 2.5580965
C8: Capital Expenditure
B9: Yes | C9: ='Owner CAPEX'!B11 -> Pre-operative costs | E9: =SUM(H9:AX9) -> 214.12704 | H9: =IF($B9="Yes",'Owner CAPEX'!E11,0)*(1+Sensitivity!$C$4) -> 114.11026 | I9: =IF($B9="Yes",'Owner CAPEX'!F11,0)*(1+Sensitivity!$C$4) -> 32.27026 | J9: =IF($B9="Yes",'Owner CAPEX'!G11,0)*(1+Sensitivity!$C$4) -> 33.45826 | K9: =IF($B9="Yes",'Owner CAPEX'!H11,0)*(1+Sensitivity!$C$4) -> 34.28826 | L9: =IF($B9="Yes",'Owner CAPEX'!I11,0)*(1+Sensitivity!$C$4) -> 0 | M9: =IF($B9="Yes",'Owner CAPEX'!J11,0)*(1+Sensitivity!$C$4) -> 0 | N9: =IF($B9="Yes",'Owner CAPEX'!K11,0)*(1+Sensitivity!$C$4) -> 0 | O9: =IF($B9="Yes",'Owner CAPEX'!L11,0)*(1+Sensitivity!$C$4) -> 0 | ... AD9: =IF($B9="Yes",'Owner CAPEX'!AA11,0)*(1+Sensitivity!$C$4) -> 0
B10: Yes | C10: ='Owner CAPEX'!B12 -> Upfront Amount | E10: =SUM(H10:AX10) -> 99.07 | H10: =IF($B10="Yes",'Owner CAPEX'!E12,0)*(1+Sensitivity!$C$4) -> 24.7675 | I10: =IF($B10="Yes",'Owner CAPEX'!F12,0)*(1+Sensitivity!$C$4) -> 0 | J10: =IF($B10="Yes",'Owner CAPEX'!G12,0)*(1+Sensitivity!$C$4) -> 0 | K10: =IF($B10="Yes",'Owner CAPEX'!H12,0)*(1+Sensitivity!$C$4) -> 24.7675 | L10: =IF($B10="Yes",'Owner CAPEX'!I12,0)*(1+Sensitivity!$C$4) -> 49.535 | M10: =IF($B10="Yes",'Owner CAPEX'!J12,0)*(1+Sensitivity!$C$4) -> 0 | N10: =IF($B10="Yes",'Owner CAPEX'!K12,0)*(1+Sensitivity!$C$4) -> 0 | O10: =IF($B10="Yes",'Owner CAPEX'!L12,0)*(1+Sensitivity!$C$4) -> 0 | ... AD10: =IF($B10="Yes",'Owner CAPEX'!AA12,0)*(1+Sensitivity!$C$4) -> 0
B11: Yes | C11: ='Owner CAPEX'!B13 -> Land Cost | E11: =SUM(H11:AX11) -> 985.07802 | H11: =IF($B11="Yes",'Owner CAPEX'!E13,0)*(1+Sensitivity!$C$4) -> 0 | I11: =IF($B11="Yes",'Owner CAPEX'!F13,0)*(1+Sensitivity!$C$4) -> 147.76226 | J11: =IF($B11="Yes",'Owner CAPEX'!G13,0)*(1+Sensitivity!$C$4) -> 98.508174 | K11: =IF($B11="Yes",'Owner CAPEX'!H13,0)*(1+Sensitivity!$C$4) -> 98.508174 | L11: =IF($B11="Yes",'Owner CAPEX'!I13,0)*(1+Sensitivity!$C$4) -> 95.8787 | M11: =IF($B11="Yes",'Owner CAPEX'!J13,0)*(1+Sensitivity!$C$4) -> 58.261429 | N11: =IF($B11="Yes",'Owner CAPEX'!K13,0)*(1+Sensitivity!$C$4) -> 73.814176 | O11: =IF($B11="Yes",'Owner CAPEX'!L13,0)*(1+Sensitivity!$C$4) -> 134.22055 | ... AD11: =IF($B11="Yes",'Owner CAPEX'!AA13,0)*(1+Sensitivity!$C$4) -> 0
B12: Yes | C12: ='Owner CAPEX'!B14 -> R&R Cost | E12: =SUM(H12:AX12) -> 1048.57 | H12: =IF($B12="Yes",'Owner CAPEX'!E14,0)*(1+Sensitivity!$C$4) -> 0 | I12: =IF($B12="Yes",'Owner CAPEX'!F14,0)*(1+Sensitivity!$C$4) -> 0 | J12: =IF($B12="Yes",'Owner CAPEX'!G14,0)*(1+Sensitivity!$C$4) -> 0 | K12: =IF($B12="Yes",'Owner CAPEX'!H14,0)*(1+Sensitivity!$C$4) -> 0 | L12: =IF($B12="Yes",'Owner CAPEX'!I14,0)*(1+Sensitivity!$C$4) -> 0 | M12: =IF($B12="Yes",'Owner CAPEX'!J14,0)*(1+Sensitivity!$C$4) -> 0 | N12: =IF($B12="Yes",'Owner CAPEX'!K14,0)*(1+Sensitivity!$C$4) -> 0 | O12: =IF($B12="Yes",'Owner CAPEX'!L14,0)*(1+Sensitivity!$C$4) -> 104.857 | ... AD12: =IF($B12="Yes",'Owner CAPEX'!AA14,0)*(1+Sensitivity!$C$4) -> 0
B13: Yes | C13: ='Owner CAPEX'!B15 -> HEMM Equipment | E13: =SUM(H13:AX13) -> 701.51584 | H13: =IF($B13="Yes",'Owner CAPEX'!E15,0)*(1+Sensitivity!$C$4) -> 0 | I13: =IF($B13="Yes",'Owner CAPEX'!F15,0)*(1+Sensitivity!$C$4) -> 0 | J13: =IF($B13="Yes",'Owner CAPEX'!G15,0)*(1+Sensitivity!$C$4) -> 0 | K13: =IF($B13="Yes",'Owner CAPEX'!H15,0)*(1+Sensitivity!$C$4) -> 0 | L13: =IF($B13="Yes",'Owner CAPEX'!I15,0)*(1+Sensitivity!$C$4) -> 134.12608 | M13: =IF($B13="Yes",'Owner CAPEX'!J15,0)*(1+Sensitivity!$C$4) -> 14.8766 | N13: =IF($B13="Yes",'Owner CAPEX'!K15,0)*(1+Sensitivity!$C$4) -> 108.86268 | O13: =IF($B13="Yes",'Owner CAPEX'!L15,0)*(1+Sensitivity!$C$4) -> 272.02313 | ... AD13: =IF($B13="Yes",'Owner CAPEX'!AA15,0)*(1+Sensitivity!$C$4) -> 0
B14: Yes | C14: ='Owner CAPEX'!B16 -> CHP | E14: =SUM(H14:AX14) -> 335.19 | H14: =IF($B14="Yes",'Owner CAPEX'!E16,0)*(1+Sensitivity!$C$4) -> 0 | I14: =IF($B14="Yes",'Owner CAPEX'!F16,0)*(1+Sensitivity!$C$4) -> 0 | J14: =IF($B14="Yes",'Owner CAPEX'!G16,0)*(1+Sensitivity!$C$4) -> 11.99 | K14: =IF($B14="Yes",'Owner CAPEX'!H16,0)*(1+Sensitivity!$C$4) -> 89.7925 | L14: =IF($B14="Yes",'Owner CAPEX'!I16,0)*(1+Sensitivity!$C$4) -> 155.605 | M14: =IF($B14="Yes",'Owner CAPEX'!J16,0)*(1+Sensitivity!$C$4) -> 77.8025 | N14: =IF($B14="Yes",'Owner CAPEX'!K16,0)*(1+Sensitivity!$C$4) -> 0 | O14: =IF($B14="Yes",'Owner CAPEX'!L16,0)*(1+Sensitivity!$C$4) -> 0 | ... AD14: =IF($B14="Yes",'Owner CAPEX'!AA16,0)*(1+Sensitivity!$C$4) -> 0
B15: Yes | C15: ='Owner CAPEX'!B17 -> Railway Siding | E15: =SUM(H15:AX15) -> 540 | H15: =IF($B15="Yes",'Owner CAPEX'!E17,0)*(1+Sensitivity!$C$4) -> 0 | I15: =IF($B15="Yes",'Owner CAPEX'!F17,0)*(1+Sensitivity!$C$4) -> 54 | J15: =IF($B15="Yes",'Owner CAPEX'!G17,0)*(1+Sensitivity!$C$4) -> 324 | K15: =IF($B15="Yes",'Owner CAPEX'!H17,0)*(1+Sensitivity!$C$4) -> 162 | L15: =IF($B15="Yes",'Owner CAPEX'!I17,0)*(1+Sensitivity!$C$4) -> 0 | M15: =IF($B15="Yes",'Owner CAPEX'!J17,0)*(1+Sensitivity!$C$4) -> 0 | N15: =IF($B15="Yes",'Owner CAPEX'!K17,0)*(1+Sensitivity!$C$4) -> 0 | O15: =IF($B15="Yes",'Owner CAPEX'!L17,0)*(1+Sensitivity!$C$4) -> 0 | ... AD15: =IF($B15="Yes",'Owner CAPEX'!AA17,0)*(1+Sensitivity!$C$4) -> 0
B16: Yes | C16: ='Owner CAPEX'!B18 -> Civil Infrastructure | E16: =SUM(H16:AX16) -> 191 | H16: =IF($B16="Yes",'Owner CAPEX'!E18,0)*(1+Sensitivity!$C$4) -> 0 | I16: =IF($B16="Yes",'Owner CAPEX'!F18,0)*(1+Sensitivity!$C$4) -> 57.3 | J16: =IF($B16="Yes",'Owner CAPEX'!G18,0)*(1+Sensitivity!$C$4) -> 95.5 | K16: =IF($B16="Yes",'Owner CAPEX'!H18,0)*(1+Sensitivity!$C$4) -> 38.2 | L16: =IF($B16="Yes",'Owner CAPEX'!I18,0)*(1+Sensitivity!$C$4) -> 0 | M16: =IF($B16="Yes",'Owner CAPEX'!J18,0)*(1+Sensitivity!$C$4) -> 0 | N16: =IF($B16="Yes",'Owner CAPEX'!K18,0)*(1+Sensitivity!$C$4) -> 0 | O16: =IF($B16="Yes",'Owner CAPEX'!L18,0)*(1+Sensitivity!$C$4) -> 0 | ... AD16: =IF($B16="Yes",'Owner CAPEX'!AA18,0)*(1+Sensitivity!$C$4) -> 0
B17: Yes | C17: ='Owner CAPEX'!B19 -> Fire Fighting & Dust Suppression | E17: =SUM(H17:AX17) -> 14.45 | H17: =IF($B17="Yes",'Owner CAPEX'!E19,0)*(1+Sensitivity!$C$4) -> 0 | I17: =IF($B17="Yes",'Owner CAPEX'!F19,0)*(1+Sensitivity!$C$4) -> 4.335 | J17: =IF($B17="Yes",'Owner CAPEX'!G19,0)*(1+Sensitivity!$C$4) -> 7.225 | K17: =IF($B17="Yes",'Owner CAPEX'!H19,0)*(1+Sensitivity!$C$4) -> 2.89 | L17: =IF($B17="Yes",'Owner CAPEX'!I19,0)*(1+Sensitivity!$C$4) -> 0 | M17: =IF($B17="Yes",'Owner CAPEX'!J19,0)*(1+Sensitivity!$C$4) -> 0 | N17: =IF($B17="Yes",'Owner CAPEX'!K19,0)*(1+Sensitivity!$C$4) -> 0 | O17: =IF($B17="Yes",'Owner CAPEX'!L19,0)*(1+Sensitivity!$C$4) -> 0 | ... AD17: =IF($B17="Yes",'Owner CAPEX'!AA19,0)*(1+Sensitivity!$C$4) -> 0
B18: Yes | C18: ='Owner CAPEX'!B20 -> Workshop and Store | E18: =SUM(H18:AX18) -> 27.27 | H18: =IF($B18="Yes",'Owner CAPEX'!E20,0)*(1+Sensitivity!$C$4) -> 0 | I18: =IF($B18="Yes",'Owner CAPEX'!F20,0)*(1+Sensitivity!$C$4) -> 0 | J18: =IF($B18="Yes",'Owner CAPEX'!G20,0)*(1+Sensitivity!$C$4) -> 13.635 | K18: =IF($B18="Yes",'Owner CAPEX'!H20,0)*(1+Sensitivity!$C$4) -> 13.635 | L18: =IF($B18="Yes",'Owner CAPEX'!I20,0)*(1+Sensitivity!$C$4) -> 0 | M18: =IF($B18="Yes",'Owner CAPEX'!J20,0)*(1+Sensitivity!$C$4) -> 0 | N18: =IF($B18="Yes",'Owner CAPEX'!K20,0)*(1+Sensitivity!$C$4) -> 0 | O18: =IF($B18="Yes",'Owner CAPEX'!L20,0)*(1+Sensitivity!$C$4) -> 0 | ... AD18: =IF($B18="Yes",'Owner CAPEX'!AA20,0)*(1+Sensitivity!$C$4) -> 0
B19: Yes | C19: ='Owner CAPEX'!B21 -> Electrical | E19: =SUM(H19:AX19) -> 34.35 | H19: =IF($B19="Yes",'Owner CAPEX'!E21,0)*(1+Sensitivity!$C$4) -> 0 | I19: =IF($B19="Yes",'Owner CAPEX'!F21,0)*(1+Sensitivity!$C$4) -> 0 | J19: =IF($B19="Yes",'Owner CAPEX'!G21,0)*(1+Sensitivity!$C$4) -> 0 | K19: =IF($B19="Yes",'Owner CAPEX'!H21,0)*(1+Sensitivity!$C$4) -> 8.5875 | L19: =IF($B19="Yes",'Owner CAPEX'!I21,0)*(1+Sensitivity!$C$4) -> 13.74 | M19: =IF($B19="Yes",'Owner CAPEX'!J21,0)*(1+Sensitivity!$C$4) -> 8.5875 | N19: =IF($B19="Yes",'Owner CAPEX'!K21,0)*(1+Sensitivity!$C$4) -> 3.435 | O19: =IF($B19="Yes",'Owner CAPEX'!L21,0)*(1+Sensitivity!$C$4) -> 0 | ... AD19: =IF($B19="Yes",'Owner CAPEX'!AA21,0)*(1+Sensitivity!$C$4) -> 0
B20: Yes | C20: ='Owner CAPEX'!B22 -> Mine Dewatering System | E20: =SUM(H20:AX20) -> 15 | H20: =IF($B20="Yes",'Owner CAPEX'!E22,0)*(1+Sensitivity!$C$4) -> 0 | I20: =IF($B20="Yes",'Owner CAPEX'!F22,0)*(1+Sensitivity!$C$4) -> 0 | J20: =IF($B20="Yes",'Owner CAPEX'!G22,0)*(1+Sensitivity!$C$4) -> 0 | K20: =IF($B20="Yes",'Owner CAPEX'!H22,0)*(1+Sensitivity!$C$4) -> 0 | L20: =IF($B20="Yes",'Owner CAPEX'!I22,0)*(1+Sensitivity!$C$4) -> 2.8256089 | M20: =IF($B20="Yes",'Owner CAPEX'!J22,0)*(1+Sensitivity!$C$4) -> 2.0484988 | N20: =IF($B20="Yes",'Owner CAPEX'!K22,0)*(1+Sensitivity!$C$4) -> 0 | O20: =IF($B20="Yes",'Owner CAPEX'!L22,0)*(1+Sensitivity!$C$4) -> 0 | ... AD20: =IF($B20="Yes",'Owner CAPEX'!AA22,0)*(1+Sensitivity!$C$4) -> 0
... B22: Yes | C22: ='Owner CAPEX'!B24 -> Contingency | E22: =SUM(H22:AX22) -> 617.48264 | H22: =IF($B22="Yes",'Owner CAPEX'!E24,0)*(1+Sensitivity!$C$4) -> 17.116539 | I22: =IF($B22="Yes",'Owner CAPEX'!F24,0)*(1+Sensitivity!$C$4) -> 44.800128 | J22: =IF($B22="Yes",'Owner CAPEX'!G24,0)*(1+Sensitivity!$C$4) -> 88.397465 | K22: =IF($B22="Yes",'Owner CAPEX'!H24,0)*(1+Sensitivity!$C$4) -> 67.485215 | L22: =IF($B22="Yes",'Owner CAPEX'!I24,0)*(1+Sensitivity!$C$4) -> 60.326308 | M22: =IF($B22="Yes",'Owner CAPEX'!J24,0)*(1+Sensitivity!$C$4) -> 24.236479 | N22: =IF($B22="Yes",'Owner CAPEX'!K24,0)*(1+Sensitivity!$C$4) -> 27.916778 | O22: =IF($B22="Yes",'Owner CAPEX'!L24,0)*(1+Sensitivity!$C$4) -> 76.665102 | ... AD22: =IF($B22="Yes",'Owner CAPEX'!AA24,0)*(1+Sensitivity!$C$4) -> 0
C23: Sub-Total | E23: =SUM(H23:AX23) -> 4833.1036 | H23: =SUM(H9:H22) -> 155.9943 | I23: =SUM(I9:I22) -> 343.46765 | J23: =SUM(J9:J22) -> 677.7139 | K23: =SUM(K9:K22) -> 542.15415 | L23: =SUM(L9:L22) -> 512.0367 | M23: =SUM(M9:M22) -> 185.81301 | N23: =SUM(N9:N22) -> 214.02863 | O23: =SUM(O9:O22) -> 587.76578 | ... AD23: =SUM(AD9:AD22) -> 0
C24: Sustainable Expenditure
B25: Yes | C25: ='Owner CAPEX'!B31 -> Mining Equipment Replacement | E25: =SUM(H25:AX25) -> 1365.0488 | H25: =IF($B25="Yes",'Owner CAPEX'!E31,0)*(1+Sensitivity!$C$4) -> 0 | I25: =IF($B25="Yes",'Owner CAPEX'!F31,0)*(1+Sensitivity!$C$4) -> 0 | J25: =IF($B25="Yes",'Owner CAPEX'!G31,0)*(1+Sensitivity!$C$4) -> 0 | K25: =IF($B25="Yes",'Owner CAPEX'!H31,0)*(1+Sensitivity!$C$4) -> 0 | L25: =IF($B25="Yes",'Owner CAPEX'!I31,0)*(1+Sensitivity!$C$4) -> 0 | M25: =IF($B25="Yes",'Owner CAPEX'!J31,0)*(1+Sensitivity!$C$4) -> 0 | N25: =IF($B25="Yes",'Owner CAPEX'!K31,0)*(1+Sensitivity!$C$4) -> 0 | O25: =IF($B25="Yes",'Owner CAPEX'!L31,0)*(1+Sensitivity!$C$4) -> 0 | ... AD25: =IF($B25="Yes",'Owner CAPEX'!AA31,0)*(1+Sensitivity!$C$4) -> 157.0256
B26: Yes | C26: ='Owner CAPEX'!B32 -> CHP | E26: =SUM(H26:AX26) -> 20.1114 | H26: =IF($B26="Yes",'Owner CAPEX'!E32,0)*(1+Sensitivity!$C$4) -> 0 | I26: =IF($B26="Yes",'Owner CAPEX'!F32,0)*(1+Sensitivity!$C$4) -> 0 | J26: =IF($B26="Yes",'Owner CAPEX'!G32,0)*(1+Sensitivity!$C$4) -> 0 | K26: =IF($B26="Yes",'Owner CAPEX'!H32,0)*(1+Sensitivity!$C$4) -> 0 | L26: =IF($B26="Yes",'Owner CAPEX'!I32,0)*(1+Sensitivity!$C$4) -> 0 | M26: =IF($B26="Yes",'Owner CAPEX'!J32,0)*(1+Sensitivity!$C$4) -> 0 | N26: =IF($B26="Yes",'Owner CAPEX'!K32,0)*(1+Sensitivity!$C$4) -> 0 | O26: =IF($B26="Yes",'Owner CAPEX'!L32,0)*(1+Sensitivity!$C$4) -> 0 | ... AD26: =IF($B26="Yes",'Owner CAPEX'!AA32,0)*(1+Sensitivity!$C$4) -> 0
B27: Yes | C27: ='Owner CAPEX'!B33 -> Civil Infrastructure | E27: =SUM(H27:AX27) -> 6.685 | H27: =IF($B27="Yes",'Owner CAPEX'!E33,0)*(1+Sensitivity!$C$4) -> 0 | I27: =IF($B27="Yes",'Owner CAPEX'!F33,0)*(1+Sensitivity!$C$4) -> 0 | J27: =IF($B27="Yes",'Owner CAPEX'!G33,0)*(1+Sensitivity!$C$4) -> 0 | K27: =IF($B27="Yes",'Owner CAPEX'!H33,0)*(1+Sensitivity!$C$4) -> 0 | L27: =IF($B27="Yes",'Owner CAPEX'!I33,0)*(1+Sensitivity!$C$4) -> 0 | M27: =IF($B27="Yes",'Owner CAPEX'!J33,0)*(1+Sensitivity!$C$4) -> 0 | N27: =IF($B27="Yes",'Owner CAPEX'!K33,0)*(1+Sensitivity!$C$4) -> 0 | O27: =IF($B27="Yes",'Owner CAPEX'!L33,0)*(1+Sensitivity!$C$4) -> 0 | ... AD27: =IF($B27="Yes",'Owner CAPEX'!AA33,0)*(1+Sensitivity!$C$4) -> 0
B28: Yes | C28: ='Owner CAPEX'!B34 -> Workshop and Store | E28: =SUM(H28:AX28) -> 0 | H28: =IF($B28="Yes",'Owner CAPEX'!E34,0)*(1+Sensitivity!$C$4) -> 0 | I28: =IF($B28="Yes",'Owner CAPEX'!F34,0)*(1+Sensitivity!$C$4) -> 0 | J28: =IF($B28="Yes",'Owner CAPEX'!G34,0)*(1+Sensitivity!$C$4) -> 0 | K28: =IF($B28="Yes",'Owner CAPEX'!H34,0)*(1+Sensitivity!$C$4) -> 0 | L28: =IF($B28="Yes",'Owner CAPEX'!I34,0)*(1+Sensitivity!$C$4) -> 0 | M28: =IF($B28="Yes",'Owner CAPEX'!J34,0)*(1+Sensitivity!$C$4) -> 0 | N28: =IF($B28="Yes",'Owner CAPEX'!K34,0)*(1+Sensitivity!$C$4) -> 0 | O28: =IF($B28="Yes",'Owner CAPEX'!L34,0)*(1+Sensitivity!$C$4) -> 0 | ... AD28: =IF($B28="Yes",'Owner CAPEX'!AA34,0)*(1+Sensitivity!$C$4) -> 0
B29: Yes | C29: ='Owner CAPEX'!B35 -> Electrical | E29: =SUM(H29:AX29) -> 0 | H29: =IF($B29="Yes",'Owner CAPEX'!E35,0)*(1+Sensitivity!$C$4) -> 0 | I29: =IF($B29="Yes",'Owner CAPEX'!F35,0)*(1+Sensitivity!$C$4) -> 0 | J29: =IF($B29="Yes",'Owner CAPEX'!G35,0)*(1+Sensitivity!$C$4) -> 0 | K29: =IF($B29="Yes",'Owner CAPEX'!H35,0)*(1+Sensitivity!$C$4) -> 0 | L29: =IF($B29="Yes",'Owner CAPEX'!I35,0)*(1+Sensitivity!$C$4) -> 0 | M29: =IF($B29="Yes",'Owner CAPEX'!J35,0)*(1+Sensitivity!$C$4) -> 0 | N29: =IF($B29="Yes",'Owner CAPEX'!K35,0)*(1+Sensitivity!$C$4) -> 0 | O29: =IF($B29="Yes",'Owner CAPEX'!L35,0)*(1+Sensitivity!$C$4) -> 0 | ... AD29: =IF($B29="Yes",'Owner CAPEX'!AA35,0)*(1+Sensitivity!$C$4) -> 0
B30: Yes | C30: ='Owner CAPEX'!B36 -> Mine Dewatering System | E30: =SUM(H30:AX30) -> 0 | H30: =IF($B30="Yes",'Owner CAPEX'!E36,0)*(1+Sensitivity!$C$4) -> 0 | I30: =IF($B30="Yes",'Owner CAPEX'!F36,0)*(1+Sensitivity!$C$4) -> 0 | J30: =IF($B30="Yes",'Owner CAPEX'!G36,0)*(1+Sensitivity!$C$4) -> 0 | K30: =IF($B30="Yes",'Owner CAPEX'!H36,0)*(1+Sensitivity!$C$4) -> 0 | L30: =IF($B30="Yes",'Owner CAPEX'!I36,0)*(1+Sensitivity!$C$4) -> 0 | M30: =IF($B30="Yes",'Owner CAPEX'!J36,0)*(1+Sensitivity!$C$4) -> 0 | N30: =IF($B30="Yes",'Owner CAPEX'!K36,0)*(1+Sensitivity!$C$4) -> 0 | O30: =IF($B30="Yes",'Owner CAPEX'!L36,0)*(1+Sensitivity!$C$4) -> 0 | ... AD30: =IF($B30="Yes",'Owner CAPEX'!AA36,0)*(1+Sensitivity!$C$4) -> 0
B31: Yes | C31: ='Owner CAPEX'!B37 -> Digitalisation | E31: =SUM(H31:AX31) -> 0 | H31: =IF($B31="Yes",'Owner CAPEX'!E37,0)*(1+Sensitivity!$C$4) -> 0 | I31: =IF($B31="Yes",'Owner CAPEX'!F37,0)*(1+Sensitivity!$C$4) -> 0 | J31: =IF($B31="Yes",'Owner CAPEX'!G37,0)*(1+Sensitivity!$C$4) -> 0 | K31: =IF($B31="Yes",'Owner CAPEX'!H37,0)*(1+Sensitivity!$C$4) -> 0 | L31: =IF($B31="Yes",'Owner CAPEX'!I37,0)*(1+Sensitivity!$C$4) -> 0 | M31: =IF($B31="Yes",'Owner CAPEX'!J37,0)*(1+Sensitivity!$C$4) -> 0 | N31: =IF($B31="Yes",'Owner CAPEX'!K37,0)*(1+Sensitivity!$C$4) -> 0 | O31: =IF($B31="Yes",'Owner CAPEX'!L37,0)*(1+Sensitivity!$C$4) -> 0 | ... AD31: =IF($B31="Yes",'Owner CAPEX'!AA37,0)*(1+Sensitivity!$C$4) -> 0
B32: Yes | C32: ='Owner CAPEX'!B38 -> Contingency | E32: =SUM(H32:AX32) -> 208.77677 | H32: =IF($B32="Yes",'Owner CAPEX'!E38,0)*(1+Sensitivity!$C$4) -> 0 | I32: =IF($B32="Yes",'Owner CAPEX'!F38,0)*(1+Sensitivity!$C$4) -> 0 | J32: =IF($B32="Yes",'Owner CAPEX'!G38,0)*(1+Sensitivity!$C$4) -> 0 | K32: =IF($B32="Yes",'Owner CAPEX'!H38,0)*(1+Sensitivity!$C$4) -> 0 | L32: =IF($B32="Yes",'Owner CAPEX'!I38,0)*(1+Sensitivity!$C$4) -> 0 | M32: =IF($B32="Yes",'Owner CAPEX'!J38,0)*(1+Sensitivity!$C$4) -> 0 | N32: =IF($B32="Yes",'Owner CAPEX'!K38,0)*(1+Sensitivity!$C$4) -> 0 | O32: =IF($B32="Yes",'Owner CAPEX'!L38,0)*(1+Sensitivity!$C$4) -> 0 | ... AD32: =IF($B32="Yes",'Owner CAPEX'!AA38,0)*(1+Sensitivity!$C$4) -> 23.55384
C33: Sub-Total | E33: =SUM(H33:AX33) -> 1600.6219 | H33: =SUM(H25:H32) -> 0 | I33: =SUM(I25:I32) -> 0 | J33: =SUM(J25:J32) -> 0 | K33: =SUM(K25:K32) -> 0 | L33: =SUM(L25:L32) -> 0 | M33: =SUM(M25:M32) -> 0 | N33: =SUM(N25:N32) -> 0 | O33: =SUM(O25:O32) -> 0 | ... AD33: =SUM(AD25:AD32) -> 180.57944
C35: Total Capital Expenditure | E35: =SUM(H35:AX35) -> 6433.7255 | H35: =H23+H33 -> 155.9943 | I35: =I23+I33 -> 343.46765 | J35: =J23+J33 -> 677.7139 | K35: =K23+K33 -> 542.15415 | L35: =L23+L33 -> 512.0367 | M35: =M23+M33 -> 185.81301 | N35: =N23+N33 -> 214.02863 | O35: =O23+O33 -> 587.76578 | ... AD35: =AD23+AD33 -> 180.57944
E36: =E35='Owner CAPEX'!D41-'Owner CAPEX'!D25 -> TRUE
C38: Depreciation- As pere books (Straight Line Method)
B39: 1 | C39: List | H39: =H2 -> 46023 | I39: =I2 -> 46389 | J39: =J2 -> 46755 | K39: =K2 -> 47121 | L39: =L2 -> 47487 | M39: =M2 -> 47853 | N39: =N2 -> 48219 | O39: =O2 -> 48585 | ... AD39: =AD2 -> 54075
B40: 2 | H40: =H3 -> -4 | I40: =I3 -> -3 | J40: =J3 -> -2 | K40: =K3 -> -1 | L40: =L3 -> 1 | M40: =M3 -> 2 | N40: =N3 -> 3 | O40: =O3 -> 4 | ... AD40: =AD3 -> 19
B41: 3 | C41: =C9 -> Pre-operative costs | F41: 0.1
B42: 4 | C42: Opening Balance | D42: INR Cr | H42: =G46 -> 0 | I42: =H46 -> 124.98998 | J42: =I46 -> 140.14544 | K42: =J46 -> 153.14307 | L42: =K46 -> 185.83263 | M42: =L46 -> 204.04793 | N42: =M46 -> 172.72822 | O42: =N46 -> 141.40852 | ... AD42: =AC46 -> -4.4408921e-14
B43: 5 | C43: Addition during year | D43: INR Cr | E43: =SUM(H43:AI43) -> 313.19704 | H43: =H9+H10 -> 138.87776 | I43: =I9+I10 -> 32.27026 | J43: =J9+J10 -> 33.45826 | K43: =K9+K10 -> 59.05576 | L43: =L9+L10 -> 49.535 | M43: =M9+M10 -> 0 | N43: =N9+N10 -> 0 | O43: =O9+O10 -> 0 | ... AD43: =AD9+AD10 -> 0
B44: 6 | C44: Book Depreciation | D44: INR Cr | E44: =SUM(H44:AI44) -> 313.19704 | H44: =H221 -> 13.887776 | I44: =I221 -> 17.114802 | J44: =J221 -> 20.460628 | K44: =K221 -> 26.366204 | L44: =L221 -> 31.319704 | M44: =M221 -> 31.319704 | N44: =N221 -> 31.319704 | O44: =O221 -> 31.319704 | ... AD44: =AD221 -> 0
B45: 7 | C45: Accumulated Depreciation | D45: INR Cr | H45: =SUM($H44:H44) -> 13.887776 | I45: =SUM($H44:I44) -> 31.002578 | J45: =SUM($H44:J44) -> 51.463206 | K45: =SUM($H44:K44) -> 77.82941 | L45: =SUM($H44:L44) -> 109.14911 | M45: =SUM($H44:M44) -> 140.46882 | N45: =SUM($H44:N44) -> 171.78852 | O45: =SUM($H44:O44) -> 203.10823 | ... AD45: =SUM($H44:AD44) -> 313.19704
B46: 8 | C46: Net Fixed Assets | D46: INR Cr | H46: =H42+H43-H44 -> 124.98998 | I46: =I42+I43-I44 -> 140.14544 | J46: =J42+J43-J44 -> 153.14307 | K46: =K42+K43-K44 -> 185.83263 | L46: =L42+L43-L44 -> 204.04793 | M46: =M42+M43-M44 -> 172.72822 | N46: =N42+N43-N44 -> 141.40852 | O46: =O42+O43-O44 -> 110.08881 | ... AD46: =AD42+AD43-AD44 -> -4.4408921e-14
B47: 9 | C47: =C11 -> Land Cost | F47: =1/COUNT(H40:AD40) -> 0.043478261
B48: 10 | C48: Opening Balance | D48: INR Cr | H48: =G52 -> 0 | I48: =H52 -> 0 | J48: =I52 -> 141.33782 | K48: =J52 -> 229.13858 | L48: =K52 -> 312.65638 | M48: =L52 -> 389.37607 | N48: =M52 -> 425.94538 | O48: =N52 -> 474.85812 | ... AD48: =AC52 -> 766.75603
B49: 11 | C49: Addition during year | D49: INR Cr | E49: =SUM(H49:AI49) -> 2033.648 | H49: =H11+H12 -> 0 | I49: =I11+I12 -> 147.76226 | J49: =J11+J12 -> 98.508174 | K49: =K11+K12 -> 98.508174 | L49: =L11+L12 -> 95.8787 | M49: =M11+M12 -> 58.261429 | N49: =N11+N12 -> 73.814176 | O49: =O11+O12 -> 239.07755 | ... AD49: =AD11+AD12 -> 0
B50: 12 | C50: Book Depreciation | D50: INR Cr | E50: =SUM(H50:AI50) -> 1355.3115 | H50: =H249 -> 0 | I50: =I249 -> 6.4244461 | J50: =J249 -> 10.70741 | K50: =K249 -> 14.990374 | L50: =L249 -> 19.159013 | M50: =M249 -> 21.692119 | N50: =N249 -> 24.901431 | O50: =O249 -> 35.296107 | ... AD50: =AD249 -> 88.41948
B51: 13 | C51: Accumulated Depreciation | D51: INR Cr | H51: =SUM($H50:H50) -> 0 | I51: =SUM($H50:I50) -> 6.4244461 | J51: =SUM($H50:J50) -> 17.131856 | K51: =SUM($H50:K50) -> 32.122231 | L51: =SUM($H50:L50) -> 51.281244 | M51: =SUM($H50:M50) -> 72.973363 | N51: =SUM($H50:N50) -> 97.874794 | O51: =SUM($H50:O50) -> 133.1709 | ... AD51: =SUM($H50:AD50) -> 1355.3115
B52: 14 | C52: Net Fixed Assets | D52: INR Cr | H52: =H48+H49-H50 -> 0 | I52: =I48+I49-I50 -> 141.33782 | J52: =J48+J49-J50 -> 229.13858 | K52: =K48+K49-K50 -> 312.65638 | L52: =L48+L49-L50 -> 389.37607 | M52: =M48+M49-M50 -> 425.94538 | N52: =N48+N49-N50 -> 474.85812 | O52: =O48+O49-O50 -> 678.63957 | ... AD52: =AD48+AD49-AD50 -> 678.33655
B53: 15 | C53: =C13 -> HEMM Equipment | F53: 0.1188
B54: 16 | C54: Opening Balance | D54: INR Cr | H54: =G58 -> 0 | I54: =H58 -> 0 | J54: =I58 -> 0 | K54: =J58 -> 0 | L54: =K58 -> 0 | M54: =L58 -> 118.1919 | N54: =M58 -> 115.36698 | O54: =N58 -> 193.59526 | ... AD54: =AC58 -> 387.16303
B55: 17 | C55: Addition during year | D55: INR Cr | E55: =SUM(H55:AI55) -> 2066.5646 | H55: =H13+H25 -> 0 | I55: =I13+I25 -> 0 | J55: =J13+J25 -> 0 | K55: =K13+K25 -> 0 | L55: =L13+L25 -> 134.12608 | M55: =M13+M25 -> 14.8766 | N55: =N13+N25 -> 108.86268 | O55: =O13+O25 -> 272.02313 | ... AD55: =AD13+AD25 -> 157.0256
B56: 18 | C56: Book Depreciation | D56: INR Cr | E56: =SUM(H56:AI56) -> 1630.8824 | H56: =H277 -> 0 | I56: =I277 -> 0 | J56: =J277 -> 0 | K56: =K277 -> 0 | L56: =L277 -> 15.934178 | M56: =M277 -> 17.701518 | N56: =N277 -> 30.634404 | O56: =O277 -> 62.950752 | ... AD56: =AD277 -> 108.50645
B57: 19 | C57: Accumulated Depreciation | D57: INR Cr | H57: =SUM($H56:H56) -> 0 | I57: =SUM($H56:I56) -> 0 | J57: =SUM($H56:J56) -> 0 | K57: =SUM($H56:K56) -> 0 | L57: =SUM($H56:L56) -> 15.934178 | M57: =SUM($H56:M56) -> 33.635696 | N57: =SUM($H56:N56) -> 64.270101 | O57: =SUM($H56:O56) -> 127.22085 | ... AD57: =SUM($H56:AD56) -> 1630.8824
B58: 20 | C58: Net Fixed Assets | D58: INR Cr | H58: =H54+H55-H56 -> 0 | I58: =I54+I55-I56 -> 0 | J58: =J54+J55-J56 -> 0 | K58: =K54+K55-K56 -> 0 | L58: =L54+L55-L56 -> 118.1919 | M58: =M54+M55-M56 -> 115.36698 | N58: =N54+N55-N56 -> 193.59526 | O58: =O54+O55-O56 -> 402.66763 | ... AD58: =AD54+AD55-AD56 -> 435.68219
B59: 21 | C59: =C14 -> CHP | F59: 0.0667
B60: 22 | C60: Opening Balance | D60: INR Cr | H60: =G64 -> 0 | I60: =H64 -> 0 | J60: =I64 -> 0 | K60: =J64 -> 11.190267 | L60: =K64 -> 94.193874 | M60: =L64 -> 232.63113 | N60: =M64 -> 288.07646 | O60: =N64 -> 265.71928 | ... AD60: =AC64 -> 10.721387
B61: 23 | C61: Addition during year | D61: INR Cr | E61: =SUM(H61:AI61) -> 355.3014 | H61: =H14+H26 -> 0 | I61: =I14+I26 -> 0 | J61: =J14+J26 -> 11.99 | K61: =K14+K26 -> 89.7925 | L61: =L14+L26 -> 155.605 | M61: =M14+M26 -> 77.8025 | N61: =N14+N26 -> 0 | O61: =O14+O26 -> 0 | ... AD61: =AD14+AD26 -> 0
B62: 24 | C62: Book Depreciation | D62: INR Cr | E62: =SUM(H62:AI62) -> 345.92144 | H62: =H305 -> 0 | I62: =I305 -> 0 | J62: =J305 -> 0.799733 | K62: =K305 -> 6.7888927 | L62: =L305 -> 17.167746 | M62: =M305 -> 22.357173 | N62: =N305 -> 22.357173 | O62: =O305 -> 22.357173 | ... AD62: =AD305 -> 1.3414304
B63: 25 | C63: Accumulated Depreciation | D63: INR Cr | H63: =SUM($H62:H62) -> 0 | I63: =SUM($H62:I62) -> 0 | J63: =SUM($H62:J62) -> 0.799733 | K63: =SUM($H62:K62) -> 7.5886257 | L63: =SUM($H62:L62) -> 24.756372 | M63: =SUM($H62:M62) -> 47.113545 | N63: =SUM($H62:N62) -> 69.470718 | O63: =SUM($H62:O62) -> 91.827891 | ... AD63: =SUM($H62:AD62) -> 345.92144
B64: 26 | C64: Net Fixed Assets | D64: INR Cr | H64: =H60+H61-H62 -> 0 | I64: =I60+I61-I62 -> 0 | J64: =J60+J61-J62 -> 11.190267 | K64: =K60+K61-K62 -> 94.193874 | L64: =L60+L61-L62 -> 232.63113 | M64: =M60+M61-M62 -> 288.07646 | N64: =N60+N61-N62 -> 265.71928 | O64: =O60+O61-O62 -> 243.36211 | ... AD64: =AD60+AD61-AD62 -> 9.379957
B65: 27 | C65: =C15 -> Railway Siding | F65: 0.05
B66: 28 | C66: Opening Balance | D66: INR Cr | H66: =G70 -> 0 | I66: =H70 -> 0 | J66: =I70 -> 51.3 | K66: =J70 -> 356.4 | L66: =K70 -> 491.4 | M66: =L70 -> 464.4 | N66: =M70 -> 437.4 | O66: =N70 -> 410.4 | ... AD66: =AC70 -> 8.1
B67: 29 | C67: Addition during year | D67: INR Cr | E67: =SUM(H67:AI67) -> 540 | H67: =H15 -> 0 | I67: =I15 -> 54 | J67: =J15 -> 324 | K67: =K15 -> 162 | L67: =L15 -> 0 | M67: =M15 -> 0 | N67: =N15 -> 0 | O67: =O15 -> 0 | ... AD67: =AD15 -> 0
B68: 30 | C68: Book Depreciation | D68: INR Cr | E68: =SUM(H68:AI68) -> 540 | H68: =H333 -> 0 | I68: =I333 -> 2.7 | J68: =J333 -> 18.9 | K68: =K333 -> 27 | L68: =L333 -> 27 | M68: =M333 -> 27 | N68: =N333 -> 27 | O68: =O333 -> 27 | ... AD68: =AD333 -> 8.1
B69: 31 | C69: Accumulated Depreciation | D69: INR Cr | H69: =SUM($H68:H68) -> 0 | I69: =SUM($H68:I68) -> 2.7 | J69: =SUM($H68:J68) -> 21.6 | K69: =SUM($H68:K68) -> 48.6 | L69: =SUM($H68:L68) -> 75.6 | M69: =SUM($H68:M68) -> 102.6 | N69: =SUM($H68:N68) -> 129.6 | O69: =SUM($H68:O68) -> 156.6 | ... AD69: =SUM($H68:AD68) -> 540
B70: 32 | C70: Net Fixed Assets | D70: INR Cr | H70: =H66+H67-H68 -> 0 | I70: =I66+I67-I68 -> 51.3 | J70: =J66+J67-J68 -> 356.4 | K70: =K66+K67-K68 -> 491.4 | L70: =L66+L67-L68 -> 464.4 | M70: =M66+M67-M68 -> 437.4 | N70: =N66+N67-N68 -> 410.4 | O70: =O66+O67-O68 -> 383.4 | ... AD70: =AD66+AD67-AD68 -> 0
B71: 33 | C71: =C16 -> Civil Infrastructure | F71: 0.0317
B72: 34 | C72: Opening Balance | D72: INR Cr | H72: =G76 -> 0 | I72: =H76 -> 0 | J72: =I76 -> 55.48359 | K72: =J76 -> 146.13983 | L72: =K76 -> 178.28513 | M72: =L76 -> 172.23043 | N72: =M76 -> 166.17573 | O72: =N76 -> 160.12103 | ... AD72: =AC76 -> 74.0783
B73: 35 | C73: Addition during year | D73: INR Cr | E73: =SUM(H73:AI73) -> 197.685 | H73: =H16+H27 -> 0 | I73: =I16+I27 -> 57.3 | J73: =J16+J27 -> 95.5 | K73: =K16+K27 -> 38.2 | L73: =L16+L27 -> 0 | M73: =M16+M27 -> 0 | N73: =N16+N27 -> 0 | O73: =O16+O27 -> 0 | ... AD73: =AD16+AD27 -> 0
B74: 36 | C74: Book Depreciation | D74: INR Cr | E74: =SUM(H74:AI74) -> 129.87332 | H74: =H361 -> 0 | I74: =I361 -> 1.81641 | J74: =J361 -> 4.84376 | K74: =K361 -> 6.0547 | L74: =L361 -> 6.0547 | M74: =M361 -> 6.0547 | N74: =N361 -> 6.0547 | O74: =O361 -> 6.0547 | ... AD74: =AD361 -> 6.2666145
B75: 37 | C75: Accumulated Depreciation | D75: INR Cr | H75: =SUM($H74:H74) -> 0 | I75: =SUM($H74:I74) -> 1.81641 | J75: =SUM($H74:J74) -> 6.66017 | K75: =SUM($H74:K74) -> 12.71487 | L75: =SUM($H74:L74) -> 18.76957 | M75: =SUM($H74:M74) -> 24.82427 | N75: =SUM($H74:N74) -> 30.87897 | O75: =SUM($H74:O74) -> 36.93367 | ... AD75: =SUM($H74:AD74) -> 129.87332
B76: 38 | C76: Net Fixed Assets | D76: INR Cr | H76: =H72+H73-H74 -> 0 | I76: =I72+I73-I74 -> 55.48359 | J76: =J72+J73-J74 -> 146.13983 | K76: =K72+K73-K74 -> 178.28513 | L76: =L72+L73-L74 -> 172.23043 | M76: =M72+M73-M74 -> 166.17573 | N76: =N72+N73-N74 -> 160.12103 | O76: =O72+O73-O74 -> 154.06633 | ... AD76: =AD72+AD73-AD74 -> 67.811685
B77: 39 | C77: =C17 -> Fire Fighting & Dust Suppression | F77: 0.0667
B78: 40 | C78: Opening Balance | D78: INR Cr | H78: =G82 -> 0 | I78: =H82 -> 0 | J78: =I82 -> 4.0458555 | K78: =J82 -> 10.499804 | L78: =K82 -> 12.425989 | M78: =L82 -> 11.462174 | N78: =M82 -> 10.498359 | O78: =N82 -> 9.5345435 | ... AD78: =AC82 -> -6.6613381e-16
B79: 41 | C79: Addition during year | D79: INR Cr | E79: =SUM(H79:AI79) -> 14.45 | H79: =H17 -> 0 | I79: =I17 -> 4.335 | J79: =J17 -> 7.225 | K79: =K17 -> 2.89 | L79: =L17 -> 0 | M79: =M17 -> 0 | N79: =N17 -> 0 | O79: =O17 -> 0 | ... AD79: =AD17 -> 0
B80: 42 | C80: Book Depreciation | D80: INR Cr | E80: =SUM(H80:AI80) -> 14.45 | H80: =H389 -> 0 | I80: =I389 -> 0.2891445 | J80: =J389 -> 0.771052 | K80: =K389 -> 0.963815 | L80: =L389 -> 0.963815 | M80: =M389 -> 0.963815 | N80: =N389 -> 0.963815 | O80: =O389 -> 0.963815 | ... AD80: =AD389 -> 0
B81: 43 | C81: Accumulated Depreciation | D81: INR Cr | H81: =SUM($H80:H80) -> 0 | I81: =SUM($H80:I80) -> 0.2891445 | J81: =SUM($H80:J80) -> 1.0601965 | K81: =SUM($H80:K80) -> 2.0240115 | L81: =SUM($H80:L80) -> 2.9878265 | M81: =SUM($H80:M80) -> 3.9516415 | N81: =SUM($H80:N80) -> 4.9154565 | O81: =SUM($H80:O80) -> 5.8792715 | ... AD81: =SUM($H80:AD80) -> 14.45
B82: 44 | C82: Net Fixed Assets | D82: INR Cr | H82: =H78+H79-H80 -> 0 | I82: =I78+I79-I80 -> 4.0458555 | J82: =J78+J79-J80 -> 10.499804 | K82: =K78+K79-K80 -> 12.425989 | L82: =L78+L79-L80 -> 11.462174 | M82: =M78+M79-M80 -> 10.498359 | N82: =N78+N79-N80 -> 9.5345435 | O82: =O78+O79-O80 -> 8.5707285 | ... AD82: =AD78+AD79-AD80 -> -6.6613381e-16
B83: 45 | C83: =C18 -> Workshop and Store | F83: 0.0667
B84: 46 | C84: Opening Balance | D84: INR Cr | H84: =G88 -> 0 | I84: =H88 -> 0 | J84: =I88 -> 0 | K84: =J88 -> 12.725545 | L84: =K88 -> 24.541636 | M84: =L88 -> 22.722727 | N84: =M88 -> 20.903818 | O84: =N88 -> 19.084909 | ... AD84: =AC88 -> 2.6645353e-15
B85: 47 | C85: Addition during year | D85: INR Cr | E85: =SUM(H85:AI85) -> 27.27 | H85: =H18+H28 -> 0 | I85: =I18+I28 -> 0 | J85: =J18+J28 -> 13.635 | K85: =K18+K28 -> 13.635 | L85: =L18+L28 -> 0 | M85: =M18+M28 -> 0 | N85: =N18+N28 -> 0 | O85: =O18+O28 -> 0 | ... AD85: =AD18+AD28 -> 0
B86: 48 | C86: Book Depreciation | D86: INR Cr | E86: =SUM(H86:AI86) -> 27.27 | H86: =H417 -> 0 | I86: =I417 -> 0 | J86: =J417 -> 0.9094545 | K86: =K417 -> 1.818909 | L86: =L417 -> 1.818909 | M86: =M417 -> 1.818909 | N86: =N417 -> 1.818909 | O86: =O417 -> 1.818909 | ... AD86: =AD417 -> 0
B87: 49 | C87: Accumulated Depreciation | D87: INR Cr | H87: =SUM($H86:H86) -> 0 | I87: =SUM($H86:I86) -> 0 | J87: =SUM($H86:J86) -> 0.9094545 | K87: =SUM($H86:K86) -> 2.7283635 | L87: =SUM($H86:L86) -> 4.5472725 | M87: =SUM($H86:M86) -> 6.3661815 | N87: =SUM($H86:N86) -> 8.1850905 | O87: =SUM($H86:O86) -> 10.003999 | ... AD87: =SUM($H86:AD86) -> 27.27
B88: 50 | C88: Net Fixed Assets | D88: INR Cr | H88: =H84+H85-H86 -> 0 | I88: =I84+I85-I86 -> 0 | J88: =J84+J85-J86 -> 12.725545 | K88: =K84+K85-K86 -> 24.541636 | L88: =L84+L85-L86 -> 22.722727 | M88: =M84+M85-M86 -> 20.903818 | N88: =N84+N85-N86 -> 19.084909 | O88: =O84+O85-O86 -> 17.266 | ... AD88: =AD84+AD85-AD86 -> 2.6645353e-15
B89: 51 | C89: =C19 -> Electrical | F89: 0.05
B90: 52 | C90: Opening Balance | D90: INR Cr | H90: =G94 -> 0 | I90: =H94 -> 0 | J90: =I94 -> 0 | K90: =J94 -> 0 | L90: =K94 -> 8.158125 | M90: =L94 -> 20.78175 | N90: =M94 -> 27.8235 | O90: =N94 -> 29.541 | ... AD90: =AC94 -> 3.7785
B91: 53 | C91: Addition during year | D91: INR Cr | E91: =SUM(H91:AI91) -> 34.35 | H91: =H19+H29 -> 0 | I91: =I19+I29 -> 0 | J91: =J19+J29 -> 0 | K91: =K19+K29 -> 8.5875 | L91: =L19+L29 -> 13.74 | M91: =M19+M29 -> 8.5875 | N91: =N19+N29 -> 3.435 | O91: =O19+O29 -> 0 | ... AD91: =AD19+AD29 -> 0
B92: 54 | C92: Book Depreciation | D92: INR Cr | E92: =SUM(H92:AI92) -> 32.289 | H92: =H445 -> 0 | I92: =I445 -> 0 | J92: =J445 -> 0 | K92: =K445 -> 0.429375 | L92: =L445 -> 1.116375 | M92: =M445 -> 1.54575 | N92: =N445 -> 1.7175 | O92: =O445 -> 1.7175 | ... AD92: =AD445 -> 1.7175
B93: 55 | C93: Accumulated Depreciation | D93: INR Cr | H93: =SUM($H92:H92) -> 0 | I93: =SUM($H92:I92) -> 0 | J93: =SUM($H92:J92) -> 0 | K93: =SUM($H92:K92) -> 0.429375 | L93: =SUM($H92:L92) -> 1.54575 | M93: =SUM($H92:M92) -> 3.0915 | N93: =SUM($H92:N92) -> 4.809 | O93: =SUM($H92:O92) -> 6.5265 | ... AD93: =SUM($H92:AD92) -> 32.289
B94: 56 | C94: Net Fixed Assets | D94: INR Cr | H94: =H90+H91-H92 -> 0 | I94: =I90+I91-I92 -> 0 | J94: =J90+J91-J92 -> 0 | K94: =K90+K91-K92 -> 8.158125 | L94: =L90+L91-L92 -> 20.78175 | M94: =M90+M91-M92 -> 27.8235 | N94: =N90+N91-N92 -> 29.541 | O94: =O90+O91-O92 -> 27.8235 | ... AD94: =AD90+AD91-AD92 -> 2.061
B95: 57 | C95: =C20 -> Mine Dewatering System | F95: 0.0667
B96: 58 | C96: Opening Balance | D96: INR Cr | H96: =G100 -> 0 | I96: =H100 -> 0 | J96: =I100 -> 0 | K96: =J100 -> 0 | L96: =K100 -> 0 | M96: =L100 -> 2.6371408 | N96: =M100 -> 4.3605366 | O96: =N100 -> 4.0354336 | ... AD96: =AC100 -> 3.7732403
B97: 59 | C97: Addition during year | D97: INR Cr | E97: =SUM(H97:AI97) -> 15 | H97: =H20+H30 -> 0 | I97: =I20+I30 -> 0 | J97: =J20+J30 -> 0 | K97: =K20+K30 -> 0 | L97: =L20+L30 -> 2.8256089 | M97: =M20+M30 -> 2.0484988 | N97: =N20+N30 -> 0 | O97: =O20+O30 -> 0 | ... AD97: =AD20+AD30 -> 0
B98: 60 | C98: Book Depreciation | D98: INR Cr | E98: =SUM(H98:AI98) -> 11.900262 | H98: =H473 -> 0 | I98: =I473 -> 0 | J98: =J473 -> 0 | K98: =K473 -> 0 | L98: =L473 -> 0.18846811 | M98: =M473 -> 0.32510298 | N98: =N473 -> 0.32510298 | O98: =O473 -> 0.32510298 | ... AD98: =AD473 -> 0.67350227
B99: 61 | C99: Accumulated Depreciation | D99: INR Cr | H99: =SUM($H98:H98) -> 0 | I99: =SUM($H98:I98) -> 0 | J99: =SUM($H98:J98) -> 0 | K99: =SUM($H98:K98) -> 0 | L99: =SUM($H98:L98) -> 0.18846811 | M99: =SUM($H98:M98) -> 0.5135711 | N99: =SUM($H98:N98) -> 0.83867408 | O99: =SUM($H98:O98) -> 1.1637771 | ... AD99: =SUM($H98:AD98) -> 11.900262
B100: 62 | C100: Net Fixed Assets | D100: INR Cr | H100: =H96+H97-H98 -> 0 | I100: =I96+I97-I98 -> 0 | J100: =J96+J97-J98 -> 0 | K100: =K96+K97-K98 -> 0 | L100: =L96+L97-L98 -> 2.6371408 | M100: =M96+M97-M98 -> 4.3605366 | N100: =N96+N97-N98 -> 4.0354336 | O100: =O96+O97-O98 -> 3.7103306 | ... AD100: =AD96+AD97-AD98 -> 3.099738
B101: 63 | C101: =C21 -> Digitalisation | F101: 0.3333
B102: 64 | C102: Opening Balance | D102: INR Cr | H102: =G106 -> 0 | I102: =H106 -> 0 | J102: =I106 -> 2.0001 | K102: =J106 -> 4.3337 | L102: =K106 -> 3.0007 | M102: =L106 -> 0.6673 | N102: =M106 -> 0.0002 | O102: =N106 -> -1.110223e-16 | ... AD102: =AC106 -> -1.110223e-16
B103: 65 | C103: Addition during year | D103: INR Cr | E103: =SUM(H103:AI103) -> 10 | H103: =H21+H31 -> 0 | I103: =I21+I31 -> 3 | J103: =J21+J31 -> 5 | K103: =K21+K31 -> 2 | L103: =L21+L31 -> 0 | M103: =M21+M31 -> 0 | N103: =N21+N31 -> 0 | O103: =O21+O31 -> 0 | ... AD103: =AD21+AD31 -> 0
B104: 66 | C104: Book Depreciation | D104: INR Cr | E104: =SUM(H104:AI104) -> 10 | H104: =H501 -> 0 | I104: =I501 -> 0.9999 | J104: =J501 -> 2.6664 | K104: =K501 -> 3.333 | L104: =L501 -> 2.3334 | M104: =M501 -> 0.6671 | N104: =N501 -> 0.0002 | O104: =O501 -> 0 | ... AD104: =AD501 -> 0
...

Sheet Depreciation-MDO
C2: Depreciation Estimation | H2: ='Production Schedule'!E1 -> 46023 | I2: ='Production Schedule'!F1 -> 46389 | J2: ='Production Schedule'!G1 -> 46755 | K2: ='Production Schedule'!H1 -> 47121 | L2: ='Production Schedule'!I1 -> 47487 | M2: ='Production Schedule'!J1 -> 47853 | N2: ='Production Schedule'!K1 -> 48219 | O2: ='Production Schedule'!L1 -> 48585 | ... AK2: ='Production Schedule'!AH1 -> 0
D3: Unit | E3: Total | H3: ='Production Schedule'!E3 -> -4 | I3: ='Production Schedule'!F3 -> -3 | J3: ='Production Schedule'!G3 -> -2 | K3: ='Production Schedule'!H3 -> -1 | L3: ='Production Schedule'!I3 -> 1 | M3: ='Production Schedule'!J3 -> 2 | N3: ='Production Schedule'!K3 -> 3 | O3: ='Production Schedule'!L3 -> 4 | ... AK3: ='Production Schedule'!AH3 -> 0
C4: Production | D4: Mt | E4: =SUM(H4:BE4) -> 225.70441 | H4: ='Production Schedule'!E5 -> 0 | I4: ='Production Schedule'!F5 -> 0 | J4: ='Production Schedule'!G5 -> 0 | K4: ='Production Schedule'!H5 -> 0 | L4: ='Production Schedule'!I5 -> 1.9999998 | M4: ='Production Schedule'!J5 -> 3.9999987 | N4: ='Production Schedule'!K5 -> 8.0000007 | O4: ='Production Schedule'!L5 -> 11.999999 | ... AK4: ='Production Schedule'!AH5 -> 0
C5: Waste Removal | D5: Mbcm | E5: =SUM(H5:BE5) -> 535.39467 | H5: ='Production Schedule'!E8 -> 0 | I5: ='Production Schedule'!F8 -> 0 | J5: ='Production Schedule'!G8 -> 0 | K5: ='Production Schedule'!H8 -> 0 | L5: ='Production Schedule'!I8 -> 11.466046 | M5: ='Production Schedule'!J8 -> 9.5178188 | N5: ='Production Schedule'!K8 -> 17.240515 | O5: ='Production Schedule'!L8 -> 36.817196 | ... AK5: ='Production Schedule'!AH8 -> 0
C6: Waste Rehandle | D6: Mbcm | E6: =SUM(H6:BE6) -> 75.64 | H6: ='Production Schedule'!E13 -> 0 | I6: ='Production Schedule'!F13 -> 0 | J6: ='Production Schedule'!G13 -> 0 | K6: ='Production Schedule'!H13 -> 0 | L6: ='Production Schedule'!I13 -> 0 | M6: ='Production Schedule'!J13 -> 0 | N6: ='Production Schedule'!K13 -> 0 | O6: ='Production Schedule'!L13 -> 0 | ... AK6: ='Production Schedule'!AH13 -> 0
C7: Average Material Handling (AMH) | D7: Mbcm | E7: =SUM(H7:BE7) -> 742.25817 | H7: =(H4/Assumptions_Dashboard!$D$32)+H5+H6 -> 0 | I7: =(I4/Assumptions_Dashboard!$D$32)+I5+I6 -> 0 | J7: =(J4/Assumptions_Dashboard!$D$32)+J5+J6 -> 0 | K7: =(K4/Assumptions_Dashboard!$D$32)+K5+K6 -> 0 | L7: =(L4/Assumptions_Dashboard!$D$32)+L5+L6 -> 12.628836 | M7: =(M4/Assumptions_Dashboard!$D$32)+M5+M6 -> 11.843399 | N7: =(N4/Assumptions_Dashboard!$D$32)+N5+N6 -> 21.891678 | O7: =(O4/Assumptions_Dashboard!$D$32)+O5+O6 -> 43.793939 | ... AK7: =(AK4/Assumptions_Dashboard!$D$32)+AK5+AK6 -> 0
C8: Capital Expenditure
B9: No | C9: ='Owner CAPEX'!B11 -> Pre-operative costs | E9: =SUM(H9:BE9) -> 0 | H9: =IF($B9="Yes",'Owner CAPEX'!E11,0) -> 0 | I9: =IF($B9="Yes",'Owner CAPEX'!F11,0) -> 0 | J9: =IF($B9="Yes",'Owner CAPEX'!G11,0) -> 0 | K9: =IF($B9="Yes",'Owner CAPEX'!H11,0) -> 0 | L9: =IF($B9="Yes",'Owner CAPEX'!I11,0) -> 0 | M9: =IF($B9="Yes",'Owner CAPEX'!J11,0) -> 0 | N9: =IF($B9="Yes",'Owner CAPEX'!K11,0) -> 0 | O9: =IF($B9="Yes",'Owner CAPEX'!L11,0) -> 0 | ... AK9: =IF($B9="Yes",'Owner CAPEX'!AH11,0) -> 0
B10: No | C10: ='Owner CAPEX'!B12 -> Upfront Amount | E10: =SUM(H10:BE10) -> 0 | H10: =IF($B10="Yes",'Owner CAPEX'!E12,0) -> 0 | I10: =IF($B10="Yes",'Owner CAPEX'!I12,0) -> 0 | J10: =IF($B10="Yes",'Owner CAPEX'!G12,0) -> 0 | K10: =IF($B10="Yes",'Owner CAPEX'!H12,0) -> 0 | L10: =IF($B10="Yes",'Owner CAPEX'!#REF!,0) -> 0 | M10: =IF($B10="Yes",'Owner CAPEX'!J12,0) -> 0 | N10: =IF($B10="Yes",'Owner CAPEX'!K12,0) -> 0 | O10: =IF($B10="Yes",'Owner CAPEX'!L12,0) -> 0 | P10: =IF($B10="Yes",'Owner CAPEX'!M12,0) -> 0 | Q10: =IF($B10="Yes",'Owner CAPEX'!N12,0) -> 0 | R10: =IF($B10="Yes",'Owner CAPEX'!O12,0) -> 0 | S10: =IF($B10="Yes",'Owner CAPEX'!P12,0) -> 0 | T10: =IF($B10="Yes",'Owner CAPEX'!Q12,0) -> 0 | ... AK10: =IF($B10="Yes",'Owner CAPEX'!AH12,0) -> 0
B11: No | C11: ='Owner CAPEX'!B13 -> Land Cost | E11: =SUM(H11:BE11) -> 0 | H11: =IF($B11="Yes",'Owner CAPEX'!E13,0) -> 0 | I11: =IF($B11="Yes",'Owner CAPEX'!F13,0) -> 0 | J11: =IF($B11="Yes",'Owner CAPEX'!G13,0) -> 0 | K11: =IF($B11="Yes",'Owner CAPEX'!H13,0) -> 0 | L11: =IF($B11="Yes",'Owner CAPEX'!I13,0) -> 0 | M11: =IF($B11="Yes",'Owner CAPEX'!J13,0) -> 0 | N11: =IF($B11="Yes",'Owner CAPEX'!K13,0) -> 0 | O11: =IF($B11="Yes",'Owner CAPEX'!L13,0) -> 0 | ... AK11: =IF($B11="Yes",'Owner CAPEX'!AH13,0) -> 0
B12: No | C12: ='Owner CAPEX'!B14 -> R&R Cost | E12: =SUM(H12:BE12) -> 0 | H12: =IF($B12="Yes",'Owner CAPEX'!E14,0) -> 0 | I12: =IF($B12="Yes",'Owner CAPEX'!F14,0) -> 0 | J12: =IF($B12="Yes",'Owner CAPEX'!G14,0) -> 0 | K12: =IF($B12="Yes",'Owner CAPEX'!H14,0) -> 0 | L12: =IF($B12="Yes",'Owner CAPEX'!I14,0) -> 0 | M12: =IF($B12="Yes",'Owner CAPEX'!J14,0) -> 0 | N12: =IF($B12="Yes",'Owner CAPEX'!K14,0) -> 0 | O12: =IF($B12="Yes",'Owner CAPEX'!L14,0) -> 0 | ... AK12: =IF($B12="Yes",'Owner CAPEX'!AH14,0) -> 0
B13: Yes | C13: ='Owner CAPEX'!B15 -> HEMM Equipment | E13: =SUM(H13:BE13) -> 0 | H13: =IF($B13="Yes",'MDO CAPEX'!E11,0) -> 0 | I13: =IF($B13="Yes",'MDO CAPEX'!F11,0) -> 0 | J13: =IF($B13="Yes",'MDO CAPEX'!G11,0) -> 0 | K13: =IF($B13="Yes",'MDO CAPEX'!H11,0) -> 0 | L13: =IF($B13="Yes",'MDO CAPEX'!I11,0) -> 0 | M13: =IF($B13="Yes",'MDO CAPEX'!J11,0) -> 0 | N13: =IF($B13="Yes",'MDO CAPEX'!K11,0) -> 0 | O13: =IF($B13="Yes",'MDO CAPEX'!L11,0) -> 0 | ... AK13: =IF($B13="Yes",'MDO CAPEX'!AH11,0) -> 0
B14: No | C14: ='Owner CAPEX'!B16 -> CHP | E14: =SUM(H14:BE14) -> 0 | H14: =IF($B14="Yes",'Owner CAPEX'!E16,0) -> 0 | I14: =IF($B14="Yes",'Owner CAPEX'!F16,0) -> 0 | J14: =IF($B14="Yes",'Owner CAPEX'!G16,0) -> 0 | K14: =IF($B14="Yes",'Owner CAPEX'!H16,0) -> 0 | L14: =IF($B14="Yes",'Owner CAPEX'!I16,0) -> 0 | M14: =IF($B14="Yes",'Owner CAPEX'!J16,0) -> 0 | N14: =IF($B14="Yes",'Owner CAPEX'!K16,0) -> 0 | O14: =IF($B14="Yes",'Owner CAPEX'!L16,0) -> 0 | ... AK14: =IF($B14="Yes",'Owner CAPEX'!AH16,0) -> 0
B15: No | C15: ='Owner CAPEX'!B17 -> Railway Siding | E15: =SUM(H15:BE15) -> 0 | H15: =IF($B15="Yes",'Owner CAPEX'!E17,0) -> 0 | I15: =IF($B15="Yes",'Owner CAPEX'!F17,0) -> 0 | J15: =IF($B15="Yes",'Owner CAPEX'!G17,0) -> 0 | K15: =IF($B15="Yes",'Owner CAPEX'!H17,0) -> 0 | L15: =IF($B15="Yes",'Owner CAPEX'!I17,0) -> 0 | M15: =IF($B15="Yes",'Owner CAPEX'!J17,0) -> 0 | N15: =IF($B15="Yes",'Owner CAPEX'!K17,0) -> 0 | O15: =IF($B15="Yes",'Owner CAPEX'!L17,0) -> 0 | ... AK15: =IF($B15="Yes",'Owner CAPEX'!AH17,0) -> 0
B16: Yes | C16: ='Owner CAPEX'!B18 -> Civil Infrastructure | E16: =SUM(H16:BE16) -> 0 | H16: =IF($B16="Yes",'MDO CAPEX'!E12,0) -> 0 | I16: =IF($B16="Yes",'MDO CAPEX'!F12,0) -> 0 | J16: =IF($B16="Yes",'MDO CAPEX'!G12,0) -> 0 | K16: =IF($B16="Yes",'MDO CAPEX'!H12,0) -> 0 | L16: =IF($B16="Yes",'MDO CAPEX'!I12,0) -> 0 | M16: =IF($B16="Yes",'MDO CAPEX'!J12,0) -> 0 | N16: =IF($B16="Yes",'MDO CAPEX'!K12,0) -> 0 | O16: =IF($B16="Yes",'MDO CAPEX'!L12,0) -> 0 | ... AK16: =IF($B16="Yes",'MDO CAPEX'!AH12,0) -> 0
B17: Yes | C17: ='Owner CAPEX'!B19 -> Fire Fighting & Dust Suppression | E17: =SUM(H17:BE17) -> 0 | H17: =IF($B17="Yes",'MDO CAPEX'!E13,0) -> 0 | I17: =IF($B17="Yes",'MDO CAPEX'!F13,0) -> 0 | J17: =IF($B17="Yes",'MDO CAPEX'!G13,0) -> 0 | K17: =IF($B17="Yes",'MDO CAPEX'!H13,0) -> 0 | L17: =IF($B17="Yes",'MDO CAPEX'!I13,0) -> 0 | M17: =IF($B17="Yes",'MDO CAPEX'!J13,0) -> 0 | N17: =IF($B17="Yes",'MDO CAPEX'!K13,0) -> 0 | O17: =IF($B17="Yes",'MDO CAPEX'!L13,0) -> 0 | ... AK17: =IF($B17="Yes",'MDO CAPEX'!AH13,0) -> 0
B18: Yes | C18: ='Owner CAPEX'!B20 -> Workshop and Store | E18: =SUM(H18:BE18) -> 0 | H18: =IF($B18="Yes",'MDO CAPEX'!E14,0) -> 0 | I18: =IF($B18="Yes",'MDO CAPEX'!F14,0) -> 0 | J18: =IF($B18="Yes",'MDO CAPEX'!G14,0) -> 0 | K18: =IF($B18="Yes",'MDO CAPEX'!H14,0) -> 0 | L18: =IF($B18="Yes",'MDO CAPEX'!I14,0) -> 0 | M18: =IF($B18="Yes",'MDO CAPEX'!J14,0) -> 0 | N18: =IF($B18="Yes",'MDO CAPEX'!K14,0) -> 0 | O18: =IF($B18="Yes",'MDO CAPEX'!L14,0) -> 0 | ... AK18: =IF($B18="Yes",'MDO CAPEX'!AH14,0) -> 0
B19: Yes | C19: ='Owner CAPEX'!B21 -> Electrical | E19: =SUM(H19:BE19) -> 0 | H19: =IF($B19="Yes",'MDO CAPEX'!E15,0) -> 0 | I19: =IF($B19="Yes",'MDO CAPEX'!F15,0) -> 0 | J19: =IF($B19="Yes",'MDO CAPEX'!G15,0) -> 0 | K19: =IF($B19="Yes",'MDO CAPEX'!H15,0) -> 0 | L19: =IF($B19="Yes",'MDO CAPEX'!I15,0) -> 0 | M19: =IF($B19="Yes",'MDO CAPEX'!J15,0) -> 0 | N19: =IF($B19="Yes",'MDO CAPEX'!K15,0) -> 0 | O19: =IF($B19="Yes",'MDO CAPEX'!L15,0) -> 0 | ... AK19: =IF($B19="Yes",'MDO CAPEX'!AH15,0) -> 0
B20: Yes | C20: ='Owner CAPEX'!B22 -> Mine Dewatering System | E20: =SUM(H20:BE20) -> 0 | H20: =IF($B20="Yes",'MDO CAPEX'!E16,0) -> 0 | I20: =IF($B20="Yes",'MDO CAPEX'!F16,0) -> 0 | J20: =IF($B20="Yes",'MDO CAPEX'!G16,0) -> 0 | K20: =IF($B20="Yes",'MDO CAPEX'!H16,0) -> 0 | L20: =IF($B20="Yes",'MDO CAPEX'!I16,0) -> 0 | M20: =IF($B20="Yes",'MDO CAPEX'!J16,0) -> 0 | N20: =IF($B20="Yes",'MDO CAPEX'!K16,0) -> 0 | O20: =IF($B20="Yes",'MDO CAPEX'!L16,0) -> 0 | ... AK20: =IF($B20="Yes",'MDO CAPEX'!AH16,0) -> 0
B21: Yes | C21: ='Owner CAPEX'!B23 -> Digitalisation | E21: =SUM(H21:BE21) -> 0 | H21: =IF($B21="Yes",'MDO CAPEX'!E17,0) -> 0 | I21: =IF($B21="Yes",'MDO CAPEX'!F17,0) -> 0 | J21: =IF($B21="Yes",'MDO CAPEX'!G17,0) -> 0 | K21: =IF($B21="Yes",'MDO CAPEX'!H17,0) -> 0 | L21: =IF($B21="Yes",'MDO CAPEX'!I17,0) -> 0 | M21: =IF($B21="Yes",'MDO CAPEX'!J17,0) -> 0 | N21: =IF($B21="Yes",'MDO CAPEX'!K17,0) -> 0 | O21: =IF($B21="Yes",'MDO CAPEX'!L17,0) -> 0 | ... AK21: =IF($B21="Yes",'MDO CAPEX'!AH17,0) -> 0
B22: Yes | C22: ='Owner CAPEX'!B24 -> Contingency | E22: =SUM(H22:BE22) -> 0 | H22: =IF($B22="Yes",'MDO CAPEX'!E18,0) -> 0 | I22: =IF($B22="Yes",'MDO CAPEX'!F18,0) -> 0 | J22: =IF($B22="Yes",'MDO CAPEX'!G18,0) -> 0 | K22: =IF($B22="Yes",'MDO CAPEX'!H18,0) -> 0 | L22: =IF($B22="Yes",'MDO CAPEX'!I18,0) -> 0 | M22: =IF($B22="Yes",'MDO CAPEX'!J18,0) -> 0 | N22: =IF($B22="Yes",'MDO CAPEX'!K18,0) -> 0 | O22: =IF($B22="Yes",'MDO CAPEX'!L18,0) -> 0 | ... AK22: =IF($B22="Yes",'MDO CAPEX'!AH18,0) -> 0
C23: Sub-Total | E23: =SUM(H23:BE23) -> 0 | H23: =SUM(H9:H22) -> 0 | I23: =SUM(I9:I22) -> 0 | J23: =SUM(J9:J22) -> 0 | K23: =SUM(K9:K22) -> 0 | L23: =SUM(L9:L22) -> 0 | M23: =SUM(M9:M22) -> 0 | N23: =SUM(N9:N22) -> 0 | O23: =SUM(O9:O22) -> 0 | ... AK23: =SUM(AK9:AK22) -> 0
C24: Sustainable Expenditure
B25: Yes | C25: ='Owner CAPEX'!B31 -> Mining Equipment Replacement | E25: =SUM(H25:BE25) -> 0 | H25: =IF($B25="Yes",'MDO CAPEX'!E25,0) -> 0 | I25: =IF($B25="Yes",'MDO CAPEX'!F25,0) -> 0 | J25: =IF($B25="Yes",'MDO CAPEX'!G25,0) -> 0 | K25: =IF($B25="Yes",'MDO CAPEX'!H25,0) -> 0 | L25: =IF($B25="Yes",'MDO CAPEX'!I25,0) -> 0 | M25: =IF($B25="Yes",'MDO CAPEX'!J25,0) -> 0 | N25: =IF($B25="Yes",'MDO CAPEX'!K25,0) -> 0 | O25: =IF($B25="Yes",'MDO CAPEX'!L25,0) -> 0 | ... AK25: =IF($B25="Yes",'MDO CAPEX'!AH25,0) -> 0
B26: No | C26: ='Owner CAPEX'!B32 -> CHP | E26: =SUM(H26:BE26) -> 0 | H26: =IF($B26="Yes",'Owner CAPEX'!E32,0) -> 0 | I26: =IF($B26="Yes",'Owner CAPEX'!F32,0) -> 0 | J26: =IF($B26="Yes",'Owner CAPEX'!G32,0) -> 0 | K26: =IF($B26="Yes",'Owner CAPEX'!H32,0) -> 0 | L26: =IF($B26="Yes",'Owner CAPEX'!I32,0) -> 0 | M26: =IF($B26="Yes",'Owner CAPEX'!J32,0) -> 0 | N26: =IF($B26="Yes",'Owner CAPEX'!K32,0) -> 0 | O26: =IF($B26="Yes",'Owner CAPEX'!L32,0) -> 0 | ... AK26: =IF($B26="Yes",'Owner CAPEX'!AH32,0) -> 0
B27: Yes | C27: ='Owner CAPEX'!B33 -> Civil Infrastructure | E27: =SUM(H27:BE27) -> 0 | H27: =IF($B27="Yes",'MDO CAPEX'!E26,0) -> 0 | I27: =IF($B27="Yes",'MDO CAPEX'!F26,0) -> 0 | J27: =IF($B27="Yes",'MDO CAPEX'!G26,0) -> 0 | K27: =IF($B27="Yes",'MDO CAPEX'!H26,0) -> 0 | L27: =IF($B27="Yes",'MDO CAPEX'!I26,0) -> 0 | M27: =IF($B27="Yes",'MDO CAPEX'!J26,0) -> 0 | N27: =IF($B27="Yes",'MDO CAPEX'!K26,0) -> 0 | O27: =IF($B27="Yes",'MDO CAPEX'!L26,0) -> 0 | ... AK27: =IF($B27="Yes",'MDO CAPEX'!AH26,0) -> 0
B28: Yes | C28: ='Owner CAPEX'!B34 -> Workshop and Store | E28: =SUM(H28:BE28) -> 0 | H28: =IF($B28="Yes",'MDO CAPEX'!E27,0) -> 0 | I28: =IF($B28="Yes",'MDO CAPEX'!F27,0) -> 0 | J28: =IF($B28="Yes",'MDO CAPEX'!G27,0) -> 0 | K28: =IF($B28="Yes",'MDO CAPEX'!H27,0) -> 0 | L28: =IF($B28="Yes",'MDO CAPEX'!I27,0) -> 0 | M28: =IF($B28="Yes",'MDO CAPEX'!J27,0) -> 0 | N28: =IF($B28="Yes",'MDO CAPEX'!K27,0) -> 0 | O28: =IF($B28="Yes",'MDO CAPEX'!L27,0) -> 0 | ... AK28: =IF($B28="Yes",'MDO CAPEX'!AH27,0) -> 0
B29: Yes | C29: ='Owner CAPEX'!B35 -> Electrical | E29: =SUM(H29:BE29) -> 0 | H29: =IF($B29="Yes",'MDO CAPEX'!E28,0) -> 0 | I29: =IF($B29="Yes",'MDO CAPEX'!F28,0) -> 0 | J29: =IF($B29="Yes",'MDO CAPEX'!G28,0) -> 0 | K29: =IF($B29="Yes",'MDO CAPEX'!H28,0) -> 0 | L29: =IF($B29="Yes",'MDO CAPEX'!I28,0) -> 0 | M29: =IF($B29="Yes",'MDO CAPEX'!J28,0) -> 0 | N29: =IF($B29="Yes",'MDO CAPEX'!K28,0) -> 0 | O29: =IF($B29="Yes",'MDO CAPEX'!L28,0) -> 0 | ... AK29: =IF($B29="Yes",'MDO CAPEX'!AH28,0) -> 0
B30: Yes | C30: ='Owner CAPEX'!B36 -> Mine Dewatering System | E30: =SUM(H30:BE30) -> 0 | H30: =IF($B30="Yes",'MDO CAPEX'!E29,0) -> 0 | I30: =IF($B30="Yes",'MDO CAPEX'!F29,0) -> 0 | J30: =IF($B30="Yes",'MDO CAPEX'!G29,0) -> 0 | K30: =IF($B30="Yes",'MDO CAPEX'!H29,0) -> 0 | L30: =IF($B30="Yes",'MDO CAPEX'!I29,0) -> 0 | M30: =IF($B30="Yes",'MDO CAPEX'!J29,0) -> 0 | N30: =IF($B30="Yes",'MDO CAPEX'!K29,0) -> 0 | O30: =IF($B30="Yes",'MDO CAPEX'!L29,0) -> 0 | ... AK30: =IF($B30="Yes",'MDO CAPEX'!AH29,0) -> 0
B31: Yes | C31: ='Owner CAPEX'!B37 -> Digitalisation | E31: =SUM(H31:BE31) -> 0 | H31: =IF($B31="Yes",'MDO CAPEX'!E30,0) -> 0 | I31: =IF($B31="Yes",'MDO CAPEX'!F30,0) -> 0 | J31: =IF($B31="Yes",'MDO CAPEX'!G30,0) -> 0 | K31: =IF($B31="Yes",'MDO CAPEX'!H30,0) -> 0 | L31: =IF($B31="Yes",'MDO CAPEX'!I30,0) -> 0 | M31: =IF($B31="Yes",'MDO CAPEX'!J30,0) -> 0 | N31: =IF($B31="Yes",'MDO CAPEX'!K30,0) -> 0 | O31: =IF($B31="Yes",'MDO CAPEX'!L30,0) -> 0 | ... AK31: =IF($B31="Yes",'MDO CAPEX'!AH30,0) -> 0
B32: Yes | C32: ='Owner CAPEX'!B38 -> Contingency | E32: =SUM(H32:BE32) -> 0 | H32: =IF($B32="Yes",'MDO CAPEX'!E31,0) -> 0 | I32: =IF($B32="Yes",'MDO CAPEX'!F31,0) -> 0 | J32: =IF($B32="Yes",'MDO CAPEX'!G31,0) -> 0 | K32: =IF($B32="Yes",'MDO CAPEX'!H31,0) -> 0 | L32: =IF($B32="Yes",'MDO CAPEX'!I31,0) -> 0 | M32: =IF($B32="Yes",'MDO CAPEX'!J31,0) -> 0 | N32: =IF($B32="Yes",'MDO CAPEX'!K31,0) -> 0 | O32: =IF($B32="Yes",'MDO CAPEX'!L31,0) -> 0 | ... AK32: =IF($B32="Yes",'MDO CAPEX'!AH31,0) -> 0
C33: Sub-Total | E33: =SUM(H33:BE33) -> 0 | H33: =SUM(H25:H32) -> 0 | I33: =SUM(I25:I32) -> 0 | J33: =SUM(J25:J32) -> 0 | K33: =SUM(K25:K32) -> 0 | L33: =SUM(L25:L32) -> 0 | M33: =SUM(M25:M32) -> 0 | N33: =SUM(N25:N32) -> 0 | O33: =SUM(O25:O32) -> 0 | ... AK33: =SUM(AK25:AK32) -> 0
C35: Total Capital Expenditure | E35: =SUM(H35:BE35) -> 0 | F35: =E35='MDO CAPEX'!D34-'MDO CAPEX'!D19 -> TRUE | H35: =H23+H33 -> 0 | I35: =I23+I33 -> 0 | J35: =J23+J33 -> 0 | K35: =K23+K33 -> 0 | L35: =L23+L33 -> 0 | M35: =M23+M33 -> 0 | N35: =N23+N33 -> 0 | O35: =O23+O33 -> 0 | ... AK35: =AK23+AK33 -> 0
C38: Depreciation- As pere books (Straight Line Method)
B39: 1 | C39: List | H39: =H2 -> 46023 | I39: =I2 -> 46389 | J39: =J2 -> 46755 | K39: =K2 -> 47121 | L39: =L2 -> 47487 | M39: =M2 -> 47853 | N39: =N2 -> 48219 | O39: =O2 -> 48585 | ... AK39: =AK2 -> 0
B40: 2 | H40: =H3 -> -4 | I40: =I3 -> -3 | J40: =J3 -> -2 | K40: =K3 -> -1 | L40: =L3 -> 1 | M40: =M3 -> 2 | N40: =N3 -> 3 | O40: =O3 -> 4 | ... AK40: =AK3 -> 0
B41: 3 | C41: =C9 -> Pre-operative costs | F41: 0.1
B42: 4 | C42: Opening Balance | D42: INR Cr | H42: =G46 -> 0 | I42: =H46 -> 0 | J42: =I46 -> 0 | K42: =J46 -> 0 | L42: =K46 -> 0 | M42: =L46 -> 0 | N42: =M46 -> 0 | O42: =N46 -> 0 | ... AK42: =AJ46 -> 0
B43: 5 | C43: Addition during year | D43: INR Cr | E43: =SUM(H43:AP43) -> 0 | H43: =H9 -> 0 | I43: =I9 -> 0 | J43: =J9 -> 0 | K43: =K9 -> 0 | L43: =L9 -> 0 | M43: =M9 -> 0 | N43: =N9 -> 0 | O43: =O9 -> 0 | ... AK43: =AK9 -> 0
B44: 6 | C44: Book Depreciation | D44: INR Cr | E44: =SUM(H44:AP44) -> 0 | H44: =H228 -> 0 | I44: =I228 -> 0 | J44: =J228 -> 0 | K44: =K228 -> 0 | L44: =L228 -> 0 | M44: =M228 -> 0 | N44: =N228 -> 0 | O44: =O228 -> 0 | ... AK44: =AK228 -> 0
B45: 7 | C45: Accumulated Depreciation | D45: INR Cr | H45: =SUM($H44:H44) -> 0 | I45: =SUM($H44:I44) -> 0 | J45: =SUM($H44:J44) -> 0 | K45: =SUM($H44:K44) -> 0 | L45: =SUM($H44:L44) -> 0 | M45: =SUM($H44:M44) -> 0 | N45: =SUM($H44:N44) -> 0 | O45: =SUM($H44:O44) -> 0 | ... AK45: =SUM($H44:AK44) -> 0
B46: 8 | C46: Net Fixed Assets | D46: INR Cr | H46: =H42+H43-H44 -> 0 | I46: =I42+I43-I44 -> 0 | J46: =J42+J43-J44 -> 0 | K46: =K42+K43-K44 -> 0 | L46: =L42+L43-L44 -> 0 | M46: =M42+M43-M44 -> 0 | N46: =N42+N43-N44 -> 0 | O46: =O42+O43-O44 -> 0 | ... AK46: =AK42+AK43-AK44 -> 0
B47: 9 | C47: =C11 -> Land Cost | F47: 0
B48: 10 | C48: Opening Balance | D48: INR Cr | H48: =G52 -> 0 | I48: =H52 -> 0 | J48: =I52 -> 0 | K48: =J52 -> 0 | L48: =K52 -> 0 | M48: =L52 -> 0 | N48: =M52 -> 0 | O48: =N52 -> 0 | ... AK48: =AJ52 -> 0
B49: 11 | C49: Addition during year | D49: INR Cr | E49: =SUM(H49:AP49) -> 0 | H49: =H11 -> 0 | I49: =I11 -> 0 | J49: =J11 -> 0 | K49: =K11 -> 0 | L49: =L11 -> 0 | M49: =M11 -> 0 | N49: =N11 -> 0 | O49: =O11 -> 0 | ... AK49: =AK11 -> 0
B50: 12 | C50: Book Depreciation | D50: INR Cr | E50: =SUM(H50:AP50) -> 0 | H50: =H263 -> 0 | I50: =I263 -> 0 | J50: =J263 -> 0 | K50: =K263 -> 0 | L50: =L263 -> 0 | M50: =M263 -> 0 | N50: =N263 -> 0 | O50: =O263 -> 0 | ... AK50: =AK263 -> 0
B51: 13 | C51: Accumulated Depreciation | D51: INR Cr | H51: =SUM($H50:H50) -> 0 | I51: =SUM($H50:I50) -> 0 | J51: =SUM($H50:J50) -> 0 | K51: =SUM($H50:K50) -> 0 | L51: =SUM($H50:L50) -> 0 | M51: =SUM($H50:M50) -> 0 | N51: =SUM($H50:N50) -> 0 | O51: =SUM($H50:O50) -> 0 | ... AK51: =SUM($H50:AK50) -> 0
B52: 14 | C52: Net Fixed Assets | D52: INR Cr | H52: =H48+H49-H50 -> 0 | I52: =I48+I49-I50 -> 0 | J52: =J48+J49-J50 -> 0 | K52: =K48+K49-K50 -> 0 | L52: =L48+L49-L50 -> 0 | M52: =M48+M49-M50 -> 0 | N52: =N48+N49-N50 -> 0 | O52: =O48+O49-O50 -> 0 | ... AK52: =AK48+AK49-AK50 -> 0
B53: 15 | C53: =C13 -> HEMM Equipment | F53: 0.1188
B54: 16 | C54: Opening Balance | D54: INR Cr | H54: =G58 -> 0 | I54: =H58 -> 0 | J54: =I58 -> 0 | K54: =J58 -> 0 | L54: =K58 -> 0 | M54: =L58 -> 0 | N54: =M58 -> 0 | O54: =N58 -> 0 | ... AK54: =AJ58 -> 0
B55: 17 | C55: Addition during year | D55: INR Cr | E55: =SUM(H55:AP55) -> 0 | H55: =H13+H25 -> 0 | I55: =I13+I25 -> 0 | J55: =J13+J25 -> 0 | K55: =K13+K25 -> 0 | L55: =L13+L25 -> 0 | M55: =M13+M25 -> 0 | N55: =N13+N25 -> 0 | O55: =O13+O25 -> 0 | ... AK55: =AK13+AK25 -> 0
B56: 18 | C56: Book Depreciation | D56: INR Cr | E56: =SUM(H56:AP56) -> 0 | H56: =H298 -> 0 | I56: =I298 -> 0 | J56: =J298 -> 0 | K56: =K298 -> 0 | L56: =L298 -> 0 | M56: =M298 -> 0 | N56: =N298 -> 0 | O56: =O298 -> 0 | ... AK56: =AK298 -> 0
B57: 19 | C57: Accumulated Depreciation | D57: INR Cr | H57: =SUM($H56:H56) -> 0 | I57: =SUM($H56:I56) -> 0 | J57: =SUM($H56:J56) -> 0 | K57: =SUM($H56:K56) -> 0 | L57: =SUM($H56:L56) -> 0 | M57: =SUM($H56:M56) -> 0 | N57: =SUM($H56:N56) -> 0 | O57: =SUM($H56:O56) -> 0 | ... AK57: =SUM($H56:AK56) -> 0
B58: 20 | C58: Net Fixed Assets | D58: INR Cr | H58: =H54+H55-H56 -> 0 | I58: =I54+I55-I56 -> 0 | J58: =J54+J55-J56 -> 0 | K58: =K54+K55-K56 -> 0 | L58: =L54+L55-L56 -> 0 | M58: =M54+M55-M56 -> 0 | N58: =N54+N55-N56 -> 0 | O58: =O54+O55-O56 -> 0 | ... AK58: =AK54+AK55-AK56 -> 0
B59: 21 | C59: =C14 -> CHP | F59: 0.0667
B60: 22 | C60: Opening Balance | D60: INR Cr | H60: =G64 -> 0 | I60: =H64 -> 0 | J60: =I64 -> 0 | K60: =J64 -> 0 | L60: =K64 -> 0 | M60: =L64 -> 0 | N60: =M64 -> 0 | O60: =N64 -> 0 | ... AK60: =AJ64 -> 0
B61: 23 | C61: Addition during year | D61: INR Cr | E61: =SUM(H61:AP61) -> 0 | H61: =H14+H26 -> 0 | I61: =I14+I26 -> 0 | J61: =J14+J26 -> 0 | K61: =K14+K26 -> 0 | L61: =L14+L26 -> 0 | M61: =M14+M26 -> 0 | N61: =N14+N26 -> 0 | O61: =O14+O26 -> 0 | ... AK61: =AK14+AK26 -> 0
B62: 24 | C62: Book Depreciation | D62: INR Cr | E62: =SUM(H62:AP62) -> 0 | H62: =H333 -> 0 | I62: =I333 -> 0 | J62: =J333 -> 0 | K62: =K333 -> 0 | L62: =L333 -> 0 | M62: =M333 -> 0 | N62: =N333 -> 0 | O62: =O333 -> 0 | ... AK62: =AK333 -> 0
B63: 25 | C63: Accumulated Depreciation | D63: INR Cr | H63: =SUM($H62:H62) -> 0 | I63: =SUM($H62:I62) -> 0 | J63: =SUM($H62:J62) -> 0 | K63: =SUM($H62:K62) -> 0 | L63: =SUM($H62:L62) -> 0 | M63: =SUM($H62:M62) -> 0 | N63: =SUM($H62:N62) -> 0 | O63: =SUM($H62:O62) -> 0 | ... AK63: =SUM($H62:AK62) -> 0
B64: 26 | C64: Net Fixed Assets | D64: INR Cr | H64: =H60+H61-H62 -> 0 | I64: =I60+I61-I62 -> 0 | J64: =J60+J61-J62 -> 0 | K64: =K60+K61-K62 -> 0 | L64: =L60+L61-L62 -> 0 | M64: =M60+M61-M62 -> 0 | N64: =N60+N61-N62 -> 0 | O64: =O60+O61-O62 -> 0 | ... AK64: =AK60+AK61-AK62 -> 0
B65: 27 | C65: =C15 -> Railway Siding | F65: 0.05
B66: 28 | C66: Opening Balance | D66: INR Cr | H66: =G70 -> 0 | I66: =H70 -> 0 | J66: =I70 -> 0 | K66: =J70 -> 0 | L66: =K70 -> 0 | M66: =L70 -> 0 | N66: =M70 -> 0 | O66: =N70 -> 0 | ... AK66: =AJ70 -> 0
B67: 29 | C67: Addition during year | D67: INR Cr | E67: =SUM(H67:AP67) -> 0 | H67: =H15 -> 0 | I67: =I15 -> 0 | J67: =J15 -> 0 | K67: =K15 -> 0 | L67: =L15 -> 0 | M67: =M15 -> 0 | N67: =N15 -> 0 | O67: =O15 -> 0 | ... AK67: =AK15 -> 0
B68: 30 | C68: Book Depreciation | D68: INR Cr | E68: =SUM(H68:AP68) -> 0 | H68: =H368 -> 0 | I68: =I368 -> 0 | J68: =J368 -> 0 | K68: =K368 -> 0 | L68: =L368 -> 0 | M68: =M368 -> 0 | N68: =N368 -> 0 | O68: =O368 -> 0 | ... AK68: =AK368 -> 0
B69: 31 | C69: Accumulated Depreciation | D69: INR Cr | H69: =SUM($H68:H68) -> 0 | I69: =SUM($H68:I68) -> 0 | J69: =SUM($H68:J68) -> 0 | K69: =SUM($H68:K68) -> 0 | L69: =SUM($H68:L68) -> 0 | M69: =SUM($H68:M68) -> 0 | N69: =SUM($H68:N68) -> 0 | O69: =SUM($H68:O68) -> 0 | ... AK69: =SUM($H68:AK68) -> 0
B70: 32 | C70: Net Fixed Assets | D70: INR Cr | H70: =H66+H67-H68 -> 0 | I70: =I66+I67-I68 -> 0 | J70: =J66+J67-J68 -> 0 | K70: =K66+K67-K68 -> 0 | L70: =L66+L67-L68 -> 0 | M70: =M66+M67-M68 -> 0 | N70: =N66+N67-N68 -> 0 | O70: =O66+O67-O68 -> 0 | ... AK70: =AK66+AK67-AK68 -> 0
B71: 33 | C71: =C16 -> Civil Infrastructure | F71: 0.0317
B72: 34 | C72: Opening Balance | D72: INR Cr | H72: =G76 -> 0 | I72: =H76 -> 0 | J72: =I76 -> 0 | K72: =J76 -> 0 | L72: =K76 -> 0 | M72: =L76 -> 0 | N72: =M76 -> 0 | O72: =N76 -> 0 | ... AK72: =AJ76 -> 0
B73: 35 | C73: Addition during year | D73: INR Cr | E73: =SUM(H73:AP73) -> 0 | H73: =H16+H27 -> 0 | I73: =I16+I27 -> 0 | J73: =J16+J27 -> 0 | K73: =K16+K27 -> 0 | L73: =L16+L27 -> 0 | M73: =M16+M27 -> 0 | N73: =N16+N27 -> 0 | O73: =O16+O27 -> 0 | ... AK73: =AK16+AK27 -> 0
B74: 36 | C74: Book Depreciation | D74: INR Cr | E74: =SUM(H74:AP74) -> 0 | H74: =H403 -> 0 | I74: =I403 -> 0 | J74: =J403 -> 0 | K74: =K403 -> 0 | L74: =L403 -> 0 | M74: =M403 -> 0 | N74: =N403 -> 0 | O74: =O403 -> 0 | ... AK74: =AK403 -> 0
B75: 37 | C75: Accumulated Depreciation | D75: INR Cr | H75: =SUM($H74:H74) -> 0 | I75: =SUM($H74:I74) -> 0 | J75: =SUM($H74:J74) -> 0 | K75: =SUM($H74:K74) -> 0 | L75: =SUM($H74:L74) -> 0 | M75: =SUM($H74:M74) -> 0 | N75: =SUM($H74:N74) -> 0 | O75: =SUM($H74:O74) -> 0 | ... AK75: =SUM($H74:AK74) -> 0
B76: 38 | C76: Net Fixed Assets | D76: INR Cr | H76: =H72+H73-H74 -> 0 | I76: =I72+I73-I74 -> 0 | J76: =J72+J73-J74 -> 0 | K76: =K72+K73-K74 -> 0 | L76: =L72+L73-L74 -> 0 | M76: =M72+M73-M74 -> 0 | N76: =N72+N73-N74 -> 0 | O76: =O72+O73-O74 -> 0 | ... AK76: =AK72+AK73-AK74 -> 0
B77: 39 | C77: =C17 -> Fire Fighting & Dust Suppression | F77: 0.0667
B78: 40 | C78: Opening Balance | D78: INR Cr | H78: =G82 -> 0 | I78: =H82 -> 0 | J78: =I82 -> 0 | K78: =J82 -> 0 | L78: =K82 -> 0 | M78: =L82 -> 0 | N78: =M82 -> 0 | O78: =N82 -> 0 | ... AK78: =AJ82 -> 0
B79: 41 | C79: Addition during year | D79: INR Cr | E79: =SUM(H79:AP79) -> 0 | H79: =H17 -> 0 | I79: =I17 -> 0 | J79: =J17 -> 0 | K79: =K17 -> 0 | L79: =L17 -> 0 | M79: =M17 -> 0 | N79: =N17 -> 0 | O79: =O17 -> 0 | ... AK79: =AK17 -> 0
B80: 42 | C80: Book Depreciation | D80: INR Cr | E80: =SUM(H80:AP80) -> 0 | H80: =H438 -> 0 | I80: =I438 -> 0 | J80: =J438 -> 0 | K80: =K438 -> 0 | L80: =L438 -> 0 | M80: =M438 -> 0 | N80: =N438 -> 0 | O80: =O438 -> 0 | ... AK80: =AK438 -> 0
B81: 43 | C81: Accumulated Depreciation | D81: INR Cr | H81: =SUM($H80:H80) -> 0 | I81: =SUM($H80:I80) -> 0 | J81: =SUM($H80:J80) -> 0 | K81: =SUM($H80:K80) -> 0 | L81: =SUM($H80:L80) -> 0 | M81: =SUM($H80:M80) -> 0 | N81: =SUM($H80:N80) -> 0 | O81: =SUM($H80:O80) -> 0 | ... AK81: =SUM($H80:AK80) -> 0
B82: 44 | C82: Net Fixed Assets | D82: INR Cr | H82: =H78+H79-H80 -> 0 | I82: =I78+I79-I80 -> 0 | J82: =J78+J79-J80 -> 0 | K82: =K78+K79-K80 -> 0 | L82: =L78+L79-L80 -> 0 | M82: =M78+M79-M80 -> 0 | N82: =N78+N79-N80 -> 0 | O82: =O78+O79-O80 -> 0 | ... AK82: =AK78+AK79-AK80 -> 0
B83: 45 | C83: =C18 -> Workshop and Store | F83: 0.0667
B84: 46 | C84: Opening Balance | D84: INR Cr | H84: =G88 -> 0 | I84: =H88 -> 0 | J84: =I88 -> 0 | K84: =J88 -> 0 | L84: =K88 -> 0 | M84: =L88 -> 0 | N84: =M88 -> 0 | O84: =N88 -> 0 | ... AK84: =AJ88 -> 0
B85: 47 | C85: Addition during year | D85: INR Cr | E85: =SUM(H85:AP85) -> 0 | H85: =H18+H28 -> 0 | I85: =I18+I28 -> 0 | J85: =J18+J28 -> 0 | K85: =K18+K28 -> 0 | L85: =L18+L28 -> 0 | M85: =M18+M28 -> 0 | N85: =N18+N28 -> 0 | O85: =O18+O28 -> 0 | ... AK85: =AK18+AK28 -> 0
B86: 48 | C86: Book Depreciation | D86: INR Cr | E86: =SUM(H86:AP86) -> 0 | H86: =H473 -> 0 | I86: =I473 -> 0 | J86: =J473 -> 0 | K86: =K473 -> 0 | L86: =L473 -> 0 | M86: =M473 -> 0 | N86: =N473 -> 0 | O86: =O473 -> 0 | ... AK86: =AK473 -> 0
B87: 49 | C87: Accumulated Depreciation | D87: INR Cr | H87: =SUM($H86:H86) -> 0 | I87: =SUM($H86:I86) -> 0 | J87: =SUM($H86:J86) -> 0 | K87: =SUM($H86:K86) -> 0 | L87: =SUM($H86:L86) -> 0 | M87: =SUM($H86:M86) -> 0 | N87: =SUM($H86:N86) -> 0 | O87: =SUM($H86:O86) -> 0 | ... AK87: =SUM($H86:AK86) -> 0
B88: 50 | C88: Net Fixed Assets | D88: INR Cr | H88: =H84+H85-H86 -> 0 | I88: =I84+I85-I86 -> 0 | J88: =J84+J85-J86 -> 0 | K88: =K84+K85-K86 -> 0 | L88: =L84+L85-L86 -> 0 | M88: =M84+M85-M86 -> 0 | N88: =N84+N85-N86 -> 0 | O88: =O84+O85-O86 -> 0 | ... AK88: =AK84+AK85-AK86 -> 0
B89: 51 | C89: =C19 -> Electrical | F89: 0.05
B90: 52 | C90: Opening Balance | D90: INR Cr | H90: =G94 -> 0 | I90: =H94 -> 0 | J90: =I94 -> 0 | K90: =J94 -> 0 | L90: =K94 -> 0 | M90: =L94 -> 0 | N90: =M94 -> 0 | O90: =N94 -> 0 | ... AK90: =AJ94 -> 0
B91: 53 | C91: Addition during year | D91: INR Cr | E91: =SUM(H91:AP91) -> 0 | H91: =H19+H29 -> 0 | I91: =I19+I29 -> 0 | J91: =J19+J29 -> 0 | K91: =K19+K29 -> 0 | L91: =L19+L29 -> 0 | M91: =M19+M29 -> 0 | N91: =N19+N29 -> 0 | O91: =O19+O29 -> 0 | ... AK91: =AK19+AK29 -> 0
B92: 54 | C92: Book Depreciation | D92: INR Cr | E92: =SUM(H92:AP92) -> 0 | H92: =H508 -> 0 | I92: =I508 -> 0 | J92: =J508 -> 0 | K92: =K508 -> 0 | L92: =L508 -> 0 | M92: =M508 -> 0 | N92: =N508 -> 0 | O92: =O508 -> 0 | ... AK92: =AK508 -> 0
B93: 55 | C93: Accumulated Depreciation | D93: INR Cr | H93: =SUM($H92:H92) -> 0 | I93: =SUM($H92:I92) -> 0 | J93: =SUM($H92:J92) -> 0 | K93: =SUM($H92:K92) -> 0 | L93: =SUM($H92:L92) -> 0 | M93: =SUM($H92:M92) -> 0 | N93: =SUM($H92:N92) -> 0 | O93: =SUM($H92:O92) -> 0 | ... AK93: =SUM($H92:AK92) -> 0
B94: 56 | C94: Net Fixed Assets | D94: INR Cr | H94: =H90+H91-H92 -> 0 | I94: =I90+I91-I92 -> 0 | J94: =J90+J91-J92 -> 0 | K94: =K90+K91-K92 -> 0 | L94: =L90+L91-L92 -> 0 | M94: =M90+M91-M92 -> 0 | N94: =N90+N91-N92 -> 0 | O94: =O90+O91-O92 -> 0 | ... AK94: =AK90+AK91-AK92 -> 0
B95: 57 | C95: =C20 -> Mine Dewatering System | F95: 0.0667
B96: 58 | C96: Opening Balance | D96: INR Cr | H96: =G100 -> 0 | I96: =H100 -> 0 | J96: =I100 -> 0 | K96: =J100 -> 0 | L96: =K100 -> 0 | M96: =L100 -> 0 | N96: =M100 -> 0 | O96: =N100 -> 0 | ... AK96: =AJ100 -> 0
B97: 59 | C97: Addition during year | D97: INR Cr | E97: =SUM(H97:AP97) -> 0 | H97: =H20+H30 -> 0 | I97: =I20+I30 -> 0 | J97: =J20+J30 -> 0 | K97: =K20+K30 -> 0 | L97: =L20+L30 -> 0 | M97: =M20+M30 -> 0 | N97: =N20+N30 -> 0 | O97: =O20+O30 -> 0 | ... AK97: =AK20+AK30 -> 0
B98: 60 | C98: Book Depreciation | D98: INR Cr | E98: =SUM(H98:AP98) -> 0 | H98: =H543 -> 0 | I98: =I543 -> 0 | J98: =J543 -> 0 | K98: =K543 -> 0 | L98: =L543 -> 0 | M98: =M543 -> 0 | N98: =N543 -> 0 | O98: =O543 -> 0 | ... AK98: =AK543 -> 0
B99: 61 | C99: Accumulated Depreciation | D99: INR Cr | H99: =SUM($H98:H98) -> 0 | I99: =SUM($H98:I98) -> 0 | J99: =SUM($H98:J98) -> 0 | K99: =SUM($H98:K98) -> 0 | L99: =SUM($H98:L98) -> 0 | M99: =SUM($H98:M98) -> 0 | N99: =SUM($H98:N98) -> 0 | O99: =SUM($H98:O98) -> 0 | ... AK99: =SUM($H98:AK98) -> 0
B100: 62 | C100: Net Fixed Assets | D100: INR Cr | H100: =H96+H97-H98 -> 0 | I100: =I96+I97-I98 -> 0 | J100: =J96+J97-J98 -> 0 | K100: =K96+K97-K98 -> 0 | L100: =L96+L97-L98 -> 0 | M100: =M96+M97-M98 -> 0 | N100: =N96+N97-N98 -> 0 | O100: =O96+O97-O98 -> 0 | ... AK100: =AK96+AK97-AK98 -> 0
B101: 63 | C101: =C21 -> Digitalisation | F101: 0.3333
B102: 64 | C102: Opening Balance | D102: INR Cr | H102: =G106 -> 0 | I102: =H106 -> 0 | J102: =I106 -> 0 | K102: =J106 -> 0 | L102: =K106 -> 0 | M102: =L106 -> 0 | N102: =M106 -> 0 | O102: =N106 -> 0 | ... AK102: =AJ106 -> 0
B103: 65 | C103: Addition during year | D103: INR Cr | E103: =SUM(H103:AP103) -> 0 | H103: =H21+H31 -> 0 | I103: =I21+I31 -> 0 | J103: =J21+J31 -> 0 | K103: =K21+K31 -> 0 | L103: =L21+L31 -> 0 | M103: =M21+M31 -> 0 | N103: =N21+N31 -> 0 | O103: =O21+O31 -> 0 | ... AK103: =AK21+AK31 -> 0
B104: 66 | C104: Book Depreciation | D104: INR Cr | E104: =SUM(H104:AP104) -> 0 | H104: =H578 -> 0 | I104: =I578 -> 0 | J104: =J578 -> 0 | K104: =K578 -> 0 | L104: =L578 -> 0 | M104: =M578 -> 0 | N104: =N578 -> 0 | O104: =O578 -> 0 | ... AK104: =AK578 -> 0
...

Sheet Project CAPEX
A1: Capital Costs
B3: Production Details | E3: ='Production Schedule'!E1 -> 46023 | F3: ='Production Schedule'!F1 -> 46389 | G3: ='Production Schedule'!G1 -> 46755 | H3: ='Production Schedule'!H1 -> 47121 | I3: ='Production Schedule'!I1 -> 47487 | J3: ='Production Schedule'!J1 -> 47853 | K3: ='Production Schedule'!K1 -> 48219 | L3: ='Production Schedule'!L1 -> 48585 | ... AA3: ='Production Schedule'!AA1 -> 54075 | AI3: ='Production Schedule'!AI1 -> 0 | AJ3: ='Production Schedule'!AJ1 -> 0 | AK3: ='Production Schedule'!AK1 -> 0 | AL3: ='Production Schedule'!AL1 -> 0 | AM3: ='Production Schedule'!AM1 -> 0 | AN3: ='Production Schedule'!AN1 -> 0 | AO3: ='Production Schedule'!AO1 -> 0
B4: List | C4: Unit | D4: Total | E4: ='Production Schedule'!E3 -> -4 | F4: ='Production Schedule'!F3 -> -3 | G4: ='Production Schedule'!G3 -> -2 | H4: ='Production Schedule'!H3 -> -1 | I4: ='Production Schedule'!I3 -> 1 | J4: ='Production Schedule'!J3 -> 2 | K4: ='Production Schedule'!K3 -> 3 | L4: ='Production Schedule'!L3 -> 4 | ... AA4: ='Production Schedule'!AA3 -> 19 | AI4: ='Production Schedule'!AI3 -> 0 | AJ4: ='Production Schedule'!AJ3 -> 0 | AK4: ='Production Schedule'!AK3 -> 0 | AL4: ='Production Schedule'!AL3 -> 0 | AM4: ='Production Schedule'!AM3 -> 0 | AN4: ='Production Schedule'!AN3 -> 0 | AO4: ='Production Schedule'!AO3 -> 0 | AP4: ='Production Schedule'!AP3 -> 0 | ... AR4: ='Production Schedule'!AR3 -> 0
B5: Coal Production | C5: Mt | D5: =+SUM(E5:AN5) -> 225.70441 | E5: ='Production Schedule'!E5 -> 0 | F5: ='Production Schedule'!F5 -> 0 | G5: ='Production Schedule'!G5 -> 0 | H5: ='Production Schedule'!H5 -> 0 | I5: ='Production Schedule'!I5 -> 1.9999998 | J5: ='Production Schedule'!J5 -> 3.9999987 | K5: ='Production Schedule'!K5 -> 8.0000007 | L5: ='Production Schedule'!L5 -> 11.999999 | ... AA5: ='Production Schedule'!AA5 -> 2.2043909 | AI5: ='Production Schedule'!AI5 -> 0 | AJ5: ='Production Schedule'!AJ5 -> 0 | AK5: ='Production Schedule'!AK5 -> 0 | AL5: ='Production Schedule'!AL5 -> 0 | AM5: ='Production Schedule'!AM5 -> 0 | AN5: ='Production Schedule'!AN5 -> 0 | AO5: ='Production Schedule'!AO5 -> 0 | AP5: ='Production Schedule'!AP5 -> 0 | ... AR5: ='Production Schedule'!AR5 -> 0
B6: Waste Removal | C6: Mbcm | D6: =+SUM(E6:AN6) -> 535.39467 | E6: ='Production Schedule'!E8 -> 0 | F6: ='Production Schedule'!F8 -> 0 | G6: ='Production Schedule'!G8 -> 0 | H6: ='Production Schedule'!H8 -> 0 | I6: ='Production Schedule'!I8 -> 11.466046 | J6: ='Production Schedule'!J8 -> 9.5178188 | K6: ='Production Schedule'!K8 -> 17.240515 | L6: ='Production Schedule'!L8 -> 36.817196 | ... AA6: ='Production Schedule'!AA8 -> 1.2764738 | AI6: ='Production Schedule'!AI8 -> 0 | AJ6: ='Production Schedule'!AJ8 -> 0 | AK6: ='Production Schedule'!AK8 -> 0 | AL6: ='Production Schedule'!AL8 -> 0 | AM6: ='Production Schedule'!AM8 -> 0 | AN6: ='Production Schedule'!AN8 -> 0 | AO6: ='Production Schedule'!AO8 -> 0 | AP6: ='Production Schedule'!AP8 -> 0 | ... AR6: ='Production Schedule'!AR8 -> 0
B7: Overall SR | C7: bcm:t | D7: =IFERROR(D6/D5,0) -> 2.3721055 | E7: =IFERROR(E6/E5,0) -> 0 | F7: =IFERROR(F6/F5,0) -> 0 | G7: =IFERROR(G6/G5,0) -> 0 | H7: =IFERROR(H6/H5,0) -> 0 | I7: =IFERROR(I6/I5,0) -> 5.7330236 | J7: =IFERROR(J6/J5,0) -> 2.3794555 | K7: =IFERROR(K6/K5,0) -> 2.1550642 | ... AA7: =IFERROR(AA6/AA5,0) -> 0.57905965 | AI7: =IFERROR(AI6/AI5,0) -> 0 | AJ7: =IFERROR(AJ6/AJ5,0) -> 0 | AK7: =IFERROR(AK6/AK5,0) -> 0 | AL7: =IFERROR(AL6/AL5,0) -> 0 | AM7: =IFERROR(AM6/AM5,0) -> 0 | AN7: =IFERROR(AN6/AN5,0) -> 0 | AO7: =IFERROR(AO6/AO5,0) -> 0 | AP7: =IFERROR(AP6/AP5,0) -> 0 | ... AR7: =IFERROR(AR6/AR5,0) -> 0
B9: Initial Capital Costs | E9: =E3 -> 46023 | F9: =F3 -> 46389 | G9: =G3 -> 46755 | H9: =H3 -> 47121 | I9: =I3 -> 47487 | J9: =J3 -> 47853 | K9: =K3 -> 48219 | L9: =L3 -> 48585 | ... AA9: =AA3 -> 54075 | AI9: =AI3 -> 0 | AJ9: =AJ3 -> 0 | AK9: =AK3 -> 0 | AL9: =AL3 -> 0 | AM9: =AM3 -> 0 | AN9: =AN3 -> 0 | AO9: =AO3 -> 0
B10: List | C10: Unit | D10: Total | E10: =E4 -> -4 | F10: =F4 -> -3 | G10: =G4 -> -2 | H10: =H4 -> -1 | I10: =I4 -> 1 | J10: =J4 -> 2 | K10: =K4 -> 3 | L10: =L4 -> 4 | ... AA10: =AA4 -> 19 | AI10: =AI4 -> 0 | AJ10: =AJ4 -> 0 | AK10: =AK4 -> 0 | AL10: =AL4 -> 0 | AM10: =AM4 -> 0 | AN10: =AN4 -> 0 | AO10: =AO4 -> 0 | AP10: =AP4 -> 0 | ... AR10: =AR4 -> 0
A11: 1 | B11: Pre-operative costs | C11: INR Cr | D11: =+SUM(E11:AR11) -> 214.12704 | E11: ='Owner CAPEX'!E11 -> 114.11026 | F11: ='Owner CAPEX'!F11 -> 32.27026 | G11: ='Owner CAPEX'!G11 -> 33.45826 | H11: ='Owner CAPEX'!H11 -> 34.28826 | I11: ='Owner CAPEX'!I11 -> 0 | J11: ='Owner CAPEX'!J11 -> 0 | K11: ='Owner CAPEX'!K11 -> 0 | L11: ='Owner CAPEX'!L11 -> 0 | ... AA11: ='Owner CAPEX'!AA11 -> 0 | AI11: ='Owner CAPEX'!AI11 -> 0 | AJ11: ='Owner CAPEX'!AJ11 -> 0 | AK11: ='Owner CAPEX'!AK11 -> 0 | AL11: ='Owner CAPEX'!AL11 -> 0 | AM11: ='Owner CAPEX'!AM11 -> 0 | AN11: ='Owner CAPEX'!AN11 -> 0 | AO11: ='Owner CAPEX'!AO11 -> 0 | AP11: ='Owner CAPEX'!AP11 -> 0 | ... AR11: ='Owner CAPEX'!AR11 -> 0
A12: =A11+1 -> 2 | B12: Upfront Amount | C12: INR Cr | D12: =+SUM(E12:AR12) -> 99.07 | E12: ='Owner CAPEX'!E12 -> 24.7675 | F12: ='Owner CAPEX'!F12 -> 0 | G12: ='Owner CAPEX'!G12 -> 0 | H12: ='Owner CAPEX'!H12 -> 24.7675 | I12: ='Owner CAPEX'!I12 -> 49.535 | J12: ='Owner CAPEX'!J12 -> 0 | K12: ='Owner CAPEX'!K12 -> 0 | L12: ='Owner CAPEX'!L12 -> 0 | ... AA12: ='Owner CAPEX'!AA12 -> 0 | AI12: ='Owner CAPEX'!AI12 -> 0 | AJ12: ='Owner CAPEX'!AJ12 -> 0 | AK12: ='Owner CAPEX'!AK12 -> 0 | AL12: ='Owner CAPEX'!AL12 -> 0 | AM12: ='Owner CAPEX'!AM12 -> 0 | AN12: ='Owner CAPEX'!AN12 -> 0 | AO12: ='Owner CAPEX'!AO12 -> 0 | AP12: ='Owner CAPEX'!AP12 -> 0 | ... AR12: ='Owner CAPEX'!AR12 -> 0
A13: =A12+1 -> 3 | B13: Land Cost | C13: INR Cr | D13: =+SUM(E13:AR13) -> 985.07802 | E13: ='Owner CAPEX'!E13 -> 0 | F13: ='Owner CAPEX'!F13 -> 147.76226 | G13: ='Owner CAPEX'!G13 -> 98.508174 | H13: ='Owner CAPEX'!H13 -> 98.508174 | I13: ='Owner CAPEX'!I13 -> 95.8787 | J13: ='Owner CAPEX'!J13 -> 58.261429 | K13: ='Owner CAPEX'!K13 -> 73.814176 | L13: ='Owner CAPEX'!L13 -> 134.22055 | ... AA13: ='Owner CAPEX'!AA13 -> 0 | AI13: ='Owner CAPEX'!AI13 -> 0 | AJ13: ='Owner CAPEX'!AJ13 -> 0 | AK13: ='Owner CAPEX'!AK13 -> 0 | AL13: ='Owner CAPEX'!AL13 -> 0 | AM13: ='Owner CAPEX'!AM13 -> 0 | AN13: ='Owner CAPEX'!AN13 -> 0 | AO13: ='Owner CAPEX'!AO13 -> 0 | AP13: ='Owner CAPEX'!AP13 -> 0 | ... AR13: ='Owner CAPEX'!AR13 -> 0
A14: =A13+1 -> 4 | B14: R&R Cost | C14: INR Cr | D14: =+SUM(E14:AR14) -> 1048.57 | E14: ='Owner CAPEX'!E14 -> 0 | F14: ='Owner CAPEX'!F14 -> 0 | G14: ='Owner CAPEX'!G14 -> 0 | H14: ='Owner CAPEX'!H14 -> 0 | I14: ='Owner CAPEX'!I14 -> 0 | J14: ='Owner CAPEX'!J14 -> 0 | K14: ='Owner CAPEX'!K14 -> 0 | L14: ='Owner CAPEX'!L14 -> 104.857 | ... AA14: ='Owner CAPEX'!AA14 -> 0 | AI14: ='Owner CAPEX'!AI14 -> 0 | AJ14: ='Owner CAPEX'!AJ14 -> 0 | AK14: ='Owner CAPEX'!AK14 -> 0 | AL14: ='Owner CAPEX'!AL14 -> 0 | AM14: ='Owner CAPEX'!AM14 -> 0 | AN14: ='Owner CAPEX'!AN14 -> 0 | AO14: ='Owner CAPEX'!AO14 -> 0 | AP14: ='Owner CAPEX'!AP14 -> 0 | ... AR14: ='Owner CAPEX'!AR14 -> 0
A15: =A14+1 -> 5 | B15: HEMM Equipment | C15: INR Cr | D15: =+SUM(E15:AR15) -> 701.51584 | E15: ='Owner CAPEX'!E15+'MDO CAPEX'!E11 -> 0 | F15: ='Owner CAPEX'!F15+'MDO CAPEX'!F11 -> 0 | G15: ='Owner CAPEX'!G15+'MDO CAPEX'!G11 -> 0 | H15: ='Owner CAPEX'!H15+'MDO CAPEX'!H11 -> 0 | I15: ='Owner CAPEX'!I15+'MDO CAPEX'!I11 -> 134.12608 | J15: ='Owner CAPEX'!J15+'MDO CAPEX'!J11 -> 14.8766 | K15: ='Owner CAPEX'!K15+'MDO CAPEX'!K11 -> 108.86268 | L15: ='Owner CAPEX'!L15+'MDO CAPEX'!L11 -> 272.02313 | ... AA15: ='Owner CAPEX'!AA15+'MDO CAPEX'!AA11 -> 0 | AI15: ='Owner CAPEX'!AI15+'MDO CAPEX'!AI11 -> 0 | AJ15: ='Owner CAPEX'!AJ15+'MDO CAPEX'!AJ11 -> 0 | AK15: ='Owner CAPEX'!AK15+'MDO CAPEX'!AK11 -> 0 | AL15: ='Owner CAPEX'!AL15+'MDO CAPEX'!AL11 -> 0 | AM15: ='Owner CAPEX'!AM15+'MDO CAPEX'!AM11 -> 0 | AN15: ='Owner CAPEX'!AN15+'MDO CAPEX'!AN11 -> 0 | AO15: ='Owner CAPEX'!AO15+'MDO CAPEX'!AO11 -> 0 | AP15: ='Owner CAPEX'!AP15+'MDO CAPEX'!AP11 -> 0 | ... AR15: ='Owner CAPEX'!AR15+'MDO CAPEX'!AR11 -> 0
A16: =A15+1 -> 6 | B16: CHP | C16: INR Cr | D16: =+SUM(E16:AR16) -> 335.19 | E16: ='Owner CAPEX'!E16 -> 0 | F16: ='Owner CAPEX'!F16 -> 0 | G16: ='Owner CAPEX'!G16 -> 11.99 | H16: ='Owner CAPEX'!H16 -> 89.7925 | I16: ='Owner CAPEX'!I16 -> 155.605 | J16: ='Owner CAPEX'!J16 -> 77.8025 | K16: ='Owner CAPEX'!K16 -> 0 | L16: ='Owner CAPEX'!L16 -> 0 | ... AA16: ='Owner CAPEX'!AA16 -> 0 | AI16: ='Owner CAPEX'!AI16 -> 0 | AJ16: ='Owner CAPEX'!AJ16 -> 0 | AK16: ='Owner CAPEX'!AK16 -> 0 | AL16: ='Owner CAPEX'!AL16 -> 0 | AM16: ='Owner CAPEX'!AM16 -> 0 | AN16: ='Owner CAPEX'!AN16 -> 0 | AO16: ='Owner CAPEX'!AO16 -> 0 | AP16: ='Owner CAPEX'!AP16 -> 0 | ... AR16: ='Owner CAPEX'!AR16 -> 0
A17: =A16+1 -> 7 | B17: Railway Siding | C17: INR Cr | D17: =+SUM(E17:AR17) -> 540 | E17: ='Owner CAPEX'!E17 -> 0 | F17: ='Owner CAPEX'!F17 -> 54 | G17: ='Owner CAPEX'!G17 -> 324 | H17: ='Owner CAPEX'!H17 -> 162 | I17: ='Owner CAPEX'!I17 -> 0 | J17: ='Owner CAPEX'!J17 -> 0 | K17: ='Owner CAPEX'!K17 -> 0 | L17: ='Owner CAPEX'!L17 -> 0 | ... AA17: ='Owner CAPEX'!AA17 -> 0 | AI17: ='Owner CAPEX'!AI17 -> 0 | AJ17: ='Owner CAPEX'!AJ17 -> 0 | AK17: ='Owner CAPEX'!AK17 -> 0 | AL17: ='Owner CAPEX'!AL17 -> 0 | AM17: ='Owner CAPEX'!AM17 -> 0 | AN17: ='Owner CAPEX'!AN17 -> 0 | AO17: ='Owner CAPEX'!AO17 -> 0 | AP17: ='Owner CAPEX'!AP17 -> 0 | ... AR17: ='Owner CAPEX'!AR17 -> 0
A18: =A17+1 -> 8 | B18: Civil Infrastructure | C18: INR Cr | D18: =+SUM(E18:AR18) -> 191 | E18: ='Owner CAPEX'!E18+'MDO CAPEX'!E12 -> 0 | F18: ='Owner CAPEX'!F18+'MDO CAPEX'!F12 -> 57.3 | G18: ='Owner CAPEX'!G18+'MDO CAPEX'!G12 -> 95.5 | H18: ='Owner CAPEX'!H18+'MDO CAPEX'!H12 -> 38.2 | I18: ='Owner CAPEX'!I18+'MDO CAPEX'!I12 -> 0 | J18: ='Owner CAPEX'!J18+'MDO CAPEX'!J12 -> 0 | K18: ='Owner CAPEX'!K18+'MDO CAPEX'!K12 -> 0 | L18: ='Owner CAPEX'!L18+'MDO CAPEX'!L12 -> 0 | ... AA18: ='Owner CAPEX'!AA18+'MDO CAPEX'!AA12 -> 0 | AI18: ='Owner CAPEX'!AI18+'MDO CAPEX'!AI12 -> 0 | AJ18: ='Owner CAPEX'!AJ18+'MDO CAPEX'!AJ12 -> 0 | AK18: ='Owner CAPEX'!AK18+'MDO CAPEX'!AK12 -> 0 | AL18: ='Owner CAPEX'!AL18+'MDO CAPEX'!AL12 -> 0 | AM18: ='Owner CAPEX'!AM18+'MDO CAPEX'!AM12 -> 0 | AN18: ='Owner CAPEX'!AN18+'MDO CAPEX'!AN12 -> 0 | AO18: ='Owner CAPEX'!AO18+'MDO CAPEX'!AO12 -> 0 | AP18: ='Owner CAPEX'!AP18+'MDO CAPEX'!AP12 -> 0 | ... AR18: ='Owner CAPEX'!AR18+'MDO CAPEX'!AR12 -> 0
A19: =A18+1 -> 9 | B19: Fire Fighting & Dust Suppression | C19: INR Cr | D19: =+SUM(E19:AR19) -> 14.45 | E19: ='Owner CAPEX'!E19+'MDO CAPEX'!E13 -> 0 | F19: ='Owner CAPEX'!F19+'MDO CAPEX'!F13 -> 4.335 | G19: ='Owner CAPEX'!G19+'MDO CAPEX'!G13 -> 7.225 | H19: ='Owner CAPEX'!H19+'MDO CAPEX'!H13 -> 2.89 | I19: ='Owner CAPEX'!I19+'MDO CAPEX'!I13 -> 0 | J19: ='Owner CAPEX'!J19+'MDO CAPEX'!J13 -> 0 | K19: ='Owner CAPEX'!K19+'MDO CAPEX'!K13 -> 0 | L19: ='Owner CAPEX'!L19+'MDO CAPEX'!L13 -> 0 | ... AA19: ='Owner CAPEX'!AA19+'MDO CAPEX'!AA13 -> 0 | AI19: ='Owner CAPEX'!AI19+'MDO CAPEX'!AI13 -> 0 | AJ19: ='Owner CAPEX'!AJ19+'MDO CAPEX'!AJ13 -> 0 | AK19: ='Owner CAPEX'!AK19+'MDO CAPEX'!AK13 -> 0 | AL19: ='Owner CAPEX'!AL19+'MDO CAPEX'!AL13 -> 0 | AM19: ='Owner CAPEX'!AM19+'MDO CAPEX'!AM13 -> 0 | AN19: ='Owner CAPEX'!AN19+'MDO CAPEX'!AN13 -> 0 | AO19: ='Owner CAPEX'!AO19+'MDO CAPEX'!AO13 -> 0 | AP19: ='Owner CAPEX'!AP19+'MDO CAPEX'!AP13 -> 0 | ... AR19: ='Owner CAPEX'!AR19+'MDO CAPEX'!AR13 -> 0
A20: =A19+1 -> 10 | B20: Workshop and Store | C20: INR Cr | D20: =+SUM(E20:AR20) -> 27.27 | E20: ='Owner CAPEX'!E20+'MDO CAPEX'!E14 -> 0 | F20: ='Owner CAPEX'!F20+'MDO CAPEX'!F14 -> 0 | G20: ='Owner CAPEX'!G20+'MDO CAPEX'!G14 -> 13.635 | H20: ='Owner CAPEX'!H20+'MDO CAPEX'!H14 -> 13.635 | I20: ='Owner CAPEX'!I20+'MDO CAPEX'!I14 -> 0 | J20: ='Owner CAPEX'!J20+'MDO CAPEX'!J14 -> 0 | K20: ='Owner CAPEX'!K20+'MDO CAPEX'!K14 -> 0 | L20: ='Owner CAPEX'!L20+'MDO CAPEX'!L14 -> 0 | ... AA20: ='Owner CAPEX'!AA20+'MDO CAPEX'!AA14 -> 0 | AI20: ='Owner CAPEX'!AI20+'MDO CAPEX'!AI14 -> 0 | AJ20: ='Owner CAPEX'!AJ20+'MDO CAPEX'!AJ14 -> 0 | AK20: ='Owner CAPEX'!AK20+'MDO CAPEX'!AK14 -> 0 | AL20: ='Owner CAPEX'!AL20+'MDO CAPEX'!AL14 -> 0 | AM20: ='Owner CAPEX'!AM20+'MDO CAPEX'!AM14 -> 0 | AN20: ='Owner CAPEX'!AN20+'MDO CAPEX'!AN14 -> 0 | AO20: ='Owner CAPEX'!AO20+'MDO CAPEX'!AO14 -> 0 | AP20: ='Owner CAPEX'!AP20+'MDO CAPEX'!AP14 -> 0 | ... AR20: ='Owner CAPEX'!AR20+'MDO CAPEX'!AR14 -> 0
A21: =A20+1 -> 11 | B21: Electrical | C21: INR Cr | D21: =+SUM(E21:AR21) -> 34.35 | E21: ='Owner CAPEX'!E21 -> 0 | F21: ='Owner CAPEX'!F21 -> 0 | G21: ='Owner CAPEX'!G21 -> 0 | H21: ='Owner CAPEX'!H21 -> 8.5875 | I21: ='Owner CAPEX'!I21 -> 13.74 | J21: ='Owner CAPEX'!J21 -> 8.5875 | K21: ='Owner CAPEX'!K21 -> 3.435 | L21: ='Owner CAPEX'!L21 -> 0 | ... AA21: ='Owner CAPEX'!AA21 -> 0 | AI21: ='Owner CAPEX'!AI21 -> 0 | AJ21: ='Owner CAPEX'!AJ21 -> 0 | AK21: ='Owner CAPEX'!AK21 -> 0 | AL21: ='Owner CAPEX'!AL21 -> 0 | AM21: ='Owner CAPEX'!AM21 -> 0 | AN21: ='Owner CAPEX'!AN21 -> 0 | AO21: ='Owner CAPEX'!AO21 -> 0 | AP21: ='Owner CAPEX'!AP21 -> 0 | ... AR21: ='Owner CAPEX'!AR21 -> 0
A22: =A21+1 -> 12 | B22: Mine Dewatering System | C22: INR Cr | D22: =+SUM(E22:AR22) -> 15 | E22: ='Owner CAPEX'!E22+'MDO CAPEX'!E16 -> 0 | F22: ='Owner CAPEX'!F22+'MDO CAPEX'!F16 -> 0 | G22: ='Owner CAPEX'!G22+'MDO CAPEX'!G16 -> 0 | H22: ='Owner CAPEX'!H22+'MDO CAPEX'!H16 -> 0 | I22: ='Owner CAPEX'!I22+'MDO CAPEX'!I16 -> 2.8256089 | J22: ='Owner CAPEX'!J22+'MDO CAPEX'!J16 -> 2.0484988 | K22: ='Owner CAPEX'!K22+'MDO CAPEX'!K16 -> 0 | L22: ='Owner CAPEX'!L22+'MDO CAPEX'!L16 -> 0 | ... AA22: ='Owner CAPEX'!AA22+'MDO CAPEX'!AA16 -> 0 | AI22: ='Owner CAPEX'!AI22+'MDO CAPEX'!AI16 -> 0 | AJ22: ='Owner CAPEX'!AJ22+'MDO CAPEX'!AJ16 -> 0 | AK22: ='Owner CAPEX'!AK22+'MDO CAPEX'!AK16 -> 0 | AL22: ='Owner CAPEX'!AL22+'MDO CAPEX'!AL16 -> 0 | AM22: ='Owner CAPEX'!AM22+'MDO CAPEX'!AM16 -> 0 | AN22: ='Owner CAPEX'!AN22+'MDO CAPEX'!AN16 -> 0 | AO22: ='Owner CAPEX'!AO22+'MDO CAPEX'!AO16 -> 0 | AP22: ='Owner CAPEX'!AP22+'MDO CAPEX'!AP16 -> 0 | ... AR22: ='Owner CAPEX'!AR22+'MDO CAPEX'!AR16 -> 0
A23: =A22+1 -> 13 | B23: Digitalization | C23: INR Cr | D23: =+SUM(E23:AR23) -> 10 | E23: ='Owner CAPEX'!E23+'MDO CAPEX'!E17 -> 0 | F23: ='Owner CAPEX'!F23+'MDO CAPEX'!F17 -> 3 | G23: ='Owner CAPEX'!G23+'MDO CAPEX'!G17 -> 5 | H23: ='Owner CAPEX'!H23+'MDO CAPEX'!H17 -> 2 | I23: ='Owner CAPEX'!I23+'MDO CAPEX'!I17 -> 0 | J23: ='Owner CAPEX'!J23+'MDO CAPEX'!J17 -> 0 | K23: ='Owner CAPEX'!K23+'MDO CAPEX'!K17 -> 0 | L23: ='Owner CAPEX'!L23+'MDO CAPEX'!L17 -> 0 | ... AA23: ='Owner CAPEX'!AA23+'MDO CAPEX'!AA17 -> 0 | AI23: ='Owner CAPEX'!AI23+'MDO CAPEX'!AI17 -> 0 | AJ23: ='Owner CAPEX'!AJ23+'MDO CAPEX'!AJ17 -> 0 | AK23: ='Owner CAPEX'!AK23+'MDO CAPEX'!AK17 -> 0 | AL23: ='Owner CAPEX'!AL23+'MDO CAPEX'!AL17 -> 0 | AM23: ='Owner CAPEX'!AM23+'MDO CAPEX'!AM17 -> 0 | AN23: ='Owner CAPEX'!AN23+'MDO CAPEX'!AN17 -> 0 | AO23: ='Owner CAPEX'!AO23+'MDO CAPEX'!AO17 -> 0 | AP23: ='Owner CAPEX'!AP23+'MDO CAPEX'!AP17 -> 0 | ... AR23: ='Owner CAPEX'!AR23+'MDO CAPEX'!AR17 -> 0
A24: =A23+1 -> 14 | B24: Contingency | C24: INR Cr | D24: =+SUM(E24:AR24) -> 617.48264 | E24: ='Owner CAPEX'!E24+'MDO CAPEX'!E18 -> 17.116539 | F24: ='Owner CAPEX'!F24+'MDO CAPEX'!F18 -> 44.800128 | G24: ='Owner CAPEX'!G24+'MDO CAPEX'!G18 -> 88.397465 | H24: ='Owner CAPEX'!H24+'MDO CAPEX'!H18 -> 67.485215 | I24: ='Owner CAPEX'!I24+'MDO CAPEX'!I18 -> 60.326308 | J24: ='Owner CAPEX'!J24+'MDO CAPEX'!J18 -> 24.236479 | K24: ='Owner CAPEX'!K24+'MDO CAPEX'!K18 -> 27.916778 | L24: ='Owner CAPEX'!L24+'MDO CAPEX'!L18 -> 76.665102 | ... AA24: ='Owner CAPEX'!AA24+'MDO CAPEX'!AA18 -> 0 | AI24: ='Owner CAPEX'!AI24+'MDO CAPEX'!AI18 -> 0 | AJ24: ='Owner CAPEX'!AJ24+'MDO CAPEX'!AJ18 -> 0 | AK24: ='Owner CAPEX'!AK24+'MDO CAPEX'!AK18 -> 0 | AL24: ='Owner CAPEX'!AL24+'MDO CAPEX'!AL18 -> 0 | AM24: ='Owner CAPEX'!AM24+'MDO CAPEX'!AM18 -> 0 | AN24: ='Owner CAPEX'!AN24+'MDO CAPEX'!AN18 -> 0 | AO24: ='Owner CAPEX'!AO24+'MDO CAPEX'!AO18 -> 0 | AP24: ='Owner CAPEX'!AP24+'MDO CAPEX'!AP18 -> 0 | ... AR24: ='Owner CAPEX'!AR24+'MDO CAPEX'!AR18 -> 0
A25: =A24+1 -> 15 | B25: IDC | C25: INR Cr | D25: =+SUM(E25:AR25) -> 0 | E25: ='Owner CAPEX'!E25+'MDO CAPEX'!E19 -> 0 | F25: ='Owner CAPEX'!F25+'MDO CAPEX'!F19 -> 0 | G25: ='Owner CAPEX'!G25+'MDO CAPEX'!G19 -> 0 | H25: ='Owner CAPEX'!H25+'MDO CAPEX'!H19 -> 0 | I25: ='Owner CAPEX'!I25+'MDO CAPEX'!I19 -> 0 | J25: ='Owner CAPEX'!J25+'MDO CAPEX'!J19 -> 0 | K25: ='Owner CAPEX'!K25+'MDO CAPEX'!K19 -> 0 | L25: ='Owner CAPEX'!L25+'MDO CAPEX'!L19 -> 0 | ... AA25: ='Owner CAPEX'!AA25+'MDO CAPEX'!AA19 -> 0 | AI25: ='Owner CAPEX'!AI25+'MDO CAPEX'!AI19 -> 0 | AJ25: ='Owner CAPEX'!AJ25+'MDO CAPEX'!AJ19 -> 0 | AK25: ='Owner CAPEX'!AK25+'MDO CAPEX'!AK19 -> 0 | AL25: ='Owner CAPEX'!AL25+'MDO CAPEX'!AL19 -> 0 | AM25: ='Owner CAPEX'!AM25+'MDO CAPEX'!AM19 -> 0 | AN25: ='Owner CAPEX'!AN25+'MDO CAPEX'!AN19 -> 0 | AO25: ='Owner CAPEX'!AO25+'MDO CAPEX'!AO19 -> 0 | AP25: ='Owner CAPEX'!AP25+'MDO CAPEX'!AP19 -> 0 | ... AR25: ='Owner CAPEX'!AR25+'MDO CAPEX'!AR19 -> 0
B26: Total Initial Capital Expenditure | C26: INR Cr | D26: =SUM(D11:D25) -> 4833.1036 | E26: =SUM(E11:E25) -> 155.9943 | F26: =SUM(F11:F25) -> 343.46765 | G26: =SUM(G11:G25) -> 677.7139 | H26: =SUM(H11:H25) -> 542.15415 | I26: =SUM(I11:I25) -> 512.0367 | J26: =SUM(J11:J25) -> 185.81301 | K26: =SUM(K11:K25) -> 214.02863 | ... AA26: =SUM(AA11:AA25) -> 0 | AI26: =SUM(AI11:AI25) -> 0 | AJ26: =SUM(AJ11:AJ25) -> 0 | AK26: =SUM(AK11:AK25) -> 0 | AL26: =SUM(AL11:AL25) -> 0 | AM26: =SUM(AM11:AM25) -> 0 | AN26: =SUM(AN11:AN25) -> 0 | AO26: =SUM(AO11:AO25) -> 0 | AP26: =SUM(AP11:AP25) -> 0 | ... AR26: =SUM(AR11:AR25) -> 0
B29: Sustaining Capital Costs | E29: =E9 -> 46023 | F29: =F9 -> 46389 | G29: =G9 -> 46755 | H29: =H9 -> 47121 | I29: =I9 -> 47487 | J29: =J9 -> 47853 | K29: =K9 -> 48219 | L29: =L9 -> 48585 | ... AA29: =AA9 -> 54075 | AI29: =AI9 -> 0 | AJ29: =AJ9 -> 0 | AK29: =AK9 -> 0 | AL29: =AL9 -> 0 | AM29: =AM9 -> 0 | AN29: =AN9 -> 0 | AO29: =AO9 -> 0
B30: List | C30: Unit | D30: Total | E30: =E10 -> -4 | F30: =F10 -> -3 | G30: =G10 -> -2 | H30: =H10 -> -1 | I30: =I10 -> 1 | J30: =J10 -> 2 | K30: =K10 -> 3 | L30: =L10 -> 4 | ... AA30: =AA10 -> 19 | AI30: =AI10 -> 0 | AJ30: =AJ10 -> 0 | AK30: =AK10 -> 0 | AL30: =AL10 -> 0 | AM30: =AM10 -> 0 | AN30: =AN10 -> 0 | AO30: =AO10 -> 0 | AP30: =AP10 -> 0 | ... AR30: =AR10 -> 0
A31: =A11 -> 1 | B31: Mining Equipment Replacement | C31: INR Cr | D31: =+SUM(E31:AR31) -> 1365.0488 | E31: ='Owner CAPEX'!E31+'MDO CAPEX'!E25 -> 0 | F31: ='Owner CAPEX'!F31+'MDO CAPEX'!F25 -> 0 | G31: ='Owner CAPEX'!G31+'MDO CAPEX'!G25 -> 0 | H31: ='Owner CAPEX'!H31+'MDO CAPEX'!H25 -> 0 | I31: ='Owner CAPEX'!I31+'MDO CAPEX'!I25 -> 0 | J31: ='Owner CAPEX'!J31+'MDO CAPEX'!J25 -> 0 | K31: ='Owner CAPEX'!K31+'MDO CAPEX'!K25 -> 0 | L31: ='Owner CAPEX'!L31+'MDO CAPEX'!L25 -> 0 | ... AA31: ='Owner CAPEX'!AA31+'MDO CAPEX'!AA25 -> 157.0256 | AI31: ='Owner CAPEX'!AI31+'MDO CAPEX'!AI25 -> 0 | AJ31: ='Owner CAPEX'!AJ31+'MDO CAPEX'!AJ25 -> 0 | AK31: ='Owner CAPEX'!AK31+'MDO CAPEX'!AK25 -> 0 | AL31: ='Owner CAPEX'!AL31+'MDO CAPEX'!AL25 -> 0 | AM31: ='Owner CAPEX'!AM31+'MDO CAPEX'!AM25 -> 0 | AN31: ='Owner CAPEX'!AN31+'MDO CAPEX'!AN25 -> 0 | AO31: ='Owner CAPEX'!AO31+'MDO CAPEX'!AO25 -> 0 | AP31: ='Owner CAPEX'!AP31+'MDO CAPEX'!AP25 -> 0 | ... AR31: ='Owner CAPEX'!AR31+'MDO CAPEX'!AR25 -> 0
A32: =A12 -> 2 | B32: =B16 -> CHP | C32: INR Cr | D32: =+SUM(E32:AR32) -> 20.1114 | E32: ='Owner CAPEX'!E32 -> 0 | F32: ='Owner CAPEX'!F32 -> 0 | G32: ='Owner CAPEX'!G32 -> 0 | H32: ='Owner CAPEX'!H32 -> 0 | I32: ='Owner CAPEX'!I32 -> 0 | J32: ='Owner CAPEX'!J32 -> 0 | K32: ='Owner CAPEX'!K32 -> 0 | L32: ='Owner CAPEX'!L32 -> 0 | ... AA32: ='Owner CAPEX'!AA32 -> 0 | AI32: ='Owner CAPEX'!AI32 -> 0 | AJ32: ='Owner CAPEX'!AJ32 -> 0 | AK32: ='Owner CAPEX'!AK32 -> 0 | AL32: ='Owner CAPEX'!AL32 -> 0 | AM32: ='Owner CAPEX'!AM32 -> 0 | AN32: ='Owner CAPEX'!AN32 -> 0 | AO32: ='Owner CAPEX'!AO32 -> 0 | AP32: ='Owner CAPEX'!AP32 -> 0 | ... AR32: ='Owner CAPEX'!AR32 -> 0
A33: =A13 -> 3 | B33: =B18 -> Civil Infrastructure | C33: INR Cr | D33: =+SUM(E33:AR33) -> 6.685 | E33: ='Owner CAPEX'!E33+'MDO CAPEX'!E26 -> 0 | F33: ='Owner CAPEX'!F33+'MDO CAPEX'!F26 -> 0 | G33: ='Owner CAPEX'!G33+'MDO CAPEX'!G26 -> 0 | H33: ='Owner CAPEX'!H33+'MDO CAPEX'!H26 -> 0 | I33: ='Owner CAPEX'!I33+'MDO CAPEX'!I26 -> 0 | J33: ='Owner CAPEX'!J33+'MDO CAPEX'!J26 -> 0 | K33: ='Owner CAPEX'!K33+'MDO CAPEX'!K26 -> 0 | L33: ='Owner CAPEX'!L33+'MDO CAPEX'!L26 -> 0 | ... AA33: ='Owner CAPEX'!AA33+'MDO CAPEX'!AA26 -> 0 | AI33: ='Owner CAPEX'!AI33+'MDO CAPEX'!AI26 -> 0 | AJ33: ='Owner CAPEX'!AJ33+'MDO CAPEX'!AJ26 -> 0 | AK33: ='Owner CAPEX'!AK33+'MDO CAPEX'!AK26 -> 0 | AL33: ='Owner CAPEX'!AL33+'MDO CAPEX'!AL26 -> 0 | AM33: ='Owner CAPEX'!AM33+'MDO CAPEX'!AM26 -> 0 | AN33: ='Owner CAPEX'!AN33+'MDO CAPEX'!AN26 -> 0 | AO33: ='Owner CAPEX'!AO33+'MDO CAPEX'!AO26 -> 0 | AP33: ='Owner CAPEX'!AP33+'MDO CAPEX'!AP26 -> 0 | ... AR33: ='Owner CAPEX'!AR33+'MDO CAPEX'!AR26 -> 0
A34: =A14 -> 4 | B34: =B20 -> Workshop and Store | C34: INR Cr | D34: =+SUM(E34:AR34) -> 0
A35: =A15 -> 5 | B35: =B21 -> Electrical | C35: INR Cr | D35: =+SUM(E35:AR35) -> 0
A36: =A16 -> 6 | B36: =B22 -> Mine Dewatering System | C36: INR Cr | D36: =+SUM(E36:AR36) -> 0
A37: =A17 -> 7 | B37: =B23 -> Digitalization | C37: INR Cr | D37: =+SUM(E37:AR37) -> 0
A38: =A18 -> 8 | B38: Contingency | C38: INR Cr | D38: =+SUM(E38:AR38) -> 208.77677 | E38: ='Owner CAPEX'!E38+'MDO CAPEX'!E31 -> 0 | F38: ='Owner CAPEX'!F38+'MDO CAPEX'!F31 -> 0 | G38: ='Owner CAPEX'!G38+'MDO CAPEX'!G31 -> 0 | H38: ='Owner CAPEX'!H38+'MDO CAPEX'!H31 -> 0 | I38: ='Owner CAPEX'!I38+'MDO CAPEX'!I31 -> 0 | J38: ='Owner CAPEX'!J38+'MDO CAPEX'!J31 -> 0 | K38: ='Owner CAPEX'!K38+'MDO CAPEX'!K31 -> 0 | L38: ='Owner CAPEX'!L38+'MDO CAPEX'!L31 -> 0 | ... AA38: ='Owner CAPEX'!AA38+'MDO CAPEX'!AA31 -> 23.55384 | AI38: ='Owner CAPEX'!AI38+'MDO CAPEX'!AI31 -> 0 | AJ38: ='Owner CAPEX'!AJ38+'MDO CAPEX'!AJ31 -> 0 | AK38: ='Owner CAPEX'!AK38+'MDO CAPEX'!AK31 -> 0 | AL38: ='Owner CAPEX'!AL38+'MDO CAPEX'!AL31 -> 0 | AM38: ='Owner CAPEX'!AM38+'MDO CAPEX'!AM31 -> 0 | AN38: ='Owner CAPEX'!AN38+'MDO CAPEX'!AN31 -> 0 | AO38: ='Owner CAPEX'!AO38+'MDO CAPEX'!AO31 -> 0 | AP38: ='Owner CAPEX'!AP38+'MDO CAPEX'!AP31 -> 0 | ... AR38: ='Owner CAPEX'!AR38+'MDO CAPEX'!AR31 -> 0
B39: Total Sustaining Capital Expenditure | C39: INR Cr | D39: =+SUM(E39:AN39) -> 1600.6219 | E39: =SUM(E31:E38) -> 0 | F39: =SUM(F31:F38) -> 0 | G39: =SUM(G31:G38) -> 0 | H39: =SUM(H31:H38) -> 0 | I39: =SUM(I31:I38) -> 0 | J39: =SUM(J31:J38) -> 0 | K39: =SUM(K31:K38) -> 0 | L39: =SUM(L31:L38) -> 0 | ... AA39: =SUM(AA31:AA38) -> 180.57944 | AI39: =SUM(AI31:AI38) -> 0 | AJ39: =SUM(AJ31:AJ38) -> 0 | AK39: =SUM(AK31:AK38) -> 0 | AL39: =SUM(AL31:AL38) -> 0 | AM39: =SUM(AM31:AM38) -> 0 | AN39: =SUM(AN31:AN38) -> 0 | AO39: =SUM(AO31:AO38) -> 0 | AP39: =SUM(AP31:AP38) -> 0 | ... AR39: =SUM(AR31:AR38) -> 0
B41: Total Capital Expenditure | C41: INR Cr | D41: =+SUM(E41:AN41) -> 6433.7255 | E41: =SUM(E26,E39) -> 155.9943 | F41: =SUM(F26,F39) -> 343.46765 | G41: =SUM(G26,G39) -> 677.7139 | H41: =SUM(H26,H39) -> 542.15415 | I41: =SUM(I26,I39) -> 512.0367 | J41: =SUM(J26,J39) -> 185.81301 | K41: =SUM(K26,K39) -> 214.02863 | L41: =SUM(L26,L39) -> 587.76578 | ... AA41: =SUM(AA26,AA39) -> 180.57944 | AI41: =SUM(AI26,AI39) -> 0 | AJ41: =SUM(AJ26,AJ39) -> 0 | AK41: =SUM(AK26,AK39) -> 0 | AL41: =SUM(AL26,AL39) -> 0 | AM41: =SUM(AM26,AM39) -> 0 | AN41: =SUM(AN26,AN39) -> 0 | AO41: =SUM(AO26,AO39) -> 0 | AP41: =SUM(AP26,AP39) -> 0 | ... AR41: =SUM(AR26,AR39) -> 0
D43: ='Owner CAPEX'!D41+'MDO CAPEX'!D34=D41 -> TRUE

Sheet Owner CAPEX
A1: Capital Costs
B3: Production Details | E3: ='Production Schedule'!E1 -> 46023 | F3: ='Production Schedule'!F1 -> 46389 | G3: ='Production Schedule'!G1 -> 46755 | H3: ='Production Schedule'!H1 -> 47121 | I3: ='Production Schedule'!I1 -> 47487 | J3: ='Production Schedule'!J1 -> 47853 | K3: ='Production Schedule'!K1 -> 48219 | L3: ='Production Schedule'!L1 -> 48585 | ... AA3: ='Production Schedule'!AA1 -> 54075
B4: List | C4: Unit | D4: Total | E4: ='Production Schedule'!E3 -> -4 | F4: ='Production Schedule'!F3 -> -3 | G4: ='Production Schedule'!G3 -> -2 | H4: ='Production Schedule'!H3 -> -1 | I4: ='Production Schedule'!I3 -> 1 | J4: ='Production Schedule'!J3 -> 2 | K4: ='Production Schedule'!K3 -> 3 | L4: ='Production Schedule'!L3 -> 4 | ... AA4: ='Production Schedule'!AA3 -> 19
B5: Coal Production | C5: Mt | D5: =+SUM(E5:AN5) -> 225.70441 | E5: ='Production Schedule'!E5 -> 0 | F5: ='Production Schedule'!F5 -> 0 | G5: ='Production Schedule'!G5 -> 0 | H5: ='Production Schedule'!H5 -> 0 | I5: ='Production Schedule'!I5 -> 1.9999998 | J5: ='Production Schedule'!J5 -> 3.9999987 | K5: ='Production Schedule'!K5 -> 8.0000007 | L5: ='Production Schedule'!L5 -> 11.999999 | ... AA5: ='Production Schedule'!AA5 -> 2.2043909
B6: Waste Removal | C6: Mbcm | D6: =+SUM(E6:AN6) -> 535.39467 | E6: ='Production Schedule'!E8 -> 0 | F6: ='Production Schedule'!F8 -> 0 | G6: ='Production Schedule'!G8 -> 0 | H6: ='Production Schedule'!H8 -> 0 | I6: ='Production Schedule'!I8 -> 11.466046 | J6: ='Production Schedule'!J8 -> 9.5178188 | K6: ='Production Schedule'!K8 -> 17.240515 | L6: ='Production Schedule'!L8 -> 36.817196 | ... AA6: ='Production Schedule'!AA8 -> 1.2764738
B7: Overall SR | C7: bcm:t | D7: =IFERROR(D6/D5,0) -> 2.3721055 | E7: =IFERROR(E6/E5,0) -> 0 | F7: =IFERROR(F6/F5,0) -> 0 | G7: =IFERROR(G6/G5,0) -> 0 | H7: =IFERROR(H6/H5,0) -> 0 | I7: =IFERROR(I6/I5,0) -> 5.7330236 | J7: =IFERROR(J6/J5,0) -> 2.3794555 | K7: =IFERROR(K6/K5,0) -> 2.1550642 | ... AA7: =IFERROR(AA6/AA5,0) -> 0.57905965
A9: Sl No | B9: Initial Capital Costs | E9: =E3 -> 46023 | F9: =F3 -> 46389 | G9: =G3 -> 46755 | H9: =H3 -> 47121 | I9: =I3 -> 47487 | J9: =J3 -> 47853 | K9: =K3 -> 48219 | L9: =L3 -> 48585 | ... AA9: =AA3 -> 54075
B10: List | C10: Unit | D10: Total | E10: =E4 -> -4 | F10: =F4 -> -3 | G10: =G4 -> -2 | H10: =H4 -> -1 | I10: =I4 -> 1 | J10: =J4 -> 2 | K10: =K4 -> 3 | L10: =L4 -> 4 | ... AA10: =AA4 -> 19
A11: 1 | B11: Pre-operative costs | C11: INR Cr | D11: =+SUM(E11:AR11) -> 214.12704 | E11: ='Pre-Operative'!F40 -> 114.11026 | F11: ='Pre-Operative'!G40 -> 32.27026 | G11: ='Pre-Operative'!H40 -> 33.45826 | H11: ='Pre-Operative'!I40 -> 34.28826 | I11: ='Pre-Operative'!J40 -> 0 | J11: ='Pre-Operative'!K40 -> 0 | K11: ='Pre-Operative'!L40 -> 0 | L11: ='Pre-Operative'!M40 -> 0 | M11: ='Pre-Operative'!K40 -> 0 | N11: ='Pre-Operative'!L40 -> 0 | O11: ='Pre-Operative'!M40 -> 0 | P11: ='Pre-Operative'!N40 -> 0 | Q11: ='Pre-Operative'!O40 -> 0 | R11: ='Pre-Operative'!P40 -> 0 | S11: ='Pre-Operative'!Q40 -> 0 | T11: ='Pre-Operative'!R40 -> 0 | ... AA11: ='Pre-Operative'!Y40 -> 0
A12: =A11+1 -> 2 | B12: Upfront Amount | C12: INR Cr | D12: =+SUM(E12:AR12) -> 99.07 | E12: =Government!E13 -> 24.7675 | F12: =Government!F13 -> 0 | G12: =Government!G13 -> 0 | H12: =Government!H13 -> 24.7675 | I12: =Government!I13 -> 49.535 | J12: =Government!J13 -> 0 | K12: =Government!K13 -> 0 | L12: =Government!L13 -> 0 | ... AA12: =Government!AA13 -> 0
A13: =A12+1 -> 3 | B13: Land Cost | C13: INR Cr | D13: =+SUM(E13:AR13) -> 985.07802 | E13: =Land!D5 -> 0 | F13: =Land!E5 -> 147.76226 | G13: =Land!F5 -> 98.508174 | H13: =Land!G5 -> 98.508174 | I13: =Land!H5 -> 95.8787 | J13: =Land!I5 -> 58.261429 | K13: =Land!J5 -> 73.814176 | L13: =Land!K5 -> 134.22055 | ... AA13: =Land!Z5 -> 0
A14: =A13+1 -> 4 | B14: R&R Cost | C14: INR Cr | D14: =+SUM(E14:AR14) -> 1048.57 | E14: ='R&R'!D6 -> 0 | F14: ='R&R'!E6 -> 0 | G14: ='R&R'!F6 -> 0 | H14: ='R&R'!G6 -> 0 | I14: ='R&R'!H6 -> 0 | J14: ='R&R'!I6 -> 0 | K14: ='R&R'!J6 -> 0 | L14: ='R&R'!K6 -> 104.857 | ... AA14: ='R&R'!Z6 -> 0
A15: =A14+1 -> 5 | B15: HEMM Equipment | C15: INR Cr | D15: =+SUM(E15:AR15) -> 701.51584 | E15: =IF(Assumptions_Dashboard!$L$4=Assumptions_Dashboard!$M$5,(Fleet!G366),0) -> 0 | F15: =IF(Assumptions_Dashboard!$L$4=Assumptions_Dashboard!$M$5,(Fleet!H366),0) -> 0 | G15: =IF(Assumptions_Dashboard!$L$4=Assumptions_Dashboard!$M$5,(Fleet!I366),0) -> 0 | H15: =IF(Assumptions_Dashboard!$L$4=Assumptions_Dashboard!$M$5,(Fleet!J366),0) -> 0 | I15: =IF(Assumptions_Dashboard!$L$4=Assumptions_Dashboard!$M$5,(Fleet!K366),0) -> 134.12608 | J15: =IF(Assumptions_Dashboard!$L$4=Assumptions_Dashboard!$M$5,(Fleet!L366),0) -> 14.8766 | K15: =IF(Assumptions_Dashboard!$L$4=Assumptions_Dashboard!$M$5,(Fleet!M366),0) -> 108.86268 | L15: =IF(Assumptions_Dashboard!$L$4=Assumptions_Dashboard!$M$5,(Fleet!N366),0) -> 272.02313 | ... AA15: =IF(Assumptions_Dashboard!$L$4=Assumptions_Dashboard!$M$5,(Fleet!AC366),0) -> 0
A16: =A15+1 -> 6 | B16: CHP | C16: INR Cr | D16: =+SUM(E16:AR16) -> 335.19 | E16: ='Capex Breakups'!E4 -> 0 | F16: ='Capex Breakups'!F4 -> 0 | G16: ='Capex Breakups'!G4 -> 11.99 | H16: ='Capex Breakups'!H4 -> 89.7925 | I16: ='Capex Breakups'!I4 -> 155.605 | J16: ='Capex Breakups'!J4 -> 77.8025 | K16: ='Capex Breakups'!K4 -> 0 | L16: ='Capex Breakups'!L4 -> 0 | ... AA16: ='Capex Breakups'!AA4 -> 0
A17: =A16+1 -> 7 | B17: Railway Siding | C17: INR Cr | D17: =+SUM(E17:AR17) -> 540 | E17: ='Capex Breakups'!E5 -> 0 | F17: ='Capex Breakups'!F5 -> 54 | G17: ='Capex Breakups'!G5 -> 324 | H17: ='Capex Breakups'!H5 -> 162 | I17: ='Capex Breakups'!I5 -> 0 | J17: ='Capex Breakups'!J5 -> 0 | K17: ='Capex Breakups'!K5 -> 0 | L17: ='Capex Breakups'!L5 -> 0 | ... AA17: ='Capex Breakups'!AA5 -> 0
A18: =A17+1 -> 8 | B18: Civil Infrastructure | C18: INR Cr | D18: =+SUM(E18:AR18) -> 191 | E18: ='Capex Breakups'!E6 -> 0 | F18: ='Capex Breakups'!F6 -> 57.3 | G18: ='Capex Breakups'!G6 -> 95.5 | H18: ='Capex Breakups'!H6 -> 38.2 | I18: ='Capex Breakups'!I6 -> 0 | J18: ='Capex Breakups'!J6 -> 0 | K18: ='Capex Breakups'!K6 -> 0 | L18: ='Capex Breakups'!L6 -> 0 | ... AA18: ='Capex Breakups'!AA6 -> 0
A19: =A18+1 -> 9 | B19: Fire Fighting & Dust Suppression | C19: INR Cr | D19: =+SUM(E19:AR19) -> 14.45 | E19: ='Capex Breakups'!E7 -> 0 | F19: ='Capex Breakups'!F7 -> 4.335 | G19: ='Capex Breakups'!G7 -> 7.225 | H19: ='Capex Breakups'!H7 -> 2.89 | I19: ='Capex Breakups'!I7 -> 0 | J19: ='Capex Breakups'!J7 -> 0 | K19: ='Capex Breakups'!K7 -> 0 | L19: ='Capex Breakups'!L7 -> 0 | ... AA19: ='Capex Breakups'!AA7 -> 0
A20: =A19+1 -> 10 | B20: ='Project CAPEX'!B20 -> Workshop and Store | C20: INR Cr | D20: =+SUM(E20:AR20) -> 27.27 | E20: =IF(Assumptions_Dashboard!$L$4="Departmental",'Capex Breakups'!E8,0) -> 0 | F20: =IF(Assumptions_Dashboard!$L$4="Departmental",'Capex Breakups'!F8,0) -> 0 | G20: =IF(Assumptions_Dashboard!$L$4="Departmental",'Capex Breakups'!G8,0) -> 13.635 | H20: =IF(Assumptions_Dashboard!$L$4="Departmental",'Capex Breakups'!H8,0) -> 13.635 | I20: =IF(Assumptions_Dashboard!$L$4="Departmental",'Capex Breakups'!I8,0) -> 0 | J20: =IF(Assumptions_Dashboard!$L$4="Departmental",'Capex Breakups'!J8,0) -> 0 | K20: =IF(Assumptions_Dashboard!$L$4="Departmental",'Capex Breakups'!K8,0) -> 0 | L20: =IF(Assumptions_Dashboard!$L$4="Departmental",'Capex Breakups'!L8,0) -> 0 | ... AA20: =IF(Assumptions_Dashboard!$L$4="Departmental",'Capex Breakups'!AA8,0) -> 0
A21: =A20+1 -> 11 | B21: Electrical | C21: INR Cr | D21: =+SUM(E21:AR21) -> 34.35 | E21: ='Capex Breakups'!E9 -> 0 | F21: ='Capex Breakups'!F9 -> 0 | G21: ='Capex Breakups'!G9 -> 0 | H21: ='Capex Breakups'!H9 -> 8.5875 | I21: ='Capex Breakups'!I9 -> 13.74 | J21: ='Capex Breakups'!J9 -> 8.5875 | K21: ='Capex Breakups'!K9 -> 3.435 | L21: ='Capex Breakups'!L9 -> 0 | ... AA21: ='Capex Breakups'!AA9 -> 0
